Workbook

Sheet Operating model
C2: K-UNITY OPERATING MODEL
D3: Fiscal Year Ends | E3: Date | G3: 45261 | H3: =EDATE(G3,12) -> 45627 | I3: =EDATE(H3,12) -> 45992 | J3: Debit | K3: Credit | L3: =I3 -> 45992 | M3: =EDATE(L3,12) -> 46357 | N3: =EDATE(M3,12) -> 46722 | O3: =EDATE(N3,12) -> 47088 | P3: =EDATE(O3,12) -> 47453 | Q3: =EDATE(P3,12) -> 47818 | R3: =EDATE(Q3,12) -> 48183 | S3: =EDATE(R3,12) -> 48549 | T3: =EDATE(S3,12) -> 48914 | ... V3: =EDATE(U3,12) -> 49644
D4: Period Count | E4: Period | G4: =F4+1 -> 1 | H4: =G4+1 -> 2 | I4: =H4+1 -> 3 | M4: =L4+1 -> 1 | N4: =M4+1 -> 2 | O4: =N4+1 -> 3 | P4: =O4+1 -> 4 | Q4: =P4+1 -> 5 | R4: =Q4+1 -> 6 | S4: =R4+1 -> 7 | T4: =S4+1 -> 8 | ... V4: =U4+1 -> 10
D5: Latest Fiscal Year End | E5: Date | F5: =I3 -> 45992
D6: Historical Period Flag | E6: Flag | G6: =IF(ISNUMBER(G3),G3<=$F$5,"N/A") -> TRUE | H6: =IF(ISNUMBER(H3),H3<=$F$5,"N/A") -> TRUE | I6: =IF(ISNUMBER(I3),I3<=$F$5,"N/A") -> TRUE | J6: =IF(ISNUMBER(J3),J3<=$F$5,"N/A") -> N/A | K6: =IF(ISNUMBER(K3),K3<=$F$5,"N/A") -> N/A | L6: =IF(ISNUMBER(L3),L3<=$F$5,"N/A") -> TRUE | M6: =IF(ISNUMBER(M3),M3<=$F$5,"N/A") -> FALSE | N6: =IF(ISNUMBER(N3),N3<=$F$5,"N/A") -> FALSE | ... V6: =IF(ISNUMBER(V3),V3<=$F$5,"N/A") -> FALSE
C8: Balance sheet
C10: =C21 -> loan to members | E10: % Growth | H10: =H21/G21-1 -> 0.12038404 | I10: =I21/H21-1 -> 0.1907882 | L10: =I10 -> 0.1907882 | M10: =L10 -> 0.1907882 | N10: =M10 -> 0.1907882 | O10: =N10 -> 0.1907882 | P10: =O10 -> 0.1907882 | Q10: =P10 -> 0.1907882 | R10: =Q10 -> 0.1907882 | S10: =R10 -> 0.1907882 | T10: =S10 -> 0.1907882 | ... V10: =U10 -> 0.1907882
C11: =C22 -> Prepayments and sundry receivables | E11: % of total Income | G11: =G22/G$77 -> 0.20230598 | H11: =H22/H$77 -> 0.22071099 | I11: =I22/I$77 -> 0.12422854 | L11: =I11 -> 0.12422854 | M11: =AVERAGE(H11:I11) -> 0.17246976 | N11: =M11 -> 0.17246976 | O11: =N11 -> 0.17246976 | P11: =O11 -> 0.17246976 | Q11: =P11 -> 0.17246976 | R11: =Q11 -> 0.17246976 | S11: =R11 -> 0.17246976 | T11: =S11 -> 0.17246976 | U11: =T11 -> 0.17246976 | V11: =U11 -> 0.17246976
C12: =C23 -> Inventories | E12: % of total Income | G12: =G23/G$77 -> 0.0018615807 | H12: =H23/H$77 -> 0.0014246474 | I12: =I23/I$77 -> 0.0014449398 | L12: =I12 -> 0.0014449398 | M12: =AVERAGE(H12:I12) -> 0.0014347936 | N12: =M12 -> 0.0014347936 | O12: =N12 -> 0.0014347936 | P12: =O12 -> 0.0014347936 | Q12: =P12 -> 0.0014347936 | R12: =Q12 -> 0.0014347936 | S12: =R12 -> 0.0014347936 | T12: =S12 -> 0.0014347936 | U12: =T12 -> 0.0014347936 | V12: =U12 -> 0.0014347936
C13: =C24 -> Financial assets | E13: % Growth | H13: =H24/G24-1 -> -0.021995219 | I13: =I24/H24-1 -> 2.8400135 | L13: =I13 -> 2.8400135 | M13: 0 | N13: =M13 -> 0 | O13: =N13 -> 0 | P13: =O13 -> 0 | Q13: =P13 -> 0 | R13: =Q13 -> 0 | S13: =R13 -> 0 | T13: =S13 -> 0 | U13: =T13 -> 0 | V13: =U13 -> 0
C14: =C25 -> Intangible assets | E14: % Growth | H14: =H25/G25-1 -> 2.7883518 | I14: =I25/H25-1 -> -0.21117368 | L14: =I14 -> -0.21117368 | M14: 0 | N14: =M14 -> 0 | O14: =N14 -> 0 | P14: =O14 -> 0 | Q14: =P14 -> 0 | R14: =Q14 -> 0 | S14: =R14 -> 0 | T14: =S14 -> 0 | U14: =T14 -> 0 | V14: =U14 -> 0
C15: =C26 -> Lease improvements | E15: % of total Income | G15: =G26/G$77 -> 0.0099658201 | H15: =H26/H$77 -> 0.0055695317 | I15: =I26/I$77 -> 0.0090039334 | L15: =I15 -> 0.0090039334 | M15: =AVERAGE(H15:I15) -> 0.0072867325 | N15: =M15 -> 0.0072867325 | O15: =N15 -> 0.0072867325 | P15: =O15 -> 0.0072867325 | Q15: =P15 -> 0.0072867325 | R15: =Q15 -> 0.0072867325 | S15: =R15 -> 0.0072867325 | T15: =S15 -> 0.0072867325 | U15: =T15 -> 0.0072867325 | V15: =U15 -> 0.0072867325
C16: =C31 -> Sundry creditors and accruals | E16: % of total Expenses | G16: =-G31/G87 -> 0.23508179 | H16: =-H31/H87 -> 0.16813267 | I16: =-I31/I87 -> 0.26563901 | L16: =I16 -> 0.26563901 | M16: =AVERAGE(H16:I16) -> 0.21688584 | N16: =M16 -> 0.21688584 | O16: =N16 -> 0.21688584 | P16: =O16 -> 0.21688584 | Q16: =P16 -> 0.21688584 | R16: =Q16 -> 0.21688584 | S16: =R16 -> 0.21688584 | T16: =S16 -> 0.21688584 | U16: =T16 -> 0.21688584 | V16: =U16 -> 0.21688584
C17: Member Savings | E17: % Growth | H17: =H33/G33-1 -> 0.11381664 | I17: =I33/H33-1 -> 0.073584693 | L17: =I17 -> 0.073584693 | M17: =L17 -> 0.073584693 | N17: =M17 -> 0.073584693 | O17: =N17 -> 0.073584693 | P17: =O17 -> 0.073584693 | Q17: =P17 -> 0.073584693 | R17: =Q17 -> 0.073584693 | S17: =R17 -> 0.073584693 | T17: =S17 -> 0.073584693 | ... V17: =U17 -> 0.073584693
C20: Cash and Cash equivalents | E20: KSH | G20: =G157 -> 1178618288 | H20: =H157 -> 1757072929 | I20: =I157 -> 1784406362 | L20: =I20+J20-K20 -> 1784406362 | M20: =M157 -> 1.6325371e+09 | N20: =N157 -> 1.4544913e+09 | O20: =O157 -> 1.1577954e+09 | P20: =P157 -> 7.1669509e+08 | Q20: =Q157 -> 1.0028074e+08 | R20: =R157 -> -7.2851534e+08 | S20: =S157 -> -1.8141146e+09 | T20: =T157 -> -3.2097179e+09 | ... V20: =V157 -> -7.1981599e+09
C21: loan to members | E21: KSH | G21: 4100662694 | H21: 4594317024 | I21: 5470858505 | L21: =I21+J21-K21 -> 5470858505 | M21: =L21*(1+M10) -> 6.5146338e+09 | N21: =M21*(1+N10) -> 7.757549e+09 | O21: =N21*(1+O10) -> 9.2375978e+09 | P21: =O21*(1+P10) -> 1.1000023e+10 | Q21: =P21*(1+Q10) -> 1.3098697e+10 | R21: =Q21*(1+R10) -> 1.5597774e+10 | S21: =R21*(1+S10) -> 1.8573645e+10 | T21: =S21*(1+T10) -> 2.2117277e+10 | ... V21: =U21*(1+V10) -> 3.1361781e+10
C22: Prepayments and sundry receivables | E22: KSH | G22: 140773968 | H22: 237371687 | I22: 157893571 | L22: =I22+J22-K22 -> 157893571 | M22: =M11*M$77 -> 2.9402099e+08 | N22: =N11*N$77 -> 3.3172351e+08 | O22: =O11*O$77 -> 3.7695149e+08 | P22: =P11*P$77 -> 4.3116515e+08 | Q22: =Q11*Q$77 -> 4.9610511e+08 | R22: =R11*R$77 -> 5.7384599e+08 | S22: =S11*S$77 -> 6.668603e+08 | T22: =T11*T$77 -> 7.7809453e+08 | ... V22: =V11*V$77 -> 1.0699392e+09
C23: Inventories | E23: KSH | G23: 1295375 | H23: 1532189 | I23: 1836508 | L23: =I23+J23-K23 -> 1836508 | M23: =M12*M$77 -> 2445990.6 | N23: =N12*N$77 -> 2759641.7 | O23: =O12*O$77 -> 3135898 | P23: =P12*P$77 -> 3586907 | Q23: =Q12*Q$77 -> 4127149.1 | R23: =R12*R$77 -> 4773883.4 | S23: =S12*S$77 -> 5547679 | T23: =T12*T$77 -> 6473047.9 | ... V23: =V12*V$77 -> 8900933.6
C24: Financial assets | E24: KSH | G24: 471449217 | H24: 461079588 | I24: 1770551845 | L24: =I24+J24-K24 -> 1770551845 | M24: =L24*(1+M13) -> 1770551845 | N24: =M24*(1+N13) -> 1770551845 | O24: =N24*(1+O13) -> 1770551845 | P24: =O24*(1+P13) -> 1770551845 | Q24: =P24*(1+Q13) -> 1770551845 | R24: =Q24*(1+R13) -> 1770551845 | S24: =R24*(1+S13) -> 1770551845 | T24: =S24*(1+T13) -> 1770551845 | ... V24: =U24*(1+V13) -> 1770551845
C25: Intangible assets | E25: KSH | G25: 7763477 | H25: 29410782 | I25: 23199999 | L25: =I25+J25-K25 -> 23199999 | M25: =L25 -> 23199999 | N25: =M25 -> 23199999 | O25: =N25 -> 23199999 | P25: =O25 -> 23199999 | Q25: =P25 -> 23199999 | R25: =Q25 -> 23199999 | S25: =R25 -> 23199999 | T25: =S25 -> 23199999 | ... V25: =U25 -> 23199999
C26: Lease improvements | E26: KSH | G26: 6934684 | H26: 5989956 | I26: 11443934 | L26: =I26+J26-K26 -> 11443934 | M26: =M15*M$77 -> 12422191 | N26: =N15*N$77 -> 14015097 | O26: =O15*O$77 -> 15925949 | P26: =P15*P$77 -> 18216440 | Q26: =Q15*Q$77 -> 20960110 | R26: =R15*R$77 -> 24244610 | S26: =S15*S$77 -> 28174403 | T26: =T15*T$77 -> 32873975 | ... V26: =V15*V$77 -> 45204218
C27: Investment Property | E27: KSH | G27: 263969021 | H27: 478156447 | I27: 473831903 | L27: =I27+J27-K27 -> 473831903 | M27: =L27 -> 473831903 | N27: =M27 -> 473831903 | O27: =N27 -> 473831903 | P27: =O27 -> 473831903 | Q27: =P27 -> 473831903 | R27: =Q27 -> 473831903 | S27: =R27 -> 473831903 | T27: =S27 -> 473831903 | ... V27: =U27 -> 473831903
C28: PPE | E28: KSH | G28: 38442895 | H28: 45624897 | I28: 44013833 | L28: =I28+J28-K28 -> 44013833 | M28: =L28+(-M131)-M111 -> 44013833 | N28: =M28+(-N131)-N111 -> 44013833 | O28: =N28+(-O131)-O111 -> 44013833 | P28: =O28+(-P131)-P111 -> 44013833 | Q28: =P28+(-Q131)-Q111 -> 44013833 | R28: =Q28+(-R131)-R111 -> 44013833 | S28: =R28+(-S131)-S111 -> 44013833 | T28: =S28+(-T131)-T111 -> 44013833 | ... V28: =U28+(-V131)-V111 -> 44013833
C29: Total assets | E29: KSH | G29: =SUM(G20:G28) -> 6209909619 | H29: =SUM(H20:H28) -> 7610555499 | I29: =SUM(I20:I28) -> 9738036460 | L29: =SUM(L20:L28) -> 9738036460 | M29: =SUM(M20:M28) -> 1.0767658e+10 | N29: =SUM(N20:N28) -> 1.1872136e+10 | O29: =SUM(O20:O28) -> 1.3103004e+10 | P29: =SUM(P20:P28) -> 1.4481284e+10 | Q29: =SUM(Q20:Q28) -> 1.6031768e+10 | R29: =SUM(R20:R28) -> 1.7783721e+10 | S29: =SUM(S20:S28) -> 1.977171e+10 | ... V29: =SUM(V20:V28) -> 2.7599263e+10
C31: Sundry creditors and accruals | E31: KSH | G31: 103108762 | H31: 123072487 | I31: 185278193 | L31: =I31-J31+K31 -> 185278193 | M31: =-M16*M87 -> 2.4515279e+08 | N31: =-N16*N87 -> 2.7658891e+08 | O31: =-O16*O87 -> 3.1429971e+08 | P31: =-P16*P87 -> 3.5950271e+08 | Q31: =-Q16*Q87 -> 4.1364922e+08 | R31: =-R16*R87 -> 4.7846906e+08 | S31: =-S16*S87 -> 5.5602379e+08 | T31: =-T16*T87 -> 6.4877017e+08 | ... V31: =-V16*V87 -> 8.9210837e+08
C32: Deferred tax liabilities | E32: KSH | G32: 10269294 | H32: 5037489 | I32: 76395583 | L32: =I32-J32+K32 -> 76395583 | M32: =L32+M115 -> 76395583 | N32: =M32+N115 -> 76395583 | O32: =N32+O115 -> 76395583 | P32: =O32+P115 -> 76395583 | Q32: =P32+Q115 -> 76395583 | R32: =Q32+R115 -> 76395583 | S32: =R32+S115 -> 76395583 | T32: =S32+T115 -> 76395583 | ... V32: =U32+V115 -> 76395583
C33: Member savings | E33: KSH | G33: 4331518839 | H33: 4824517743 | I33: 5179528400 | L33: =I33-J33+K33 -> 5179528400 | M33: =L33*(1+M17) -> 5.5606624e+09 | N33: =M33*(1+N17) -> 5.969842e+09 | O33: =N33*(1+O17) -> 6.409131e+09 | P33: =O33*(1+P17) -> 6.880745e+09 | Q33: =P33*(1+Q17) -> 7.3870625e+09 | R33: =Q33*(1+R17) -> 7.9306372e+09 | S33: =R33*(1+S17) -> 8.5142107e+09 | T33: =S33*(1+T17) -> 9.1407263e+09 | ... V33: =U33*(1+V17) -> 1.0535456e+10
C34: External borrowings | E34: KSH | G34: 0 | H34: 493150844 | I34: 428588860 | L34: =I34-J34+K34 -> 428588860 | M34: =L34 -> 428588860 | N34: =M34 -> 428588860 | O34: =N34 -> 428588860 | P34: =O34 -> 428588860 | Q34: =P34 -> 428588860 | R34: =Q34 -> 428588860 | S34: =R34 -> 428588860 | T34: =S34 -> 428588860 | ... V34: =U34 -> 428588860
C35: Allowance for loan/debtors Impairment | L35: 0 | M35: =L35+M114 -> 1.9422681e+08 | N35: =M35+N114 -> 4.1335947e+08 | O35: =N35+O114 -> 6.623692e+08 | P35: =O35+P114 -> 9.4719184e+08 | Q35: =P35+Q114 -> 1.2749131e+09 | R35: =Q35+R114 -> 1.653989e+09 | S35: =R35+S114 -> 2.0945091e+09 | T35: =S35+T114 -> 2.6085092e+09 | ... V35: =U35+V114 -> 3.9171338e+09
C36: Total liabilities | E36: KSH | G36: =SUM(G31:G34) -> 4444896895 | H36: =SUM(H31:H34) -> 5445778563 | I36: =SUM(I31:I34) -> 5869791036 | L36: =SUM(L31:L34) -> 5869791036 | M36: =SUM(M31:M35) -> 6.5050265e+09 | N36: =SUM(N31:N35) -> 7.1647749e+09 | O36: =SUM(O31:O35) -> 7.8907844e+09 | P36: =SUM(P31:P35) -> 8.692424e+09 | Q36: =SUM(Q31:Q35) -> 9.5806092e+09 | R36: =SUM(R31:R35) -> 1.056808e+10 | S36: =SUM(S31:S35) -> 1.1669728e+10 | T36: =SUM(T31:T35) -> 1.290299e+10 | ... V36: =SUM(V31:V35) -> 1.5849682e+10
C38: Total equity | E38: KSH | G38: 1765012724 | H38: 2164776961 | I38: 3868245421 | K38: =I42 -> 3 | L38: =I38-J38+K38 -> 3868245424 | M38: =L38+M107+M142+M143 -> 4.2626312e+09 | N38: =M38+N107+N142+N143 -> 4.7073613e+09 | O38: =N38+O107+O142+O143 -> 5.2122198e+09 | P38: =O38+P107+P142+P143 -> 5.7888597e+09 | Q38: =P38+Q107+Q142+Q143 -> 6.4511585e+09 | R38: =Q38+R107+R142+R143 -> 7.2156409e+09 | S38: =R38+S107+S142+S143 -> 8.1019824e+09 | T38: =S38+T107+T142+T143 -> 9.1336085e+09 | ... V38: =U38+V107+V142+V143 -> 1.174958e+10
C40: Total liabilities + Equity | E40: KSH | G40: =G36+G38 -> 6209909619 | H40: =H36+H38 -> 7610555524 | I40: =I36+I38 -> 9738036457 | L40: =L38+L36 -> 9738036460 | M40: =M36+M38 -> 1.0767658e+10 | N40: =N36+N38 -> 1.1872136e+10 | O40: =O36+O38 -> 1.3103004e+10 | P40: =P36+P38 -> 1.4481284e+10 | Q40: =Q36+Q38 -> 1.6031768e+10 | R40: =R36+R38 -> 1.7783721e+10 | S40: =S36+S38 -> 1.977171e+10 | T40: =T36+T38 -> 2.2036599e+10 | ... V40: =V36+V38 -> 2.7599263e+10
C42: Check | G42: =G29-G40 -> 0 | H42: =H29-H40 -> -25 | I42: =I29-I40 -> 3 | L42: =L29-L40 -> 0 | M42: =M29-M40 -> 0 | N42: =N29-N40 -> 0 | O42: =O29-O40 -> 0 | P42: =P29-P40 -> 0 | Q42: =Q29-Q40 -> 0 | R42: =R29-R40 -> 0 | S42: =S29-S40 -> 0 | ... V42: =V29-V40 -> 0
C44: Income Statement
C46: Effective Interest Yield - Loans to Members | E46: EIY | H46: =H65/AVERAGE(G21:H21) -> 0.16953945 | I46: =I65/AVERAGE(H21:I21) -> 0.17132639 | L46: =I46 -> 0.17132639 | M46: =AVERAGE(H46:I46) -> 0.17043292 | N46: =M46 -> 0.17043292 | O46: =N46 -> 0.17043292 | P46: =O46 -> 0.17043292 | Q46: =P46 -> 0.17043292 | R46: =Q46 -> 0.17043292 | S46: =R46 -> 0.17043292 | T46: =S46 -> 0.17043292 | U46: =T46 -> 0.17043292 | V46: =U46 -> 0.17043292
C47: Effective Interest Yield - Financial Investmets | E47: EIY | H47: =H66/AVERAGE(G24:H24) -> 0.37404428 | I47: =I66/AVERAGE(H24:I24) -> 0.18490686 | L47: =I47 -> 0.18490686 | M47: =L47 -> 0.18490686 | N47: =M47 -> 0.18490686 | O47: =N47 -> 0.18490686 | P47: =O47 -> 0.18490686 | Q47: =P47 -> 0.18490686 | R47: =Q47 -> 0.18490686 | S47: =R47 -> 0.18490686 | T47: =S47 -> 0.18490686 | ... V47: =U47 -> 0.18490686
C48: Effective Interest Yield - Interest Expense | E48: EIY | H48: =-H69/AVERAGE(G33:H33) -> 0.03279217 | I48: =-I69/AVERAGE(H33:I33) -> 0.041597012 | L48: =I48 -> 0.041597012 | M48: =L48 -> 0.041597012 | N48: =M48 -> 0.041597012 | O48: =N48 -> 0.041597012 | P48: =O48 -> 0.041597012 | Q48: =P48 -> 0.041597012 | R48: =Q48 -> 0.041597012 | S48: =R48 -> 0.041597012 | T48: =S48 -> 0.041597012 | ... V48: =U48 -> 0.041597012
C49: Other Operating Income | E49: % of Loans to Members | H49: =H72/AVERAGE(G21:H21) -> 0.03996973 | I49: =I72/AVERAGE(H21:I21) -> 0.035140153 | L49: =I49 -> 0.035140153 | M49: =L49 -> 0.035140153 | N49: =M49 -> 0.035140153 | O49: =N49 -> 0.035140153 | P49: =O49 -> 0.035140153 | Q49: =P49 -> 0.035140153 | R49: =Q49 -> 0.035140153 | S49: =R49 -> 0.035140153 | T49: =S49 -> 0.035140153 | ... V49: =U49 -> 0.035140153
C50: Dividend income | E50: % of Financial Assets | H50: =H74/AVERAGE(G24:H24) -> 0.30104604 | I50: =I74/AVERAGE(H24:I24) -> 0.20830442 | L50: =I50 -> 0.20830442 | M50: =L50 -> 0.20830442 | N50: =M50 -> 0.20830442 | O50: =N50 -> 0.20830442 | P50: =O50 -> 0.20830442 | Q50: =P50 -> 0.20830442 | R50: =Q50 -> 0.20830442 | S50: =R50 -> 0.20830442 | T50: =S50 -> 0.20830442 | ... V50: =U50 -> 0.20830442
C52: =D80 -> Governance Expenses | E52: % of Total Income | G52: =-G80/G$77 -> 0.062592447 | H52: =-H80/H$77 -> 0.060656201 | I52: =-I80/I$77 -> 0.03963757 | L52: =I52 -> 0.03963757 | M52: =AVERAGE(G52:I52) -> 0.054295406 | N52: =M52 -> 0.054295406 | O52: =N52 -> 0.054295406 | P52: =O52 -> 0.054295406 | Q52: =P52 -> 0.054295406 | R52: =Q52 -> 0.054295406 | S52: =R52 -> 0.054295406 | T52: =S52 -> 0.054295406 | U52: =T52 -> 0.054295406 | V52: =U52 -> 0.054295406
C53: =D81 -> Administration Expenses | E53: % of Total Income | G53: =-G81/G$77 -> 0.026895397 | H53: =-H81/H$77 -> 0.17043448 | I53: =-I81/I$77 -> 0.13392066 | L53: =I53 -> 0.13392066 | M53: =AVERAGE(H53:I53) -> 0.15217757 | N53: =M53 -> 0.15217757 | O53: =N53 -> 0.15217757 | P53: =O53 -> 0.15217757 | Q53: =P53 -> 0.15217757 | R53: =Q53 -> 0.15217757 | S53: =R53 -> 0.15217757 | T53: =S53 -> 0.15217757 | U53: =T53 -> 0.15217757 | V53: =U53 -> 0.15217757
C54: =D82 -> Financial Expenses | E54: % of Total Income | G54: =-G82/G$77 -> 0.11852632 | H54: =-H82/H$77 -> 0.029607165 | I54: =-I82/I$77 -> 0.039630494 | L54: =I54 -> 0.039630494 | M54: =AVERAGE(H54:I54) -> 0.03461883 | N54: =M54 -> 0.03461883 | O54: =N54 -> 0.03461883 | P54: =O54 -> 0.03461883 | Q54: =P54 -> 0.03461883 | R54: =Q54 -> 0.03461883 | S54: =R54 -> 0.03461883 | T54: =S54 -> 0.03461883 | U54: =T54 -> 0.03461883 | V54: =U54 -> 0.03461883
C55: =D83 -> Marketing and Public Relations | E55: % of Total Income | G55: =-G83/G$77 -> 0.0029509024 | H55: =-H83/H$77 -> 0.019328866 | I55: =-I83/I$77 -> 0.019426424 | L55: =I55 -> 0.019426424 | M55: =AVERAGE(H55:I55) -> 0.019377645 | N55: =M55 -> 0.019377645 | O55: =N55 -> 0.019377645 | P55: =O55 -> 0.019377645 | Q55: =P55 -> 0.019377645 | R55: =Q55 -> 0.019377645 | S55: =R55 -> 0.019377645 | T55: =S55 -> 0.019377645 | U55: =T55 -> 0.019377645 | V55: =U55 -> 0.019377645
C56: =D84 -> Personnel Expenses | E56: % of Total Income | G56: =-G84/G$77 -> 0.22730062 | H56: =-H84/H$77 -> 0.26651376 | I56: =-I84/I$77 -> 0.23158307 | L56: =I56 -> 0.23158307 | M56: =AVERAGE(H56:I56) -> 0.24904841 | N56: =M56 -> 0.24904841 | O56: =N56 -> 0.24904841 | P56: =O56 -> 0.24904841 | Q56: =P56 -> 0.24904841 | R56: =Q56 -> 0.24904841 | S56: =R56 -> 0.24904841 | T56: =S56 -> 0.24904841 | U56: =T56 -> 0.24904841 | V56: =U56 -> 0.24904841
C57: =D85 -> Allowance of Asset Impairment | E57: % of Total Income | G57: =-G85/G$77 -> 0.0043050942 | H57: =-H85/H$77 -> 0.025014752 | I57: =-I85/I$77 -> 0.039591475 | L57: =I57 -> 0.039591475 | M57: =L57 -> 0.039591475 | N57: =M57 -> 0.039591475 | O57: =N57 -> 0.039591475 | P57: =O57 -> 0.039591475 | Q57: =P57 -> 0.039591475 | R57: =Q57 -> 0.039591475 | S57: =R57 -> 0.039591475 | T57: =S57 -> 0.039591475 | ... V57: =U57 -> 0.039591475
C58: =D86 -> Allowance for loan/debtors Impairment | E58: % of Total Income | G58: =-G86/G$77 -> 0.18775192 | H58: =-H86/H$77 -> 0.10906351 | I58: =-I86/I$77 -> 0.044979073 | L58: =I58 -> 0.044979073 | M58: =AVERAGE(G58:I58) -> 0.1139315 | N58: =M58 -> 0.1139315 | O58: =N58 -> 0.1139315 | P58: =O58 -> 0.1139315 | Q58: =P58 -> 0.1139315 | R58: =Q58 -> 0.1139315 | S58: =R58 -> 0.1139315 | T58: =S58 -> 0.1139315 | U58: =T58 -> 0.1139315 | V58: =U58 -> 0.1139315
C59: =D87 -> Total Expenses | E59: % of Total Income | G59: =-G87/G$77 -> 0.6303227 | H59: =-H87/H$77 -> 0.68061874 | I59: =-I87/I$77 -> 0.54876877 | L59: =I59 -> 0.54876877 | M59: =-M87/M$77 -> 0.66304084 | N59: =-N87/N$77 -> 0.66304084 | O59: =-O87/O$77 -> 0.66304084 | P59: =-P87/P$77 -> 0.66304084 | Q59: =-Q87/Q$77 -> 0.66304084 | R59: =-R87/R$77 -> 0.66304084 | S59: =-S87/S$77 -> 0.66304084 | T59: =-T87/T$77 -> 0.66304084 | ... V59: =-V87/V$77 -> 0.66304084
C60: =D88 -> 0
C61: Effective Tax Rate | E61: % of Pretax Income | G61: =-G90/G89 -> 0.36817859 | H61: =-H90/H89 -> 0.25672967 | I61: =-I90/I89 -> 0.27585843 | L61: =I61 -> 0.27585843 | M61: =AVERAGE(H61:I61) -> 0.26629405 | N61: =M61 -> 0.26629405 | O61: =N61 -> 0.26629405 | P61: =O61 -> 0.26629405 | Q61: =P61 -> 0.26629405 | R61: =Q61 -> 0.26629405 | S61: =R61 -> 0.26629405 | T61: =S61 -> 0.26629405 | U61: =T61 -> 0.26629405 | V61: =U61 -> 0.26629405
C62: Net Margin | E62: % of Total Income | G62: =G91/G77 -> 0.23357003 | H62: =H91/H77 -> 0.23738662 | I62: =I91/I77 -> 0.32675529 | L62: =I62 -> 0.32675529 | M62: =M91/M77 -> 0.24722894 | N62: =N91/N77 -> 0.24722894 | O62: =O91/O77 -> 0.24722894 | P62: =P91/P77 -> 0.24722894 | Q62: =Q91/Q77 -> 0.24722894 | R62: =R91/R77 -> 0.24722894 | S62: =S91/S77 -> 0.24722894 | T62: =T91/T77 -> 0.24722894 | ... V62: =V91/V77 -> 0.24722894
C64: Revenue
D65: Interest from loans and advances | E65: KSH | G65: 625696835 | H65: 737071049 | I65: 862215114 | L65: =I65 -> 862215114 | M65: =M46*(AVERAGE(L21:M21)) -> 1.0213612e+09 | N65: =N46*(AVERAGE(M21:N21)) -> 1.2162249e+09 | O65: =O46*(AVERAGE(N21:O21)) -> 1.4482663e+09 | P65: =P46*(AVERAGE(O21:P21)) -> 1.7245784e+09 | Q65: =Q46*(AVERAGE(P21:Q21)) -> 2.0536076e+09 | R65: =R46*(AVERAGE(Q21:R21)) -> 2.4454117e+09 | S65: =S46*(AVERAGE(R21:S21)) -> 2.9119674e+09 | T65: =T46*(AVERAGE(S21:T21)) -> 3.4675364e+09 | ... V65: =V46*(AVERAGE(U21:V21)) -> 4.9168853e+09
D66: Interest Income from Financial Investment | E66: KSH | G66: 87492386 | H66: 174403535 | I66: 206321981 | L66: =I66 -> 206321981 | M66: =M47*(AVERAGE(L24:M24)) -> 3.2738718e+08 | N66: =N47*(AVERAGE(M24:N24)) -> 3.2738718e+08 | O66: =O47*(AVERAGE(N24:O24)) -> 3.2738718e+08 | P66: =P47*(AVERAGE(O24:P24)) -> 3.2738718e+08 | Q66: =Q47*(AVERAGE(P24:Q24)) -> 3.2738718e+08 | R66: =R47*(AVERAGE(Q24:R24)) -> 3.2738718e+08 | S66: =S47*(AVERAGE(R24:S24)) -> 3.2738718e+08 | T66: =T47*(AVERAGE(S24:T24)) -> 3.2738718e+08 | ... V66: =V47*(AVERAGE(U24:V24)) -> 3.2738718e+08
D67: Total Interest | E67: KSH | G67: =SUM(G65:G66) -> 713189221 | H67: =SUM(H65:H66) -> 911474584 | I67: =SUM(I65:I66) -> 1068537095 | L67: =I67 -> 1068537095 | M67: =SUM(M65:M66) -> 1.3487484e+09 | N67: =SUM(N65:N66) -> 1.5436121e+09 | O67: =SUM(O65:O66) -> 1.7756535e+09 | P67: =SUM(P65:P66) -> 2.0519656e+09 | Q67: =SUM(Q65:Q66) -> 2.3809948e+09 | R67: =SUM(R65:R66) -> 2.7727989e+09 | S67: =SUM(S65:S66) -> 3.2393546e+09 | T67: =SUM(T65:T66) -> 3.7949236e+09 | ... V67: =SUM(V65:V66) -> 5.2442725e+09
D69: Interest Expense | E69: KSH | G69: -127796333 | H69: -150123154 | I69: -208069216 | L69: =I69 -> -208069216 | M69: =-M48*AVERAGE(L33:M33) -> -2.2337993e+08 | N69: =-N48*AVERAGE(M33:N33) -> -2.3981727e+08 | O69: =-O48*AVERAGE(N33:O33) -> -2.5746415e+08 | P69: =-P48*AVERAGE(O33:P33) -> -2.7640957e+08 | Q69: =-Q48*AVERAGE(P33:Q33) -> -2.9674908e+08 | R69: =-R48*AVERAGE(Q33:R33) -> -3.1858527e+08 | S69: =-S48*AVERAGE(R33:S33) -> -3.4202827e+08 | T69: =-T48*AVERAGE(S33:T33) -> -3.6719632e+08 | ... V69: =-V48*AVERAGE(U33:V33) -> -4.2322463e+08
D70: Net Interest Income | E70: KSH | G70: =SUM(G67:G69) -> 585392888 | H70: =SUM(H67:H69) -> 761351430 | I70: =SUM(I67:I69) -> 860467879 | L70: =I70 -> 860467879 | M70: =SUM(M67:M69) -> 1.1253685e+09 | N70: =SUM(N67:N69) -> 1.3037948e+09 | O70: =SUM(O67:O69) -> 1.5181893e+09 | P70: =SUM(P67:P69) -> 1.775556e+09 | Q70: =SUM(Q67:Q69) -> 2.0842457e+09 | R70: =SUM(R67:R69) -> 2.4542136e+09 | S70: =SUM(S67:S69) -> 2.8973263e+09 | T70: =SUM(T67:T69) -> 3.4277273e+09 | ... V70: =SUM(V67:V69) -> 4.8210479e+09
D72: Other Operating Income | E72: KSH | G72: =(134334461-23880549)-G74 -> -37550343 | H72: 173767998 | I72: 176845905 | L72: =I72 -> 176845905 | M72: =M49*AVERAGE(L21:M21) -> 2.1058602e+08 | N72: =N49*AVERAGE(M21:N21) -> 2.5076334e+08 | O72: =O49*AVERAGE(N21:O21) -> 2.9860603e+08 | P72: =P49*AVERAGE(O21:P21) -> 3.5557654e+08 | Q72: =Q49*AVERAGE(P21:Q21) -> 4.2341635e+08 | R72: =R49*AVERAGE(Q21:R21) -> 5.0419919e+08 | S72: =S49*AVERAGE(R21:S21) -> 6.0039445e+08 | T72: =T49*AVERAGE(S21:T21) -> 7.1494263e+08 | ... V72: =V49*AVERAGE(U21:V21) -> 1.0137719e+09
D73: Gain on asset disposal | E73: KSH | G73: 0 | H73: 0 | I73: 1249616 | L73: =I73 -> 1249616 | M73: 0 | N73: 0 | O73: 0 | P73: 0 | Q73: 0 | R73: 0 | S73: 0 | T73: 0 | U73: 0 | V73: 0
D74: Dividend incomes | E74: KSH | G74: 148004255 | H74: 140367051 | I74: 232429343 | L74: =I74 -> 232429343 | M74: =M50*AVERAGE(L24:M24) -> 3.6881377e+08 | N74: =N50*AVERAGE(M24:N24) -> 3.6881377e+08 | O74: =O50*AVERAGE(N24:O24) -> 3.6881377e+08 | P74: =P50*AVERAGE(O24:P24) -> 3.6881377e+08 | Q74: =Q50*AVERAGE(P24:Q24) -> 3.6881377e+08 | R74: =R50*AVERAGE(Q24:R24) -> 3.6881377e+08 | S74: =S50*AVERAGE(R24:S24) -> 3.6881377e+08 | T74: =T50*AVERAGE(S24:T24) -> 3.6881377e+08 | ... V74: =V50*AVERAGE(U24:V24) -> 3.6881377e+08
D75: Total other income | E75: KSH | G75: =SUM(G72:G74) -> 110453912 | H75: =SUM(H72:H74) -> 314135049 | I75: =SUM(I72:I74) -> 410524864 | L75: =I75 -> 410524864 | M75: =SUM(M72:M74) -> 5.7939979e+08 | N75: =SUM(N72:N74) -> 6.1957712e+08 | O75: =SUM(O72:O74) -> 6.674198e+08 | P75: =SUM(P72:P74) -> 7.2439031e+08 | Q75: =SUM(Q72:Q74) -> 7.9223012e+08 | R75: =SUM(R72:R74) -> 8.7301296e+08 | S75: =SUM(S72:S74) -> 9.6920822e+08 | T75: =SUM(T72:T74) -> 1.0837564e+09 | ... V75: =SUM(V72:V74) -> 1.3825856e+09
D77: Total Income | E77: KSH | G77: =G70+G75 -> 695846800 | H77: =H70+H75 -> 1075486479 | I77: =I70+I75 -> 1270992743 | L77: =L70+L75 -> 1270992743 | M77: =M70+M75 -> 1.7047683e+09 | N77: =N70+N75 -> 1.9233719e+09 | O77: =O70+O75 -> 2.1856091e+09 | P77: =P70+P75 -> 2.4999463e+09 | Q77: =Q70+Q75 -> 2.8764758e+09 | R77: =R70+R75 -> 3.3272266e+09 | S77: =S70+S75 -> 3.8665345e+09 | ... V77: =V70+V75 -> 6.2036335e+09
C79: Expenses
D80: Governance Expenses | E80: KSH | G80: -43554754 | H80: -65234924 | I80: ='2025 Data'!H77 -> -50379064 | L80: =I80 -> -50379064 | M80: =-M52*M$77 -> -92561086 | N80: =-N52*N$77 -> -1.0443026e+08 | O80: =-O52*O$77 -> -1.1866853e+08 | P80: =-P52*P$77 -> -1.357356e+08 | Q80: =-Q52*Q$77 -> -1.5617942e+08 | R80: =-R52*R$77 -> -1.8065312e+08 | S80: =-S52*S$77 -> -2.0993506e+08 | T80: =-T52*T$77 -> -2.4495284e+08 | ... V80: =-V52*V$77 -> -3.368288e+08
D81: Administration Expenses | E81: KSH | G81: -18715076 | H81: -183299974 | I81: -170212192 | L81: =I81 -> -170212192 | M81: =-M53*M$77 -> -2.5942749e+08 | N81: =-N53*N$77 -> -2.9269407e+08 | O81: =-O53*O$77 -> -3.3260068e+08 | P81: =-P53*P$77 -> -3.8043576e+08 | Q81: =-Q53*Q$77 -> -4.377351e+08 | R81: =-R53*R$77 -> -5.0632926e+08 | S81: =-S53*S$77 -> -5.8839983e+08 | T81: =-T53*T$77 -> -6.8654662e+08 | ... V81: =-V53*V$77 -> -9.4405387e+08
D82: Financial Expenses | E82: KSH | G82: -82476161 | H82: -31842106 | I82: -50370070 | L82: =I82 -> -50370070 | M82: =-M54*M$77 -> -59017083 | N82: =-N54*N$77 -> -66584886 | O82: =-O54*O$77 -> -75663229 | P82: =-P54*P$77 -> -86545216 | Q82: =-Q54*Q$77 -> -99580226 | R82: =-R54*R$77 -> -1.1518469e+08 | S82: =-S54*S$77 -> -1.338549e+08 | T82: =-T54*T$77 -> -1.5618229e+08 | ... V82: =-V54*V$77 -> -2.1476253e+08
D83: Marketing and Public Relations | E83: KSH | G83: -2053376 | H83: -20787934 | I83: -24690844 | L83: =I83 -> -24690844 | M83: =-M55*M$77 -> -33034395 | N83: =-N55*N$77 -> -37270419 | O83: =-O55*O$77 -> -42351958 | P83: =-P55*P$77 -> -48443072 | Q83: =-Q55*Q$77 -> -55739327 | R83: =-R55*R$77 -> -64473816 | S83: =-S55*S$77 -> -74924334 | T83: =-T55*T$77 -> -87421930 | ... V83: =-V55*V$77 -> -1.2021181e+08
D84: Personnel Expenses | E84: KSH | G84: -158166409 | H84: -286631948 | I84: -294340396 | L84: =I84 -> -294340396 | M84: =-M56*M$77 -> -4.2456984e+08 | N84: =-N56*N$77 -> -4.7901273e+08 | O84: =-O56*O$77 -> -5.4432248e+08 | P84: =-P56*P$77 -> -6.2260767e+08 | Q84: =-Q56*Q$77 -> -7.1638174e+08 | R84: =-R56*R$77 -> -8.286405e+08 | S84: =-S56*S$77 -> -9.629543e+08 | T84: =-T56*T$77 -> -1.1235779e+09 | ... V84: =-V56*V$77 -> -1.5450051e+09
D85: Allowance of Asset Impairment | E85: KSH | G85: -2995686 | H85: -26903028 | I85: -50320477 | L85: =I85 -> -50320477 | M85: =-M57*M$77 -> -67494290 | N85: =-N57*N$77 -> -76149132 | O85: =-O57*O$77 -> -86531488 | P85: =-P57*P$77 -> -98976561 | Q85: =-Q57*Q$77 -> -1.1388392e+08 | R85: =-R57*R$77 -> -1.3172981e+08 | S85: =-S57*S$77 -> -1.530818e+08 | T85: =-T57*T$77 -> -1.7861629e+08 | ... V85: =-V57*V$77 -> -2.45611e+08
D86: Allowance for loan/debtors Impairment | E86: KSH | G86: -130646575 | H86: -117296333 | I86: -57168076 | L86: =I86 -> -57168076 | M86: =-M58*M$77 -> -1.9422681e+08 | N86: =-N58*N$77 -> -2.1913266e+08 | O86: =-O58*O$77 -> -2.4900973e+08 | P86: =-P58*P$77 -> -2.8482264e+08 | Q86: =-Q58*Q$77 -> -3.2772121e+08 | R86: =-R58*R$77 -> -3.7907593e+08 | S86: =-S58*S$77 -> -4.4052009e+08 | T86: =-T58*T$77 -> -5.1400012e+08 | ... V86: =-V58*V$77 -> -7.0678929e+08
D87: Total Expenses | E87: KSH | G87: =SUM(G80:G86) -> -438608037 | H87: =SUM(H80:H86) -> -731996247 | I87: =SUM(I80:I86) -> -697481119 | L87: =I87 -> -697481119 | M87: =SUM(M80:M86) -> -1.130331e+09 | N87: =SUM(N80:N86) -> -1.2752742e+09 | O87: =SUM(O80:O86) -> -1.4491481e+09 | P87: =SUM(P80:P86) -> -1.6575665e+09 | Q87: =SUM(Q80:Q86) -> -1.907221e+09 | R87: =SUM(R80:R86) -> -2.2060871e+09 | S87: =SUM(S80:S86) -> -2.5636703e+09 | T87: =SUM(T80:T86) -> -2.9912979e+09 | ... V87: =SUM(V80:V86) -> -4.1132624e+09
D89: Net Surplus before tax | E89: KSH | G89: =G77+G87 -> 257238763 | H89: =H77+H87 -> 343490232 | I89: =I77+I87 -> 573511624 | L89: =I89 -> 573511624 | M89: =M77+M87 -> 5.7443729e+08 | N89: =N77+N87 -> 6.4809779e+08 | O89: =O77+O87 -> 7.3646101e+08 | P89: =P77+P87 -> 8.4237981e+08 | Q89: =Q77+Q87 -> 9.6925487e+08 | R89: =R77+R87 -> 1.1211395e+09 | S89: =S77+S87 -> 1.3028642e+09 | T89: =T77+T87 -> 1.5201857e+09 | ... V89: =V77+V87 -> 2.0903711e+09
D90: Income tax expense | E90: KSH | G90: -94709805 | H90: -88184135 | I90: -158208018 | L90: =I90 -> -158208018 | M90: =-M89*M61 -> -1.5296923e+08 | N90: =-N89*N61 -> -1.7258459e+08 | O90: =-O89*O61 -> -1.9611519e+08 | P90: =-P89*P61 -> -2.2432073e+08 | Q90: =-Q89*Q61 -> -2.5810681e+08 | R90: =-R89*R61 -> -2.9855277e+08 | S90: =-S89*S61 -> -3.4694499e+08 | T90: =-T89*T61 -> -4.0481642e+08 | ... V90: =-V89*V61 -> -5.566534e+08
D91: Net Operating surplus after tax | E91: KSH | G91: =SUM(G89:G90) -> 162528958 | H91: =SUM(H89:H90) -> 255306097 | I91: =SUM(I89:I90) -> 415303606 | L91: =I91 -> 415303606 | M91: =SUM(M89:M90) -> 4.2146805e+08 | N91: =SUM(N89:N90) -> 4.755132e+08 | O91: =SUM(O89:O90) -> 5.4034582e+08 | P91: =SUM(P89:P90) -> 6.1805907e+08 | Q91: =SUM(Q89:Q90) -> 7.1114806e+08 | R91: =SUM(R89:R90) -> 8.2258669e+08 | S91: =SUM(S89:S90) -> 9.5591923e+08 | T91: =SUM(T89:T90) -> 1.1153693e+09 | ... V91: =SUM(V89:V90) -> 1.5337177e+09
C93: Other Comprehensive Incomes
D94: Gain/loss on PPE Revaluation | E94: KSH | G94: 0 | H94: 222122523 | I94: 2383814 | L94: =I94 -> 2383814 | M94: 0 | N94: 0 | O94: 0 | P94: 0 | Q94: 0 | R94: 0 | S94: 0 | T94: 0 | U94: 0 | V94: 0
D95: Gain/loss on Equity Instrument | E95: KSH | G95: 0 | H95: 6031263 | I95: 1328827311 | L95: =I95 -> 1328827311 | M95: 0 | N95: 0 | O95: 0 | P95: 0 | Q95: 0 | R95: 0 | S95: 0 | T95: 0 | U95: 0 | V95: 0
D96: Total Comprehensive Income | E96: KSH | G96: =SUM(G91:G95) -> 162528958 | H96: =SUM(H91:H95) -> 483459883 | I96: =SUM(I91:I95) -> 1746514731 | L96: =I96 -> 1746514731 | M96: =SUM(M91:M95) -> 4.2146805e+08 | N96: =SUM(N91:N95) -> 4.755132e+08 | O96: =SUM(O91:O95) -> 5.4034582e+08 | P96: =SUM(P91:P95) -> 6.1805907e+08 | Q96: =SUM(Q91:Q95) -> 7.1114806e+08 | R96: =SUM(R91:R95) -> 8.2258669e+08 | S96: =SUM(S91:S95) -> 9.5591923e+08 | T96: =SUM(T91:T95) -> 1.1153693e+09 | ... V96: =SUM(V91:V95) -> 1.5337177e+09
C98: Cashflow statement
B100: Depreciation | E100: % of Total Income | G100: =G111/G$77 -> 0.023797081 | H100: =H111/H$77 -> 0.024329549 | I100: =I111/I$77 -> 0.018823584 | L100: =I100 -> 0.018823584 | M100: 0.02 | N100: =M100 -> 0.02 | O100: =N100 -> 0.02 | P100: =O100 -> 0.02 | Q100: =P100 -> 0.02 | R100: =Q100 -> 0.02 | S100: =R100 -> 0.02 | T100: =S100 -> 0.02 | U100: =T100 -> 0.02 | V100: =U100 -> 0.02
B101: =D131 -> Purchase of fixed assets | E101: % of Total Income | G101: =-G131/G$77 -> 0.018507143 | H101: =-H131/H$77 -> 0.016323361 | I101: =-I131/I$77 -> 0.0065376306 | L101: =I101 -> 0.0065376306 | M101: 0.02 | N101: =M101 -> 0.02 | O101: =N101 -> 0.02 | P101: =O101 -> 0.02 | Q101: =P101 -> 0.02 | R101: =Q101 -> 0.02 | S101: =R101 -> 0.02 | T101: =S101 -> 0.02 | U101: =T101 -> 0.02 | V101: =U101 -> 0.02
B103: Members share contribution | E103: % Growth | H103: =H143/G143-1 -> -0.36709895 | I103: =I143/H143-1 -> 0.46632802 | L103: =I103 -> 0.46632802 | M103: 0.12 | N103: =M103 -> 0.12 | O103: =N103 -> 0.12 | P103: =O103 -> 0.12 | Q103: =P103 -> 0.12 | R103: =Q103 -> 0.12 | S103: =R103 -> 0.12 | T103: =S103 -> 0.12 | U103: =T103 -> 0.12 | V103: =U103 -> 0.12
B104: Dividends Paid | E104: % of Net Income | G104: =-G142/G107 -> 0.35102854 | H104: =-H142/H107 -> 0.27258219 | I104: =-I142/I107 -> 0.15201215 | L104: =I104 -> 0.15201215 | M104: 0.13 | N104: =M104 -> 0.13 | O104: =N104 -> 0.13 | P104: =O104 -> 0.13 | Q104: =P104 -> 0.13 | R104: =Q104 -> 0.13 | S104: =R104 -> 0.13 | T104: =S104 -> 0.13 | U104: =T104 -> 0.13 | V104: =U104 -> 0.13
B106: Operating activities
C107: Net Income | E107: KSH | G107: =G91 -> 162528958 | H107: =H91 -> 255306097 | I107: =I91 -> 415303606 | L107: =I107 -> 415303606 | M107: =M91 -> 4.2146805e+08 | N107: =N91 -> 4.755132e+08 | O107: =O91 -> 5.4034582e+08 | P107: =P91 -> 6.1805907e+08 | Q107: =Q91 -> 7.1114806e+08 | R107: =R91 -> 8.2258669e+08 | S107: =S91 -> 9.5591923e+08 | T107: =T91 -> 1.1153693e+09 | ... V107: =V91 -> 1.5337177e+09
C108: Allowance for asset impairment
D109: Bad debt written off | E109: KSH | G109: 0 | H109: 0 | I109: 5217191 | L109: =I109 -> 5217191 | M109: 0 | N109: 0 | O109: 0 | P109: 0 | Q109: 0 | R109: 0 | S109: 0 | T109: 0 | U109: 0 | V109: 0
D110: Impairement of KUSSCO (Financial asset) | E110: KSH | G110: 0 | H110: 736927 | I110: 21178647 | L110: =I110 -> 21178647 | M110: 0 | N110: 0 | O110: 0 | P110: 0 | Q110: 0 | R110: 0 | S110: 0 | T110: 0 | U110: 0 | V110: 0
D111: Depreciation | E111: KSH | G111: =182860860-SUM(G107:G110,G112:G115) -> 16559123 | H111: 26166101 | I111: 23924639 | L111: =I111 -> 23924639 | M111: =M100*M77 -> 34095366 | N111: =N100*N77 -> 38467439 | O111: =O100*O77 -> 43712182 | P111: =P100*P77 -> 49998926 | Q111: =Q100*Q77 -> 57529517 | R111: =R100*R77 -> 66544532 | S111: =S100*S77 -> 77330691 | T111: =T100*T77 -> 90229674 | ... V111: =V100*V77 -> 1.2407267e+08
C112: Dividend income adjustment | E112: KSH | G112: =-G74 -> -148004255 | H112: =-H74 -> -140367051 | I112: =-I74 -> -232429343 | L112: =I112 -> -232429343 | M112: =-M74 -> -3.6881377e+08 | N112: =-N74 -> -3.6881377e+08 | O112: =-O74 -> -3.6881377e+08 | P112: =-P74 -> -3.6881377e+08 | Q112: =-Q74 -> -3.6881377e+08 | R112: =-R74 -> -3.6881377e+08 | S112: =-S74 -> -3.6881377e+08 | T112: =-T74 -> -3.6881377e+08 | ... V112: =-V74 -> -3.6881377e+08
C113: Gain on asset disposal adjustment | E113: KSH | G113: =-G73 -> 0 | H113: =-H73 -> 0 | I113: =-I73 -> -1249616 | L113: =I113 -> -1249616 | M113: =-M73 -> 0 | N113: =-N73 -> 0 | O113: =-O73 -> 0 | P113: =-P73 -> 0 | Q113: =-Q73 -> 0 | R113: =-R73 -> 0 | S113: =-S73 -> 0 | T113: =-T73 -> 0 | ... V113: =-V73 -> 0
C114: Allowance of loans impairement | E114: KSH | G114: =-G86 -> 130646575 | H114: =-H86 -> 117296333 | I114: =-I86 -> 57168076 | L114: =I114 -> 57168076 | M114: =-M86 -> 1.9422681e+08 | N114: =-N86 -> 2.1913266e+08 | O114: =-O86 -> 2.4900973e+08 | P114: =-P86 -> 2.8482264e+08 | Q114: =-Q86 -> 3.2772121e+08 | R114: =-R86 -> 3.7907593e+08 | S114: =-S86 -> 4.4052009e+08 | T114: =-T86 -> 5.1400012e+08 | ... V114: =-V86 -> 7.0678929e+08
C115: Deffered income taxes | E115: KSH | G115: =-(G90--73579346) -> 21130459 | H115: =-(H90--110024342) -> -21840207 | I115: =-(I90--91409349) -> 66798669 | L115: =I115 -> 66798669 | M115: 0 | N115: 0 | O115: 0 | P115: 0 | Q115: 0 | R115: 0 | S115: 0 | T115: 0 | U115: 0 | V115: 0
C117: Increase / decrease in Operating Assets and Liabilities | E117: KSH | G117: =SUM(G118:G123) -> -48179603 | H117: =SUM(H118:H123) -> -192339017 | I117: =SUM(I118:I123) -> -468879528 | L117: =I117 -> -468879528 | M117: =SUM(M118:M123) -> -7.404818e+08 | N117: =SUM(N118:N123) -> -8.4190858e+08 | O117: =SUM(O118:O123) -> -1.0505641e+09 | P117: =SUM(P118:P123) -> -1.3025629e+09 | Q117: =SUM(Q118:Q123) -> -1.6064344e+09 | R117: =SUM(R118:R123) -> -1.9723544e+09 | S117: =SUM(S118:S123) -> -2.4124609e+09 | T117: =SUM(T118:T123) -> -2.9412295e+09 | ... V117: =SUM(V118:V123) -> -4.3371167e+09
C118: Net change in loans to member | E118: KSH | G118: -362736631 | H118: -456540633 | I118: -927682894 | L118: =I118 -> -927682894 | M118: =L21-M21 -> -1.0437753e+09 | N118: =M21-N21 -> -1.2429153e+09 | O118: =N21-O21 -> -1.4800488e+09 | P118: =O21-P21 -> -1.7624247e+09 | Q118: =P21-Q21 -> -2.0986745e+09 | R118: =Q21-R21 -> -2.4990768e+09 | S118: =R21-S21 -> -2.9758712e+09 | T118: =S21-T21 -> -3.5436323e+09 | ... V118: =U21-V21 -> -5.0247875e+09
C119: Net change in debtors and prepayments | E119: KSH | G119: -45080317 | H119: -96587719 | I119: 50079475 | L119: =I119 -> 50079475 | M119: =L22-M22 -> -1.3612741e+08 | N119: =M22-N22 -> -37702522 | O119: =N22-O22 -> -45227983 | P119: =O22-P22 -> -54213664 | Q119: =P22-Q22 -> -64939955 | R119: =Q22-R22 -> -77740877 | S119: =R22-S22 -> -93014317 | T119: =S22-T22 -> -1.1123423e+08 | ... V119: =U22-V22 -> -1.5887952e+08
C120: net change in inventories | E120: KSH | G120: -36390 | H120: -236813 | I120: -304319 | L120: =I120 -> -304319 | M120: =L23-M23 -> -609482.61 | N120: =M23-N23 -> -313651.13 | O120: =N23-O23 -> -376256.21 | P120: =O23-P23 -> -451009.01 | Q120: =P23-Q23 -> -540242.12 | R120: =Q23-R23 -> -646734.29 | S120: =R23-S23 -> -773795.6 | T120: =S23-T23 -> -925368.92 | ... V120: =U23-V23 -> -1321735
C121: Additional in lease improvement | E121: KSH | G121: 0 | H121: 0 | I121: -8188154 | L121: =I121 -> -8188154 | M121: =L26-M26 -> -978256.52 | N121: =M26-N26 -> -1592906.4 | O121: =N26-O26 -> -1910852.1 | P121: =O26-P26 -> -2290491.1 | Q121: =P26-Q26 -> -2743669.8 | R121: =Q26-R26 -> -3284500.2 | S121: =R26-S26 -> -3929792.8 | T121: =S26-T26 -> -4699572 | ... V121: =U26-V26 -> -6712553.9
C122: Net change in sundry creditors and accruals | E122: KSH | G122: 33734683 | H122: 19963724 | I122: 62205707 | L122: =I122 -> 62205707 | M122: =M31-L31 -> 59874597 | N122: =N31-M31 -> 31436118 | O122: =O31-N31 -> 37710799 | P122: =P31-O31 -> 45203001 | Q122: =Q31-P31 -> 54146513 | R122: =R31-Q31 -> 64819839 | S122: =S31-R31 -> 77554734 | T122: =T31-S31 -> 92746379 | ... V122: =V31-U31 -> 1.3247272e+08
C123: Net change in members deposits | E123: KSH | G123: 325939052 | H123: 341062424 | I123: 355010657 | L123: =I123 -> 355010657 | M123: =M33-L33 -> 3.8113401e+08 | N123: =N33-M33 -> 4.0917964e+08 | O123: =O33-N33 -> 4.3928899e+08 | P123: =P33-O33 -> 4.7161394e+08 | Q123: =Q33-P33 -> 5.0631751e+08 | R123: =R33-Q33 -> 5.4357473e+08 | S123: =S33-R33 -> 5.835735e+08 | T123: =T33-S33 -> 6.2651558e+08 | ... V123: =V33-U33 -> 7.2211189e+08
C125: Total Operating Cashflows | E125: KSH | G125: =SUM(G107:G117) -> 134681257 | H125: =SUM(H107:H117) -> 44959183 | I125: =SUM(I107:I117) -> -112967659 | L125: =I125 -> -112967659 | M125: =SUM(M107:M117) -> -4.5950534e+08 | N125: =SUM(N107:N117) -> -4.7760905e+08 | O125: =SUM(O107:O117) -> -5.8631016e+08 | P125: =SUM(P107:P117) -> -7.1849603e+08 | Q125: =SUM(Q107:Q117) -> -8.7884933e+08 | R125: =SUM(R107:R117) -> -1.072961e+09 | S125: =SUM(S107:S117) -> -1.3075046e+09 | T125: =SUM(T107:T117) -> -1.5904442e+09 | ... V125: =SUM(V107:V117) -> -2.3413508e+09
...

Sheet DDM
C2: Dividend Discount Model
F3: ='Operating model'!L3 -> 45992 | G3: ='Operating model'!M3 -> 46357 | H3: ='Operating model'!N3 -> 46722 | I3: ='Operating model'!O3 -> 47088 | J3: ='Operating model'!P3 -> 47453 | K3: ='Operating model'!Q3 -> 47818 | L3: ='Operating model'!R3 -> 48183 | M3: ='Operating model'!S3 -> 48549 | ... P3: ='Operating model'!V3 -> 49644
D4: Periods | G4: 1 | H4: =G4+1 -> 2 | I4: =H4+1 -> 3 | J4: =I4+1 -> 4 | K4: =J4+1 -> 5 | L4: =K4+1 -> 6 | M4: =L4+1 -> 7 | N4: =M4+1 -> 8 | O4: =N4+1 -> 9 | P4: =O4+1 -> 10
D5: Mid - Year Periods | G5: 0.5 | H5: =G5+1 -> 1.5 | I5: =H5+1 -> 2.5 | J5: =I5+1 -> 3.5 | K5: =J5+1 -> 4.5 | L5: =K5+1 -> 5.5 | M5: =L5+1 -> 6.5 | N5: =M5+1 -> 7.5 | O5: =N5+1 -> 8.5 | P5: =O5+1 -> 9.5
D8: Dividends Paid | G8: =-'Operating model'!M142 -> 54790847 | H8: =-'Operating model'!N142 -> 61816716 | I8: =-'Operating model'!O142 -> 70244957 | J8: =-'Operating model'!P142 -> 80347680 | K8: =-'Operating model'!Q142 -> 92449248 | L8: =-'Operating model'!R142 -> 1.0693627e+08 | M8: =-'Operating model'!S142 -> 1.242695e+08 | N8: =-'Operating model'!T142 -> 1.4499801e+08 | ... P8: =-'Operating model'!V142 -> 1.993833e+08
D9: Discount Factor | G9: =1/(1+$F$12)^G5 -> 0.93437982 | H9: =1/(1+$F$12)^H5 -> 0.81577493 | I9: =1/(1+$F$12)^I5 -> 0.71222508 | J9: =1/(1+$F$12)^J5 -> 0.62181925 | K9: =1/(1+$F$12)^K5 -> 0.54288903 | L9: =1/(1+$F$12)^L5 -> 0.47397777 | M9: =1/(1+$F$12)^M5 -> 0.41381371 | N9: =1/(1+$F$12)^N5 -> 0.36128654 | ... P9: =1/(1+$F$12)^P5 -> 0.27538837
D10: Discounted Dividends | G10: =G8*G9 -> 51195462 | H10: =H8*H9 -> 50428528 | I10: =I8*I9 -> 50030220 | J10: =J8*J9 -> 49961734 | K10: =K8*K9 -> 50189683 | L10: =L8*L9 -> 50685415 | M10: =M8*M9 -> 51424423 | N10: =N8*N9 -> 52385830 | ... P10: =P8*P9 -> 54907842
D12: Cost of Equity | F12: ='Cost of Equity'!E18 -> 0.14538923
D13: Terminal Growth Rate | F13: 0.03
D15: Terminal Value | F15: =P8*(1+F12)/(F12-F13) -> 1.9791404e+09
D16: Discounted Terminal Value | F16: =F15/(1+F12)^P5 -> 5.4503224e+08
D17: Discounted Dividends | F17: =SUM(G10:P10) -> 5.1476107e+08
D19: Equity Value | F19: =F16+F17 -> 1.0597933e+09
D20: Share Count | F20: 16000000 | G20: =F19/G21 -> 3532644.4
D21: Intrinsic value per share | F21: =F19/F20 -> 66.237082 | G21: 300
D23: EV Sensitivity | J23: Cost of Equity
E24: =F19 -> 1.0597933e+09 | F24: 0.14538923 | G24: =F24+1% -> 0.15538923 | H24: =G24+1% -> 0.16538923 | I24: =H24+1% -> 0.17538923 | J24: =I24+1% -> 0.18538923 | K24: =J24+1% -> 0.19538923 | L24: =K24+1% -> 0.20538923 | M24: =L24+1% -> 0.21538923
E25: 0.01 | F25: 9.7927993e+08 | G25: 8.9448279e+08 | H25: 8.2145534e+08 | I25: 7.5802457e+08 | J25: 7.0251409e+08 | K25: 6.5361029e+08 | L25: 6.1026959e+08 | M25: 5.7165272e+08
E26: =E25+0.5% -> 0.015 | F26: 9.9709271e+08 | G26: 9.0879155e+08 | H26: 8.330703e+08 | I26: 7.6754008e+08 | J26: 7.103736e+08 | K26: 6.6014964e+08 | L26: 6.1574648e+08 | M26: 5.7626723e+08
E27: =E26+0.5% -> 0.02 | F27: 1.0163261e+09 | G27: 9.2415717e+08 | H27: 8.4548414e+08 | I27: 7.7766795e+08 | J27: 7.1870832e+08 | K27: 6.6706183e+08 | L27: 6.2151879e+08 | M27: 5.8111792e+08
D28: PGR | E28: =E27+0.5% -> 0.025 | F28: 1.0371571e+09 | G28: 9.4070124e+08 | H28: 8.5878223e+08 | I28: 7.8846926e+08 | J28: 7.275627e+08 | K28: 6.743797e+08 | L28: 6.2761109e+08 | M28: 5.8622338e+08
E29: =E28+0.5% -> 0.03 | F29: 1.0597933e+09 | G29: 9.5856472e+08 | H29: 8.7306253e+08 | I29: 8.000135e+08 | J29: 7.369869e+08 | K29: 6.8214002e+08 | L29: 6.3405076e+08 | M29: 5.9160423e+08
E30: =E29+0.5% -> 0.035 | F30: 1.0844801e+09 | G30: 9.7791201e+08 | H30: 8.8843804e+08 | I30: 8.1238004e+08 | J30: 7.4703775e+08 | K30: 6.903842e+08 | L30: 6.4086836e+08 | M30: 5.9728338e+08
E31: =E30+0.5% -> 0.04 | F31: 1.1115094e+09 | G31: 9.9893601e+08 | H31: 9.0503977e+08 | I31: 8.2565999e+08 | J31: 7.577799e+08 | K31: 6.9915892e+08 | L31: 6.4809818e+08 | M31: 6.0328632e+08
E32: =E31+0.5% -> 0.045 | F32: 1.1412312e+09 | G32: 1.0218645e+09 | H32: 9.230205e+08 | I32: 8.3995842e+08 | J32: 7.6928723e+08 | K32: 7.085171e+08 | L32: 6.5577876e+08 | M32: 6.0964158e+08
D34: Intrinsic Value Sensitivity | J34: Cost of Equity
E35: =F21 -> 66.237082 | F35: 0.14538923 | G35: =F35+1% -> 0.15538923 | H35: =G35+1% -> 0.16538923 | I35: =H35+1% -> 0.17538923 | J35: =I35+1% -> 0.18538923 | K35: =J35+1% -> 0.19538923 | L35: =K35+1% -> 0.20538923 | M35: =L35+1% -> 0.21538923
E36: 0.01 | F36: 61.204996 | G36: 55.905174 | H36: 51.340959 | I36: 47.376536 | J36: 43.907131 | K36: 40.850643 | L36: 38.14185 | M36: 35.728295
E37: =E36+0.5% -> 0.015 | F37: 62.318294 | G37: 56.799472 | H37: 52.066894 | I37: 47.971255 | J37: 44.39835 | K37: 41.259353 | L37: 38.484155 | M37: 36.016702
E38: =E37+0.5% -> 0.02 | F38: 63.52038 | G38: 57.759823 | H38: 52.842759 | I38: 48.604247 | J38: 44.91927 | K38: 41.691365 | L38: 38.844924 | M38: 36.31987
D39: PGR | E39: =E38+0.5% -> 0.025 | F39: 64.822316 | G39: 58.793827 | H39: 53.673889 | I39: 49.279329 | J39: 45.472669 | K39: 42.148731 | L39: 39.225693 | M39: 36.638961
E40: =E39+0.5% -> 0.03 | F40: 66.237082 | G40: 59.910295 | H40: 54.566408 | I40: 50.000844 | J40: 46.061681 | K40: 42.633752 | L40: 39.628172 | M40: 36.975265
E41: =E40+0.5% -> 0.035 | F41: 67.780009 | G41: 61.119501 | H41: 55.527377 | I41: 50.773753 | J41: 46.689859 | K41: 43.149012 | L41: 40.054272 | M41: 37.330211
E42: =E41+0.5% -> 0.04 | F42: 69.469339 | G42: 62.4335 | H42: 56.564985 | I42: 51.603749 | J42: 47.361244 | K42: 43.697432 | L42: 40.506136 | M42: 37.705395
E43: =E42+0.5% -> 0.045 | F43: 71.326948 | G43: 63.866533 | H43: 57.688781 | I43: 52.497401 | J43: 48.080452 | K43: 44.282319 | L43: 40.986172 | M43: 38.102599
B45: END

Sheet Cost of Equity
C2: Cost of Equity
D4: US Risk Premium | E4: 0.0446 | G4: External Debt | H4: ='Operating model'!I34 -> 428588860
D5: US Default Spread | E5: 0.0023 | G5: Equity | H5: ='Operating model'!I38 -> 3868245421
D6: Mature Market ERP | E6: =E4-E5 -> 0.0423 | G6: Debt to Equity | H6: =H4/H5 -> 0.11079671
D7: Kenya Risk Premium | E7: 0.0841
D8: Total risk Premium | E8: =E6+E7 -> 0.1264
D10: Corporate Tax Rate | E10: 0.3 | G10: Inflation Entries
G11: US Inflation Rate | H11: 0.042
D12: Ten year Bond yield (US) | E12: 0.04456 | G12: Kenya Inflation Rate | H12: 0.064
D13: =D5 -> US Default Spread | E13: =E5 -> 0.0023
D14: Risk Free Rate | E14: =SUM(E12:E13) -> 0.04686
D16: Beta | E16: =E36*(1+(1-E10)*H6) -> 0.59213902
D17: Cost of Equity | E17: =E14+E16*E8 -> 0.12170637
D18: Cost of Equity Adjusted for Currency | E18: =(1+E17)*(1+H12)/(1+H11)-1 -> 0.14538923
D21: Beta Calulation
D22: Ticker | E22: Company | F22: Market Cap | G22: Total Debt | H22: Debt to Equity | I22: Levered Beta | J22: Country | K22: Industry | L22: Corporate Tax Rate | M22: Unlevered Beta
D23: BDMN.JK | E23: PT Bank Danamon Indonesia Tbk | F23: 36650822402048 | G23: 28222332862464 | H23: =G23/F23 -> 0.77003273 | I23: 0.657 | J23: Indonesia | K23: Banks - Regional | L23: 0.22 | M23: =I23/(1+(1-L23)*H23) -> 0.41046453
D24: SBIN.NS | E24: State Bank of India | F24: 9478921519104 | G24: 8610153758720 | H24: =G24/F24 -> 0.9083474 | I24: 0.37 | J24: India | K24: Banks - Regional | L24: 0.25 | M24: =I24/(1+(1-L24)*H24) -> 0.22007297
D25: CPI.JO | E25: Capitec Bank Holdings Limited | F25: 550319751168 | G25: 3829224960 | H25: =G25/F25 -> 0.006958182 | I25: 0.764 | J25: South Africa | K25: Banks - Regional | L25: 0.28 | M25: =I25/(1+(1-L25)*H25) -> 0.76019152
D26: FSR.JO | E26: FirstRand Limited | F26: 543860621312 | G26: 112150003712 | H26: =G26/F26 -> 0.20621093 | I26: 0.552 | J26: South Africa | K26: Banks - Diversified | L26: 0.28 | M26: =I26/(1+(1-L26)*H26) -> 0.48063868
D27: SBK.JO | E27: Standard Bank Group Limited | F27: 524306153472 | G27: 122018996224 | H27: =G27/F27 -> 0.23272471 | I27: 0.418 | J27: South Africa | K27: Banks - Regional | L27: 0.28 | M27: =I27/(1+(1-L27)*H27) -> 0.35801103
D28: UJJIVANSFB.NS | E28: Ujjivan Small Finance Bank Limited | F28: 114867355648 | G28: 37360099328 | H28: =G28/F28 -> 0.32524558 | I28: 0.451 | J28: India | K28: Banks - Regional | L28: 0.25 | M28: =I28/(1+(1-L28)*H28) -> 0.36255938
D29: BAP | E29: Credicorp Ltd. | F29: 30969749504 | G29: 26705020928 | H29: =G29/F29 -> 0.86229373 | I29: 0.862 | J29: Peru | K29: Banks - Regional | L29: 0.29 | M29: =I29/(1+(1-L29)*H29) -> 0.53466365
D30: FCFS | E30: FirstCash Holdings, Inc. | F30: 9482753024 | G30: 2610895872 | H30: =G30/F30 -> 0.275331 | I30: 0.525 | J30: United States | K30: Credit Services | L30: 0.21 | M30: =I30/(1+(1-L30)*H30) -> 0.43120743
D31: ENVA | E31: Enova International, Inc. | F31: 5984071168 | G31: 4864254976 | H31: =G31/F31 -> 0.81286717 | I31: 1.298 | J31: United States | K31: Credit Services | L31: 0.21 | M31: =I31/(1+(1-L31)*H31) -> 0.79041993
D32: CASH | E32: Pathward Financial, Inc. | F32: 1837839488 | G32: 82702000 | H32: =G32/F32 -> 0.044999577 | I32: 0.618 | J32: United States | K32: Banks - Regional | L32: 0.21 | M32: =I32/(1+(1-L32)*H32) -> 0.59678451
D33: WRLD | E33: World Acceptance Corporation | F33: 1038643520 | G33: 661193536 | H33: =G33/F33 -> 0.63659333 | I33: 1.199 | J33: United States | K33: Credit Services | L33: 0.21 | M33: =I33/(1+(1-L33)*H33) -> 0.7977863
D34: ASAI.L | E34: ASA International Group PLC | F34: 235716656 | G34: 431720000 | H34: =G34/F34 -> 1.831521 | I34: 2.021 | J34: Netherlands | K34: Credit Services | L34: 0.25 | M34: =I34/(1+(1-L34)*H34) -> 0.85143466
D36: Average Unlevered Beta | E36: =AVERAGE(M23:M34) -> 0.54951955
C38: END

Sheet Wangige Historicals
C2: Wangige Historicals | F2: 2024 | G2: 2025 | I2: 2024 | J2: 2025
D4: ='2024 Data'!C183 -> Interest on short term loan me | E4: ='2025 Data'!E6 -> KSH | F4: ='2024 Data'!P6 -> 1719502 | G4: ='2025 Data'!P6 -> 1888828 | H4: Growth % | J4: =IFERROR(G4/F4-1,0) -> 0.09847386
D5: ='2025 Data'!D7 -> Interest on short term loan Cu | E5: ='2025 Data'!E7 -> KSH | F5: ='2024 Data'!P7 -> 6275706 | G5: ='2025 Data'!P7 -> 5875619 | H5: Growth % | J5: =IFERROR(G5/F5-1,0) -> -0.063751712
D6: ='2025 Data'!D8 -> Interest on medium term loan m | E6: ='2025 Data'!E8 -> KSH | F6: ='2024 Data'!P8 -> 5658096 | G6: ='2025 Data'!P8 -> 6262546 | H6: Growth % | J6: =IFERROR(G6/F6-1,0) -> 0.10682922
D7: ='2025 Data'!D9 -> Interest on medium term loan C | E7: ='2025 Data'!E9 -> KSH | F7: ='2024 Data'!P9 -> 8821027 | G7: ='2025 Data'!P9 -> 11708782 | H7: Growth % | J7: =IFERROR(G7/F7-1,0) -> 0.32737174
D8: ='2025 Data'!D10 -> Interest on staff loan | E8: ='2025 Data'!E10 -> KSH | F8: ='2024 Data'!P10 -> 0 | G8: ='2025 Data'!P10 -> 0 | H8: Growth % | J8: =IFERROR(G8/F8-1,0) -> 0
D9: ='2025 Data'!D11 -> Interest on development loan soc | E9: ='2025 Data'!E11 -> KSH | F9: ='2024 Data'!P11 -> 0 | G9: ='2025 Data'!P11 -> 0 | H9: Growth % | J9: =IFERROR(G9/F9-1,0) -> 0
D10: ='2025 Data'!D12 -> Interest on overdraft members | E10: ='2025 Data'!E12 -> KSH | F10: ='2024 Data'!P12 -> 44205 | G10: ='2025 Data'!P12 -> 75929 | H10: Growth % | J10: =IFERROR(G10/F10-1,0) -> 0.71765637
D11: ='2025 Data'!D13 -> Interest on Overdue loan | E11: ='2025 Data'!E13 -> KSH | F11: ='2024 Data'!P13 -> 153248 | G11: ='2025 Data'!P13 -> 127199 | H11: Growth % | J11: =IFERROR(G11/F11-1,0) -> -0.16997938
D12: ='2025 Data'!D14 -> Advance interest | E12: ='2025 Data'!E14 -> KSH | F12: ='2024 Data'!P14 -> 4796459 | G12: ='2025 Data'!P14 -> 5692776 | H12: Growth % | J12: =IFERROR(G12/F12-1,0) -> 0.18687056
D13: ='2025 Data'!D15 -> Interest on shirika loan | E13: ='2025 Data'!E15 -> KSH | F13: ='2024 Data'!P15 -> 664086 | G13: ='2025 Data'!P15 -> 539878 | H13: Growth % | J13: =IFERROR(G13/F13-1,0) -> -0.18703602
D14: ='2025 Data'!D16 -> Interest on bonus advance loan | E14: ='2025 Data'!E16 -> KSH | F14: ='2024 Data'!P16 -> 0 | G14: ='2025 Data'!P16 -> 0 | H14: Growth % | J14: =IFERROR(G14/F14-1,0) -> 0
D15: ='2025 Data'!D17 -> Interest on Premium Financing | E15: ='2025 Data'!E17 -> KSH | F15: ='2024 Data'!P17 -> 640721 | G15: ='2025 Data'!P17 -> 32414 | H15: Growth % | J15: =IFERROR(G15/F15-1,0) -> -0.94941012
D16: ='2025 Data'!D18 -> Interest on MFI loan | E16: ='2025 Data'!E18 -> KSH | F16: ='2024 Data'!P18 -> 2692066 | G16: ='2025 Data'!P18 -> 2191585 | H16: Growth % | J16: =IFERROR(G16/F16-1,0) -> -0.18590963
... D35: ='2025 Data'!D37 -> Interest on corporate Bonds | E35: ='2025 Data'!E37 -> KSH | F35: ='2024 Data'!P37 -> 1950000 | G35: ='2025 Data'!P37 -> 1950000 | H35: Growth % | J35: =IFERROR(G35/F35-1,0) -> 0
D36: ='2025 Data'!D38 -> Total Government Securities | E36: ='2025 Data'!E38 -> KSH | F36: ='2024 Data'!P39 -> 3064704 | G36: ='2025 Data'!P38 -> 3058086 | H36: Growth % | J36: =IFERROR(G36/F36-1,0) -> -0.0021594255
D38: ='2025 Data'!D40 -> Interest on fixed deposit | E38: ='2025 Data'!E40 -> KSH | F38: ='2024 Data'!P41 -> 0 | G38: ='2025 Data'!P40 -> 0 | H38: Growth % | J38: =IFERROR(G38/F38-1,0) -> 0
D39: ='2025 Data'!D41 -> Interest on call deposit | E39: ='2025 Data'!E41 -> KSH | F39: ='2024 Data'!P42 -> 0 | G39: ='2025 Data'!P41 -> 0 | H39: Growth % | J39: =IFERROR(G39/F39-1,0) -> 0
D40: ='2025 Data'!D42 -> Total deposit with bank | E40: ='2025 Data'!E42 -> KSH | F40: ='2024 Data'!P43 -> 0 | G40: ='2025 Data'!P42 -> 0 | H40: Growth % | J40: =IFERROR(G40/F40-1,0) -> 0
D42: ='2025 Data'!D44 -> Interest Income From Financial Investment | E42: ='2025 Data'!E44 -> KSH | F42: ='2024 Data'!P45 -> 3064704 | G42: ='2025 Data'!P44 -> 3058086 | H42: Growth % | J42: =IFERROR(G42/F42-1,0) -> -0.0021594255
D44: ='2025 Data'!D46 -> Salary Processiong Charges | E44: ='2025 Data'!E46 -> KSH | F44: ='2024 Data'!P47 -> 675330 | G44: ='2025 Data'!P46 -> 601200 | H44: Growth % | J44: =IFERROR(G44/F44-1,0) -> -0.10976856
D45: ='2025 Data'!D47 -> Withdrawal transaction charge | E45: ='2025 Data'!E47 -> KSH | F45: ='2024 Data'!P48 -> 2489435 | G45: ='2025 Data'!P47 -> 2490960 | H45: Growth % | J45: =IFERROR(G45/F45-1,0) -> 0.0006125888
D46: ='2025 Data'!D48 -> Mobile Banking cash withdrawal and notification charge | E46: ='2025 Data'!E48 -> KSH | F46: ='2024 Data'!P49 -> 1570714 | G46: ='2025 Data'!P48 -> 1763913 | H46: Growth % | J46: =IFERROR(G46/F46-1,0) -> 0.12300075
D47: ='2025 Data'!D49 -> Ledger fee on charging customers | E47: ='2025 Data'!E49 -> KSH | F47: ='2024 Data'!P50 -> 1159399 | G47: ='2025 Data'!P49 -> 1445645 | H47: Growth % | J47: =IFERROR(G47/F47-1,0) -> 0.24689171
D48: ='2025 Data'!D50 -> Other Operating Income | E48: ='2025 Data'!E50 -> KSH | F48: ='2024 Data'!P51 -> 2014714 | G48: ='2025 Data'!P50 -> 2219915 | H48: Growth % | J48: =IFERROR(G48/F48-1,0) -> 0.10185118
D49: ='2025 Data'!D51 -> Total other operating income | E49: ='2025 Data'!E51 -> KSH | F49: ='2024 Data'!P52 -> 7909592 | G49: ='2025 Data'!P51 -> 8521633 | H49: Growth % | J49: =IFERROR(G49/F49-1,0) -> 0.077379592
D51: ='2025 Data'!D53 -> Other Income | E51: ='2025 Data'!E53 -> KSH | F51: ='2024 Data'!P54 -> 0 | G51: ='2025 Data'!P53 -> 0 | H51: Growth % | J51: =IFERROR(G51/F51-1,0) -> 0
D53: ='2025 Data'!D55 -> Total Revenue | E53: ='2025 Data'!E55 -> KSH | F53: ='2024 Data'!P56 -> 58960769 | G53: ='2025 Data'!P55 -> 63287462 | H53: Growth % | J53: =IFERROR(G53/F53-1,0) -> 0.073382574
D55: ='2025 Data'!D57 -> Interest on savings | E55: ='2025 Data'!E57 -> KSH | F55: ='2024 Data'!P58 -> -13378596 | G55: ='2025 Data'!P57 -> -22190926 | H55: % Of Total Revenue | I55: =-F55/F$53 -> 0.22690674 | J55: =-G55/G$53 -> 0.350637
D56: ='2025 Data'!D58 -> Interest on fixed deposits | E56: ='2025 Data'!E58 -> KSH | F56: ='2024 Data'!P59 -> -503412 | G56: ='2025 Data'!P58 -> -573312 | H56: % Of Total Revenue | I56: =-F56/F$53 -> 0.008538084 | J56: =-G56/G$53 -> 0.0090588559
D57: ='2025 Data'!D59 -> Interest on Diaspora jijenge savings | E57: ='2025 Data'!E59 -> KSH | F57: ='2024 Data'!P60 -> 0 | G57: ='2025 Data'!P59 -> 0 | H57: % Of Total Revenue | I57: =-F57/F$53 -> 0 | J57: =-G57/G$53 -> 0
D58: ='2025 Data'!D60 -> Total interest expense on deposits | E58: ='2025 Data'!E60 -> KSH | F58: ='2024 Data'!P61 -> -13882008 | G58: ='2025 Data'!P60 -> -22764238 | H58: % Of Total Revenue | I58: =-F58/F$53 -> 0.23544483 | J58: =-G58/G$53 -> 0.35969586
D60: ='2025 Data'!D62 -> Mobile deposit charges paybill | E60: ='2025 Data'!E62 -> KSH | F60: ='2024 Data'!P63 -> -1601042 | G60: ='2025 Data'!P62 -> -1184443 | H60: % Of Total Revenue | I60: =-F60/F$53 -> 0.027154361 | J60: =-G60/G$53 -> 0.018715287
D61: ='2025 Data'!D63 -> loss impairement of financial assets | E61: ='2025 Data'!E63 -> KSH | F61: ='2024 Data'!P64 -> 0 | G61: ='2025 Data'!P63 -> 0 | H61: % Of Total Revenue | I61: =-F61/F$53 -> 0 | J61: =-G61/G$53 -> 0
D62: ='2025 Data'!D64 -> Appraisal fee | E62: ='2025 Data'!E64 -> KSH | F62: ='2024 Data'!P65 -> 0 | G62: ='2025 Data'!P64 -> -2048870 | H62: % Of Total Revenue | I62: =-F62/F$53 -> 0 | J62: =-G62/G$53 -> 0.032374027
D63: ='2025 Data'!D65 -> Other Expenses | E63: ='2025 Data'!E65 -> KSH | F63: ='2024 Data'!P66 -> -40117 | G63: ='2025 Data'!P65 -> -2306 | H63: % Of Total Revenue | I63: =-F63/F$53 -> 0.00068040157 | J63: =-G63/G$53 -> 3.6436917e-05
D64: ='2025 Data'!D66 -> Total fees and commission expenses | E64: ='2025 Data'!E66 -> KSH | F64: ='2024 Data'!P67 -> -1641159 | G64: ='2025 Data'!P66 -> -3235619 | H64: % Of Total Revenue | I64: =-F64/F$53 -> 0.027834762 | J64: =-G64/G$53 -> 0.051125751
D66: ='2025 Data'!D68 -> Other Expenses | E66: ='2025 Data'!E68 -> KSH | F66: ='2024 Data'!P69 -> 0 | G66: ='2025 Data'!P68 -> -1500 | H66: % Of Total Revenue | I66: =-F66/F$53 -> 0 | J66: =-G66/G$53 -> 2.3701377e-05
D68: ='2025 Data'!D70 -> Total Provision for Loan Losses | E68: ='2025 Data'!E70 -> KSH | F68: ='2024 Data'!P71 -> -5793784 | G68: ='2025 Data'!P70 -> 1804419 | H68: % Of Total Revenue | I68: =-F68/F$53 -> 0.098265068 | J68: =-G68/G$53 -> -0.028511477
D70: ='2025 Data'!D72 -> Staff salaries | E70: ='2025 Data'!E72 -> KSH | F70: ='2024 Data'!P73 -> -7285498 | G70: ='2025 Data'!P72 -> -7185464 | H70: % Of Total Revenue | I70: =-F70/F$53 -> 0.12356518 | J70: =-G70/G$53 -> 0.11353693
... D85: ='2025 Data'!D87 -> Total Expenses | E85: ='2025 Data'!E87 -> KSH | F85: ='2024 Data'!P88 -> -43062987 | G85: ='2025 Data'!P87 -> -44987298 | H85: % Of Total Revenue | I85: =-F85/F$53 -> 0.73036678 | J85: =-G85/G$53 -> 0.71084061
D87: ='2025 Data'!D89 -> Banking Operating Profit | E87: ='2025 Data'!E89 -> KSH | F87: ='2024 Data'!P90 -> 15897782 | G87: ='2025 Data'!P89 -> 18300164 | H87: % Of Total Revenue | I87: =F87/F$53 -> 0.26963322 | J87: =G87/G$53 -> 0.28915939
B90: END

Sheet K unity Historicals
C2: K Unity Historicals | F2: 2023 | G2: 2024 | H2: 2025 | J2: =F2 -> 2023 | K2: =G2 -> 2024 | L2: =H2 -> 2025
D4: ='2025 Data'!D6 -> Interest on short term loan me | E4: ='2025 Data'!E6 -> KSH | F4: ='2023 Data'!F6 -> 39201557 | G4: ='2024 Data'!F6 -> 40146646 | H4: ='2025 Data'!F6 -> 46170443 | I4: Growth % | K4: =IFERROR(G4/F4-1,0) -> 0.024108456 | L4: =IFERROR(H4/G4-1,0) -> 0.15004484
D5: ='2025 Data'!D7 -> Interest on short term loan Cu | E5: ='2025 Data'!E7 -> KSH | F5: ='2023 Data'!F7 -> 57246553 | G5: ='2024 Data'!F7 -> 60779965 | H5: ='2025 Data'!F7 -> 64698667 | I5: Growth % | K5: =IFERROR(G5/F5-1,0) -> 0.061722703 | L5: =IFERROR(H5/G5-1,0) -> 0.064473581
D6: ='2025 Data'!D8 -> Interest on medium term loan m | E6: ='2025 Data'!E8 -> KSH | F6: ='2023 Data'!F8 -> 48782578 | G6: ='2024 Data'!F8 -> 56015978 | H6: ='2025 Data'!F8 -> 67314965 | I6: Growth % | K6: =IFERROR(G6/F6-1,0) -> 0.14827835 | L6: =IFERROR(H6/G6-1,0) -> 0.20171007
D7: ='2025 Data'!D9 -> Interest on medium term loan C | E7: ='2025 Data'!E9 -> KSH | F7: ='2023 Data'!F9 -> 194424006 | G7: ='2024 Data'!F9 -> 239627084 | H7: ='2025 Data'!F9 -> 267584894 | I7: Growth % | K7: =IFERROR(G7/F7-1,0) -> 0.23249741 | L7: =IFERROR(H7/G7-1,0) -> 0.11667216
D8: ='2025 Data'!D10 -> Interest on staff loan | E8: ='2025 Data'!E10 -> KSH | F8: ='2023 Data'!F10 -> 18038056 | G8: ='2024 Data'!F10 -> 19774041 | H8: ='2025 Data'!F10 -> 22370511 | I8: Growth % | K8: =IFERROR(G8/F8-1,0) -> 0.096240138 | L8: =IFERROR(H8/G8-1,0) -> 0.131307
D9: ='2025 Data'!D11 -> Interest on development loan soc | E9: ='2025 Data'!E11 -> KSH | F9: ='2023 Data'!F11 -> 9838194 | G9: ='2024 Data'!F11 -> 10551967 | H9: ='2025 Data'!F11 -> 10430099 | I9: Growth % | K9: =IFERROR(G9/F9-1,0) -> 0.072551222 | L9: =IFERROR(H9/G9-1,0) -> -0.011549316
D10: ='2025 Data'!D12 -> Interest on overdraft members | E10: ='2025 Data'!E12 -> KSH | F10: ='2023 Data'!F12 -> 26739072 | G10: ='2024 Data'!F12 -> 19080366 | H10: ='2025 Data'!F12 -> 13572578 | I10: Growth % | K10: =IFERROR(G10/F10-1,0) -> -0.28642378 | L10: =IFERROR(H10/G10-1,0) -> -0.2886626
D11: ='2025 Data'!D13 -> Interest on Overdue loan | E11: ='2025 Data'!E13 -> KSH | F11: ='2023 Data'!F13 -> 2437563 | G11: ='2024 Data'!F13 -> 2837299 | H11: ='2025 Data'!F13 -> 3123169 | I11: Growth % | K11: =IFERROR(G11/F11-1,0) -> 0.16399002 | L11: =IFERROR(H11/G11-1,0) -> 0.10075427
D12: ='2025 Data'!D14 -> Advance interest | E12: ='2025 Data'!E14 -> KSH | F12: ='2023 Data'!F14 -> 69730536 | G12: ='2024 Data'!F14 -> 72228964 | H12: ='2025 Data'!F14 -> 106197039 | I12: Growth % | K12: =IFERROR(G12/F12-1,0) -> 0.035829755 | L12: =IFERROR(H12/G12-1,0) -> 0.47028329
D13: ='2025 Data'!D15 -> Interest on shirika loan | E13: ='2025 Data'!E15 -> KSH | F13: ='2023 Data'!F15 -> 2727798 | G13: ='2024 Data'!F15 -> 5616400 | H13: ='2025 Data'!F15 -> 4302196 | I13: Growth % | K13: =IFERROR(G13/F13-1,0) -> 1.0589501 | L13: =IFERROR(H13/G13-1,0) -> -0.23399402
D14: ='2025 Data'!D16 -> Interest on bonus advance loan | E14: ='2025 Data'!E16 -> KSH | F14: ='2023 Data'!F16 -> 7995144 | G14: ='2024 Data'!F16 -> 16899662 | H14: ='2025 Data'!F16 -> 13607645 | I14: Growth % | K14: =IFERROR(G14/F14-1,0) -> 1.1137408 | L14: =IFERROR(H14/G14-1,0) -> -0.1947978
D15: ='2025 Data'!D17 -> Interest on Premium Financing | E15: ='2025 Data'!E17 -> KSH | F15: ='2023 Data'!F17 -> 15743721 | G15: ='2024 Data'!F17 -> 11223687 | H15: ='2025 Data'!F17 -> 267258 | I15: Growth % | K15: =IFERROR(G15/F15-1,0) -> -0.28710074 | L15: =IFERROR(H15/G15-1,0) -> -0.97618804
... D31: ='2025 Data'!D33 -> Total fees and Commision on loan Portfolio | E31: ='2025 Data'!E33 -> KSH | F31: ='2023 Data'!F33 -> 40421560 | G31: ='2024 Data'!F33 -> 32637513 | H31: ='2025 Data'!F33 -> 29466468 | I31: Growth % | K31: =IFERROR(G31/F31-1,0) -> -0.19257166 | L31: =IFERROR(H31/G31-1,0) -> -0.097159517
E32: ='2025 Data'!E34 -> 0 | F32: ='2023 Data'!F34 -> 0 | G32: ='2024 Data'!F34 -> 0 | H32: ='2025 Data'!F34 -> 0
D33: ='2025 Data'!D35 -> Interest on treasury bonds | E33: ='2025 Data'!E35 -> KSH | F33: ='2023 Data'!F35 -> 12759332 | G33: ='2024 Data'!F35 -> 13034253 | H33: ='2025 Data'!F35 -> 12923306 | I33: Growth % | K33: =IFERROR(G33/F33-1,0) -> 0.021546661 | L33: =IFERROR(H33/G33-1,0) -> -0.0085119569
D34: ='2025 Data'!D36 -> Discount on infrastructure Bonds | E34: ='2025 Data'!E36 -> KSH | F34: ='2023 Data'!F36 -> 231170 | G34: ='2024 Data'!F36 -> 234268 | H34: ='2025 Data'!F36 -> 458238 | I34: Growth % | K34: =IFERROR(G34/F34-1,0) -> 0.013401393 | L34: =IFERROR(H34/G34-1,0) -> 0.9560418
D35: ='2025 Data'!D37 -> Interest on corporate Bonds | E35: ='2025 Data'!E37 -> KSH | F35: ='2023 Data'!F37 -> 10399992 | G35: ='2024 Data'!F37 -> 10399992 | H35: ='2025 Data'!F37 -> 10399992 | I35: Growth % | K35: =IFERROR(G35/F35-1,0) -> 0 | L35: =IFERROR(H35/G35-1,0) -> 0
D36: ='2025 Data'!D38 -> Total Government Securities | E36: ='2025 Data'!E38 -> KSH | F36: ='2023 Data'!F39 -> 23402909 | G36: ='2024 Data'!F39 -> 23678878 | H36: ='2025 Data'!F38 -> 23781536 | I36: Growth % | K36: =IFERROR(G36/F36-1,0) -> 0.011792081 | L36: =IFERROR(H36/G36-1,0) -> 0.004335425
E37: ='2025 Data'!E39 -> 0 | F37: ='2023 Data'!F40 -> 0 | G37: ='2024 Data'!F40 -> 0 | H37: ='2025 Data'!F39 -> 0
D38: ='2025 Data'!D40 -> Interest on fixed deposit | E38: ='2025 Data'!E40 -> KSH | F38: ='2023 Data'!F41 -> 48045587 | G38: ='2024 Data'!F41 -> 66730025 | H38: ='2025 Data'!F40 -> 80499628 | I38: Growth % | K38: =IFERROR(G38/F38-1,0) -> 0.38888979 | L38: =IFERROR(H38/G38-1,0) -> 0.20634794
D39: ='2025 Data'!D41 -> Interest on call deposit | E39: ='2025 Data'!E41 -> KSH | F39: ='2023 Data'!F42 -> 16043890 | G39: ='2024 Data'!F42 -> 19020729 | H39: ='2025 Data'!F41 -> 5081574 | I39: Growth % | K39: =IFERROR(G39/F39-1,0) -> 0.18554347 | L39: =IFERROR(H39/G39-1,0) -> -0.73284021
D40: ='2025 Data'!D42 -> Total deposit with bank | E40: ='2025 Data'!E42 -> KSH | F40: ='2023 Data'!F43 -> 64089477 | G40: ='2024 Data'!F43 -> 85750754 | H40: ='2025 Data'!F42 -> 85581202 | I40: Growth % | K40: =IFERROR(G40/F40-1,0) -> 0.33798492 | L40: =IFERROR(H40/G40-1,0) -> -0.0019772654
E41: ='2025 Data'!E43 -> 0 | F41: ='2023 Data'!F44 -> 0 | G41: ='2024 Data'!F44 -> 0 | H41: ='2025 Data'!F43 -> 0
D42: ='2025 Data'!D44 -> Interest Income From Financial Investment | E42: ='2025 Data'!E44 -> KSH | F42: ='2023 Data'!F45 -> 87492386 | G42: ='2024 Data'!F45 -> 109429632 | H42: ='2025 Data'!F44 -> 109362738 | I42: Growth % | K42: =IFERROR(G42/F42-1,0) -> 0.2507332 | L42: =IFERROR(H42/G42-1,0) -> -0.00061129695
E43: ='2025 Data'!E45 -> 0 | F43: ='2023 Data'!F46 -> 0 | G43: ='2024 Data'!F46 -> 0 | H43: ='2025 Data'!F45 -> 0 | K43: =IFERROR(G43/F43-1,0) -> 0 | L43: =IFERROR(H43/G43-1,0) -> 0
D44: ='2025 Data'!D46 -> Salary Processiong Charges | E44: ='2025 Data'!E46 -> KSH | F44: ='2023 Data'!F47 -> 11623361 | G44: ='2024 Data'!F47 -> 10131507 | H44: ='2025 Data'!F46 -> 7773364 | I44: Growth % | K44: =IFERROR(G44/F44-1,0) -> -0.12834962 | L44: =IFERROR(H44/G44-1,0) -> -0.23275343
D45: ='2025 Data'!D47 -> Withdrawal transaction charge | E45: ='2025 Data'!E47 -> KSH | F45: ='2023 Data'!F48 -> 26994820 | G45: ='2024 Data'!F48 -> 27360908 | H45: ='2025 Data'!F47 -> 25616170 | I45: Growth % | K45: =IFERROR(G45/F45-1,0) -> 0.013561417 | L45: =IFERROR(H45/G45-1,0) -> -0.063767547
D46: ='2025 Data'!D48 -> Mobile Banking cash withdrawal and notification charge | E46: ='2025 Data'!E48 -> KSH | F46: ='2023 Data'!F49 -> 17758576 | G46: ='2024 Data'!F49 -> 12984431 | H46: ='2025 Data'!F48 -> 17052437 | I46: Growth % | K46: =IFERROR(G46/F46-1,0) -> -0.26883603 | L46: =IFERROR(H46/G46-1,0) -> 0.31329875
D47: ='2025 Data'!D49 -> Ledger fee on charging customers | E47: ='2025 Data'!E49 -> KSH | F47: ='2023 Data'!F50 -> 14343910 | G47: ='2024 Data'!F50 -> 12841942 | H47: ='2025 Data'!F49 -> 14326729 | I47: Growth % | K47: =IFERROR(G47/F47-1,0) -> -0.1047112 | L47: =IFERROR(H47/G47-1,0) -> 0.11562013
D48: ='2025 Data'!D50 -> Other Operating Income | E48: ='2025 Data'!E50 -> KSH | F48: ='2023 Data'!F51 -> 23192234 | G48: ='2024 Data'!F51 -> 24733827 | H48: ='2025 Data'!F50 -> 25711184 | I48: Growth % | K48: =IFERROR(G48/F48-1,0) -> 0.066470224 | L48: =IFERROR(H48/G48-1,0) -> 0.039514993
D49: ='2025 Data'!D51 -> Total other operating income | E49: ='2025 Data'!E51 -> KSH | F49: ='2023 Data'!F52 -> 93912901 | G49: ='2024 Data'!F52 -> 88052615 | H49: ='2025 Data'!F51 -> 90479884 | I49: Growth % | K49: =IFERROR(G49/F49-1,0) -> -0.062401288 | L49: =IFERROR(H49/G49-1,0) -> 0.027566121
E50: ='2025 Data'!E52 -> 0 | F50: ='2023 Data'!F53 -> 0 | G50: ='2024 Data'!F53 -> 0 | H50: ='2025 Data'!F52 -> 0
D51: ='2025 Data'!D53 -> Other Income | E51: ='2025 Data'!E53 -> KSH | F51: ='2023 Data'!F54 -> 0 | G51: ='2024 Data'!F54 -> 0 | H51: ='2025 Data'!F53 -> 0 | I51: Growth % | K51: =IFERROR(G51/F51-1,0) -> 0 | L51: =IFERROR(H51/G51-1,0) -> 0
E52: ='2025 Data'!E54 -> 0 | F52: ='2023 Data'!F55 -> 0 | G52: ='2024 Data'!F55 -> 0 | H52: ='2025 Data'!F54 -> 0
D53: ='2025 Data'!D55 -> Total Revenue | E53: ='2025 Data'!E55 -> KSH | F53: ='2023 Data'!F56 -> 847503573 | G53: ='2024 Data'!F56 -> 967190810 | H53: ='2025 Data'!F55 -> 1091524083 | I53: Growth % | K53: =IFERROR(G53/F53-1,0) -> 0.14122328 | L53: =IFERROR(H53/G53-1,0) -> 0.12855092
E54: ='2025 Data'!E56 -> 0 | F54: ='2023 Data'!F57 -> 0 | G54: ='2024 Data'!F57 -> 0 | H54: ='2025 Data'!F56 -> 0
D55: ='2025 Data'!D57 -> Interest on savings | E55: ='2025 Data'!E57 -> KSH | F55: ='2023 Data'!F58 -> -117780391 | G55: ='2024 Data'!F58 -> -137377401 | H55: ='2025 Data'!F57 -> -194768850 | I55: % Of Total Revenue | J55: =-F55/F$53 -> 0.13897333 | K55: =-G55/G$53 -> 0.14203754 | L55: =-H55/H$53 -> 0.17843752
D56: ='2025 Data'!D58 -> Interest on fixed deposits | E56: ='2025 Data'!E58 -> KSH | F56: ='2023 Data'!F59 -> -10015942 | G56: ='2024 Data'!F59 -> -12745753 | H56: ='2025 Data'!F58 -> -10650246 | I56: % Of Total Revenue | J56: =-F56/F$53 -> 0.011818171 | K56: =-G56/G$53 -> 0.013178116 | L56: =-H56/H$53 -> 0.0097572249
D57: ='2025 Data'!D59 -> Interest on Diaspora jijenge savings | E57: ='2025 Data'!E59 -> KSH | F57: ='2023 Data'!F60 -> 0 | G57: ='2024 Data'!F60 -> 0 | H57: ='2025 Data'!F59 -> -2650123 | I57: % Of Total Revenue | J57: =-F57/F$53 -> 0 | K57: =-G57/G$53 -> 0 | L57: =-H57/H$53 -> 0.0024279107
D58: ='2025 Data'!D60 -> Total interest expense on deposits | E58: ='2025 Data'!E60 -> KSH | F58: ='2023 Data'!F61 -> -127796333 | G58: ='2024 Data'!F61 -> -150123154 | H58: ='2025 Data'!F60 -> -208069219 | I58: % Of Total Revenue | J58: =-F58/F$53 -> 0.1507915 | K58: =-G58/G$53 -> 0.15521565 | L58: =-H58/H$53 -> 0.19062266
E59: ='2025 Data'!E61 -> 0 | F59: ='2023 Data'!F62 -> 0 | G59: ='2024 Data'!F62 -> 0 | H59: ='2025 Data'!F61 -> 0
D60: ='2025 Data'!D62 -> Mobile deposit charges paybill | E60: ='2025 Data'!E62 -> KSH | F60: ='2023 Data'!F63 -> -17576878 | G60: ='2024 Data'!F63 -> -10588128 | H60: ='2025 Data'!F62 -> -10966219 | I60: % Of Total Revenue | J60: =-F60/F$53 -> 0.020739592 | K60: =-G60/G$53 -> 0.0109473 | L60: =-H60/H$53 -> 0.010046704
D61: ='2025 Data'!D63 -> loss impairement of financial assets | E61: ='2025 Data'!E63 -> KSH | F61: ='2023 Data'!F64 -> 0 | G61: ='2024 Data'!F64 -> -736927 | H61: ='2025 Data'!F63 -> -21178647 | I61: % Of Total Revenue | J61: =-F61/F$53 -> 0 | K61: =-G61/G$53 -> 0.00076192515 | L61: =-H61/H$53 -> 0.019402822
D62: ='2025 Data'!D64 -> Appraisal fee | E62: ='2025 Data'!E64 -> KSH | F62: ='2023 Data'!F65 -> 0 | G62: ='2024 Data'!F65 -> -22700 | H62: ='2025 Data'!F64 -> -24809401 | I62: % Of Total Revenue | J62: =-F62/F$53 -> 0 | K62: =-G62/G$53 -> 2.3470033e-05 | L62: =-H62/H$53 -> 0.022729138
D63: ='2025 Data'!D65 -> Other Expenses | E63: ='2025 Data'!E65 -> KSH | F63: ='2023 Data'!F66 -> -759178 | G63: ='2024 Data'!F66 -> -671146 | H63: ='2025 Data'!F65 -> -875964 | I63: % Of Total Revenue | J63: =-F63/F$53 -> 0.00089578147 | K63: =-G63/G$53 -> 0.00069391271 | L63: =-H63/H$53 -> 0.00080251459
D64: ='2025 Data'!D66 -> Total fees and commission expenses | E64: ='2025 Data'!E66 -> KSH | F64: ='2023 Data'!F67 -> -18336056 | G64: ='2024 Data'!F67 -> -12018901 | H64: ='2025 Data'!F66 -> -57830231 | I64: % Of Total Revenue | J64: =-F64/F$53 -> 0.021635373 | K64: =-G64/G$53 -> 0.012426608 | L64: =-H64/H$53 -> 0.052981177
E65: ='2025 Data'!E67 -> 0 | F65: ='2023 Data'!F68 -> 0 | G65: ='2024 Data'!F68 -> 0 | H65: ='2025 Data'!F67 -> 0
D66: ='2025 Data'!D68 -> Other Expenses | E66: ='2025 Data'!E68 -> KSH | F66: ='2023 Data'!F69 -> 0 | G66: ='2024 Data'!F69 -> 0 | H66: ='2025 Data'!F68 -> -765718 | I66: % Of Total Revenue | J66: =-F66/F$53 -> 0 | K66: =-G66/G$53 -> 0 | L66: =-H66/H$53 -> 0.00070151269
E67: ='2025 Data'!E69 -> 0 | F67: ='2023 Data'!F70 -> 0 | G67: ='2024 Data'!F70 -> 0 | H67: ='2025 Data'!F69 -> 0
D68: ='2025 Data'!D70 -> Total Provision for Loan Losses | E68: ='2025 Data'!E70 -> KSH | F68: ='2023 Data'!F71 -> -130646575 | G68: ='2024 Data'!F71 -> -117296332 | H68: ='2025 Data'!F70 -> -54165271 | I68: % Of Total Revenue | J68: =-F68/F$53 -> 0.1541546 | K68: =-G68/G$53 -> 0.12127528 | L68: =-H68/H$53 -> 0.049623524
E69: ='2025 Data'!E71 -> 0 | F69: ='2023 Data'!F72 -> 0 | G69: ='2024 Data'!F72 -> 0 | H69: ='2025 Data'!F71 -> 0
D70: ='2025 Data'!D72 -> Staff salaries | E70: ='2025 Data'!E72 -> KSH | F70: ='2023 Data'!F73 -> -87948465 | G70: ='2024 Data'!F73 -> -93418728 | H70: ='2025 Data'!F72 -> -99004652 | I70: % Of Total Revenue | J70: =-F70/F$53 -> 0.10377356 | K70: =-G70/G$53 -> 0.096587692 | L70: =-H70/H$53 -> 0.090703131
D71: ='2025 Data'!D73 -> House alowance | E71: ='2025 Data'!E73 -> KSH | F71: ='2023 Data'!F74 -> -20555655 | G71: ='2024 Data'!F74 -> -21733528 | H71: ='2025 Data'!F73 -> -23173335 | I71: % Of Total Revenue | J71: =-F71/F$53 -> 0.024254358 | K71: =-G71/G$53 -> 0.022470776 | L71: =-H71/H$53 -> 0.021230255
D72: ='2025 Data'!D74 -> Other personnel expenses | E72: ='2025 Data'!E74 -> KSH | F72: ='2023 Data'!F75 -> -49662288 | G72: ='2024 Data'!F75 -> -51537083 | H72: ='2025 Data'!F74 -> -54734958 | I72: % Of Total Revenue | J72: =-F72/F$53 -> 0.058598323 | K72: =-G72/G$53 -> 0.053285332 | L72: =-H72/H$53 -> 0.050145442
D73: ='2025 Data'!D75 -> Total personnel expenses | E73: ='2025 Data'!E75 -> KSH | F73: ='2023 Data'!F76 -> -158166408 | G73: ='2024 Data'!F76 -> -166689339 | H73: ='2025 Data'!F75 -> -176912945 | I73: % Of Total Revenue | J73: =-F73/F$53 -> 0.18662624 | K73: =-G73/G$53 -> 0.1723438 | L73: =-H73/H$53 -> 0.16207883
E74: ='2025 Data'!E76 -> 0 | F74: ='2023 Data'!F77 -> 0 | G74: ='2024 Data'!F77 -> 0 | H74: ='2025 Data'!F76 -> 0
D75: ='2025 Data'!D77 -> Total governance Expenses | E75: ='2025 Data'!E77 -> KSH | F75: ='2023 Data'!F78 -> -43554754 | G75: ='2024 Data'!F78 -> -56550927 | H75: ='2025 Data'!F77 -> -47313870 | I75: % Of Total Revenue | J75: =-F75/F$53 -> 0.051391823 | K75: =-G75/G$53 -> 0.058469256 | L75: =-H75/H$53 -> 0.043346611
E76: ='2025 Data'!E78 -> 0 | F76: ='2023 Data'!F79 -> 0 | G76: ='2024 Data'!F79 -> 0 | H76: ='2025 Data'!F78 -> 0
D77: ='2025 Data'!D79 -> Total Marketing Expenses | E77: ='2025 Data'!E79 -> KSH | F77: ='2023 Data'!F80 -> -2053376 | G77: ='2024 Data'!F80 -> -1717399 | H77: ='2025 Data'!F79 -> -2474757 | I77: % Of Total Revenue | J77: =-F77/F$53 -> 0.0024228523 | K77: =-G77/G$53 -> 0.0017756569 | L77: =-H77/H$53 -> 0.0022672491
E78: ='2025 Data'!E80 -> 0 | F78: ='2023 Data'!F81 -> 0 | G78: ='2024 Data'!F81 -> 0 | H78: ='2025 Data'!F80 -> 0
D79: ='2025 Data'!D81 -> Total Depreciation and amortization | E79: ='2025 Data'!E81 -> KSH | F79: ='2023 Data'!F82 -> -2995686 | G79: ='2024 Data'!F82 -> -2564321 | H79: ='2025 Data'!F81 -> -3305308 | I79: % Of Total Revenue | J79: =-F79/F$53 -> 0.0035347178 | K79: =-G79/G$53 -> 0.0026513083 | L79: =-H79/H$53 -> 0.0030281586
E80: ='2025 Data'!E82 -> 0 | F80: ='2023 Data'!F83 -> 0 | G80: ='2024 Data'!F83 -> 0 | H80: ='2025 Data'!F82 -> 0
D81: ='2025 Data'!D83 -> Security | E81: ='2025 Data'!E83 -> KSH | F81: ='2023 Data'!F84 -> -26115116 | G81: ='2024 Data'!F84 -> -27077015 | H81: ='2025 Data'!F83 -> -27026462 | I81: % Of Total Revenue | J81: =-F81/F$53 -> 0.030814166 | K81: =-G81/G$53 -> 0.027995526 | L81: =-H81/H$53 -> 0.024760298
D82: ='2025 Data'!D84 -> Other Admin Expenses | E82: ='2025 Data'!E84 -> KSH | F82: ='2023 Data'!F85 -> -56401045 | G82: ='2024 Data'!F85 -> -58548388 | H82: ='2025 Data'!F84 -> -54136686 | I82: % Of Total Revenue | J82: =-F82/F$53 -> 0.066549625 | K82: =-G82/G$53 -> 0.060534475 | L82: =-H82/H$53 -> 0.049597335
D83: ='2025 Data'!D85 -> Total Admin expenses | E83: ='2025 Data'!E85 -> KSH | F83: ='2023 Data'!F86 -> -82516161 | G83: ='2024 Data'!F86 -> -85625403 | H83: ='2025 Data'!F85 -> -81163148 | I83: % Of Total Revenue | J83: =-F83/F$53 -> 0.097363791 | K83: =-G83/G$53 -> 0.088530001 | L83: =-H83/H$53 -> 0.074357634
E84: ='2025 Data'!E86 -> 0 | F84: ='2023 Data'!F87 -> 0 | G84: ='2024 Data'!F87 -> 0 | H84: ='2025 Data'!F86 -> 0
D85: ='2025 Data'!D87 -> Total Expenses | E85: ='2025 Data'!E87 -> KSH | F85: ='2023 Data'!F88 -> -566065349 | G85: ='2024 Data'!F88 -> -592585776 | H85: ='2025 Data'!F87 -> -632000467 | I85: % Of Total Revenue | J85: =-F85/F$53 -> 0.6679209 | K85: =-G85/G$53 -> 0.61268756 | L85: =-H85/H$53 -> 0.57900735
E86: ='2025 Data'!E88 -> 0 | F86: ='2023 Data'!F89 -> 0 | G86: ='2024 Data'!F89 -> 0 | H86: ='2025 Data'!F88 -> 0
D87: ='2025 Data'!D89 -> Banking Operating Profit | E87: ='2025 Data'!E89 -> KSH | F87: ='2023 Data'!F90 -> 281438224 | G87: ='2024 Data'!F90 -> 374605034 | H87: ='2025 Data'!F89 -> 459523616 | I87: % Of Total Revenue | J87: =F87/F$53 -> 0.3320791 | K87: =G87/G$53 -> 0.38731244 | L87: =H87/H$53 -> 0.42099265
B90: END

Sheet 2025 Data
D2: ='2024 Data'!D2 -> K - Unity Data
D3: 2025 | F3: Totals | G3: Other Ops | H3: Totals Net Other Ops | I3: Kiambu | J3: Githunguri | K3: Kagwe | L3: Kiriita | M3: Limuru | N3: Mai mahiu | O3: Kikuyu | P3: Wangige | Q3: Banana | R3: Gikomba | S3: Suswa | T3: Ruaka | U3: Wakimbo | V3: Gikambura | W3: Nairekia Enkare | X3: Kamwangi
C5: Income Statements
D6: Interest on short term loan me | E6: KSH | F6: =SUM(I6:X6) -> 46170443 | I6: 2460400 | J6: 12060595 | K6: 3105538 | L6: 2375219 | M6: 5871443 | N6: 719046 | O6: 2191385 | P6: 1888828 | Q6: 223336 | R6: 175 | S6: 7549893 | T6: 29854 | U6: 264164 | V6: 42924 | W6: 7287819 | X6: 99824
D7: Interest on short term loan Cu | E7: KSH | F7: =SUM(I7:X7) -> 64698667 | I7: 6704834 | J7: 5902276 | K7: 1504528 | L7: 6446852 | M7: 7172253 | N7: 4921519 | O7: 5464171 | P7: 5875619 | Q7: 2527197 | R7: 8615855 | S7: 1560104 | T7: 1304242 | U7: 1506996 | V7: 808478 | W7: 3457895 | X7: 925848
D8: Interest on medium term loan m | E8: KSH | F8: =SUM(I8:X8) -> 67314965 | I8: 2944307 | J8: 36158179 | K8: 2034507 | L8: 1873267 | M8: 11428387 | N8: 332039 | O8: 2228204 | P8: 6262546 | Q8: 1464223 | R8: 0 | S8: 395834 | T8: 0 | U8: 386895 | V8: 111158 | W8: 1593971 | X8: 101448
D9: Interest on medium term loan C | E9: KSH | F9: =SUM(I9:X9) -> 267584894 | I9: 47885892 | J9: 39369311 | K9: 2531509 | L9: 15028079 | M9: 24874155 | N9: 23543727 | O9: 35169771 | P9: 11708782 | Q9: 12875600 | R9: 27689714 | S9: 8087325 | T9: 2691972 | U9: 5151325 | V9: 3671856 | W9: 5763528 | X9: 1542348
D10: Interest on staff loan | E10: KSH | F10: =SUM(I10:X10) -> 22370511 | I10: 22370511 | J10: 0 | K10: 0 | L10: 0 | M10: 0 | N10: 0 | O10: 0 | P10: 0 | Q10: 0 | R10: 0 | S10: 0 | T10: 0 | U10: 0 | V10: 0 | W10: 0 | X10: 0
D11: Interest on development loan soc | E11: KSH | F11: =SUM(I11:X11) -> 10430099 | I11: 2832934 | J11: 1915540 | K11: 22753 | L11: 0 | M11: 0 | N11: 0 | O11: 1757099 | P11: 0 | Q11: 3901773 | R11: 0 | S11: 0 | T11: 0 | U11: 0 | V11: 0 | W11: 0 | X11: 0
D12: Interest on overdraft members | E12: KSH | F12: =SUM(I12:X12) -> 13572578 | I12: 5896630 | J12: 0 | K12: 0 | L12: 1308294 | M12: 567767 | N12: 197817 | O12: 1567593 | P12: 75929 | Q12: 3540054 | R12: 45890 | S12: 0 | T12: 0 | U12: 0 | V12: 258917 | W12: 2341 | X12: 111346
D13: Interest on Overdue loan | E13: KSH | F13: =SUM(I13:X13) -> 3123169 | I13: 322185 | J13: 714795 | K13: 201769 | L13: 521974 | M13: 737943 | N13: 23612 | O13: 473692 | P13: 127199 | Q13: 0 | R13: 0 | S13: 0 | T13: 0 | U13: 0 | V13: 0 | W13: 0 | X13: 0
D14: Advance interest | E14: KSH | F14: =SUM(I14:X14) -> 106197039 | I14: 17754962 | J14: 21446339 | K14: 4203390 | L14: 7080050 | M14: 12142861 | N14: 3306117 | O14: 9635860 | P14: 5692776 | Q14: 4267797 | R14: 6257200 | S14: 2449317 | T14: 3115516 | U14: 1847991 | V14: 1052222 | W14: 3955532 | X14: 1989109
D15: Interest on shirika loan | E15: KSH | F15: =SUM(I15:X15) -> 4302196 | I15: 2737 | J15: 0 | K15: 294 | L15: 188026 | M15: 88807 | N15: 969741 | O15: 1131168 | P15: 539878 | Q15: 0 | R15: 0 | S15: 37250 | T15: 0 | U15: 1313 | V15: 0 | W15: 1331180 | X15: 11802
D16: Interest on bonus advance loan | E16: KSH | F16: =SUM(I16:X16) -> 13607645 | I16: 0 | J16: 6392940 | K16: 5419729 | L16: 368574 | M16: 225189 | N16: 0 | O16: 0 | P16: 0 | Q16: 0 | R16: 0 | S16: 0 | T16: 0 | U16: 0 | V16: 0 | W16: 1046893 | X16: 154320
D17: Interest on Premium Financing | E17: KSH | F17: =SUM(I17:X17) -> 267258 | I17: 16466 | J17: 86585 | K17: 5045 | L17: 7392 | M17: 0 | N17: 167 | O17: 0 | P17: 32414 | Q17: 408 | R17: 19775 | S17: 3779 | T17: 3618 | U17: 72248 | V17: 0 | W17: 19361 | X17: 0
... D19: Interest on Jijenge Loan | E19: KSH | F19: =SUM(I19:X19) -> 150440318 | I19: 59362053 | J19: 12327416 | K19: 3414908 | L19: 4047954 | M19: 11061299 | N19: 5255703 | O19: 10008491 | P19: 9274439 | Q19: 8176318 | R19: 13279004 | S19: 224879 | T19: 7254280 | U19: 139817 | V19: 2234468 | W19: 3558748 | X19: 820541
D20: Interest on Soko loan | E20: KSH | F20: =SUM(I20:X20) -> 462 | J20: 0 | K20: 0 | L20: 0 | M20: 0 | N20: 0 | O20: 0 | P20: 0 | Q20: 0 | R20: 0 | S20: 462 | T20: 0 | U20: 0 | V20: 0 | W20: 0 | X20: 0
D21: Interest on Inuka loan | E21: KSH | F21: =SUM(I21:X21) -> 27819848 | I21: 2080121 | J21: 12331979 | K21: 2579733 | L21: 1465103 | M21: 3478907 | N21: 228749 | O21: 1447601 | P21: 1973384 | Q21: 729563 | R21: 34351 | S21: 51715 | T21: 136303 | U21: 94956 | V21: 466017 | W21: 530659 | X21: 190707
D22: Interest on youthbiz loan | E22: KSH | F22: =SUM(I22:X22) -> 655079 | I22: 0 | J22: 0 | K22: 0 | L22: 0 | M22: 0 | N22: 0 | O22: 0 | P22: 0 | Q22: 0 | R22: 0 | S22: 77730 | T22: 44071 | U22: 0 | V22: 23812 | W22: 77039 | X22: 432427
D23: Interest on Kwamua Biashara | E23: KSH | F23: =SUM(I23:X23) -> 33334076 | I23: 4279169 | J23: 2007247 | K23: 213474 | L23: 2829401 | M23: 2178502 | N23: 2465593 | O23: 6231865 | P23: 2178926 | Q23: 1621290 | R23: 3515693 | S23: 603966 | T23: 759876 | U23: 775624 | V23: 1999190 | W23: 986922 | X23: 687338
D24: Interest on Uni-Mobiloan | E24: KSH | F24: =SUM(I24:X24) -> 16175788 | I24: 4262024 | J24: 1695295 | K24: 409789 | L24: 840514 | M24: 1044236 | N24: 471790 | O24: 1132842 | P24: 1220222 | Q24: 577044 | R24: 1784341 | S24: 359953 | T24: 592641 | U24: 314148 | V24: 193104 | W24: 491960 | X24: 785885
B25: x | D25: Total interest on loan Portfolio | E25: KSH | F25: =SUM(F6:F24) -> 862214993 | G25: =H25-F25 -> 121 | H25: 862215114 | I25: =SUM(I6:I24) -> 179755457 | J25: =SUM(J6:J24) -> 153494200 | K25: =SUM(K6:K24) -> 25684786 | L25: =SUM(L6:L24) -> 45967882 | M25: =SUM(M6:M24) -> 81204128 | N25: =SUM(N6:N24) -> 43824206 | O25: =SUM(O6:O24) -> 84434962 | P25: =SUM(P6:P24) -> 49042527 | ... X25: =SUM(X6:X24) -> 7852943
D27: Loan Processing fee | E27: KSH | F27: =SUM(I27:X27) -> 7043623 | I27: 1826701 | J27: 1026000 | K27: 478200 | L27: 465360 | M27: 657621 | N27: 306840 | O27: 604800 | P27: 388900 | Q27: 180301 | R27: 309500 | S27: 122000 | T27: 112400 | U27: 65900 | V27: 106200 | W27: 292500 | X27: 100400
D28: Other loan recovey inome | E28: KSH | F28: =SUM(I28:X28) -> 982165 | I28: 127537 | J28: 270420 | K28: 30600 | L28: 156379 | M28: 40292 | N28: 36908 | O28: 43558 | P28: 81554 | Q28: 0 | R28: 1820 | S28: 99917 | T28: 0 | U28: 6500 | V28: 0 | W28: 86680 | X28: 0
D29: Ledger fee on loans | E29: KSH | F29: =SUM(I29:X29) -> 17946295 | I29: 2259281 | J29: 3184638 | K29: 596684 | L29: 1561677 | M29: 1388786 | N29: 1240277 | O29: 1132523 | P29: 1553610 | Q29: 1006337 | R29: 1167145 | S29: 635331 | T29: 366810 | U29: 292552 | V29: 235457 | W29: 1097526 | X29: 227661
D30: Ledger fee on MFI loan | E30: KSH | F30: =SUM(I30:X30) -> 3226089 | I30: 149131 | J30: 249251 | K30: 13521 | L30: 321981 | M30: 123537 | N30: 316273 | O30: 1268089 | P30: 595852 | Q30: 148231 | R30: 39263 | S30: 0 | T30: 0 | U30: 0 | V30: 0 | W30: 960 | X30: 0
D31: MFI loan procesing fee | E31: KSH | F31: =SUM(I31:X31) -> 155250 | I31: 750 | J31: 10400 | K31: 0 | L31: 14000 | M31: 6000 | N31: 19200 | O31: 67700 | P31: 30800 | Q31: 5200 | R31: 800 | S31: 0 | T31: 0 | U31: 0 | V31: 0 | W31: 400 | X31: 0
D32: MFI other incomes | E32: KSH | F32: =SUM(I32:X32) -> 113046 | I32: 500 | J32: 0 | K32: 0 | L32: 21600 | M32: 1500 | N32: 11500 | O32: 42900 | P32: 14500 | Q32: 1000 | R32: 0 | S32: 0 | T32: 0 | U32: 0 | V32: 0 | W32: 19546 | X32: 0
B33: x | D33: Total fees and Commision on loan Portfolio | E33: KSH | F33: =SUM(F27:F32) -> 29466468 | I33: =SUM(I27:I32) -> 4363900 | J33: =SUM(J27:J32) -> 4740709 | K33: =SUM(K27:K32) -> 1119005 | L33: =SUM(L27:L32) -> 2540997 | M33: =SUM(M27:M32) -> 2217736 | N33: =SUM(N27:N32) -> 1930998 | O33: =SUM(O27:O32) -> 3159570 | P33: =SUM(P27:P32) -> 2665216 | ... X33: =SUM(X27:X32) -> 328061
D35: Interest on treasury bonds | E35: KSH | F35: =SUM(I35:X35) -> 12923306 | I35: 1343379 | J35: 3319156 | K35: 1539820 | L35: 790610 | M35: 504593 | N35: 1800768 | O35: 1814793 | P35: 1108086 | Q35: 405534 | R35: 296567 | S35: 0 | T35: 0 | U35: 0 | V35: 0 | W35: 0 | X35: 0
D36: Discount on infrastructure Bonds | E36: KSH | F36: =SUM(I36:X36) -> 458238 | I36: 8413 | J36: 320160 | K36: 8334 | L36: 19501 | M36: 18929 | N36: 9356 | O36: 62697 | P36: 0 | Q36: 10848 | R36: 0 | S36: 0 | T36: 0 | U36: 0 | V36: 0 | W36: 0 | X36: 0
D37: Interest on corporate Bonds | E37: KSH | F37: =SUM(I37:X37) -> 10399992 | G37: 932412 | I37: 0 | J37: 1299996 | K37: 0 | L37: 0 | M37: 2600004 | N37: 1299996 | O37: 1950000 | P37: 1950000 | Q37: 1299996 | R37: 0 | S37: 0 | T37: 0 | U37: 0 | V37: 0 | W37: 0 | X37: 0
D38: Total Government Securities | E38: KSH | F38: =SUM(F35:F37) -> 23781536 | H38: =F38+SUM(G35:G37) -> 24713948 | I38: =SUM(I35:I37) -> 1351792 | J38: =SUM(J35:J37) -> 4939312 | K38: =SUM(K35:K37) -> 1548154 | L38: =SUM(L35:L37) -> 810111 | M38: =SUM(M35:M37) -> 3123526 | N38: =SUM(N35:N37) -> 3110120 | O38: =SUM(O35:O37) -> 3827490 | P38: =SUM(P35:P37) -> 3058086 | ... X38: =SUM(X35:X37) -> 0
D40: Interest on fixed deposit | E40: KSH | F40: =SUM(I40:X40) -> 80499628 | G40: 95655891 | I40: 1520241 | J40: 35715659 | K40: 10036352 | L40: 0 | M40: 23382442 | N40: 0 | O40: 7312361 | P40: 0 | Q40: 0 | R40: 2532573 | S40: 0 | T40: 0 | U40: 0 | V40: 0 | W40: 0 | X40: 0
D41: Interest on call deposit | E41: KSH | F41: =SUM(I41:X41) -> 5081574 | G41: 370939 | I41: 0 | J41: 3321637 | K41: 0 | L41: 0 | M41: 1759932 | N41: 0 | O41: 5 | P41: 0 | Q41: 0 | R41: 0 | S41: 0 | T41: 0 | U41: 0 | V41: 0 | W41: 0 | X41: 0
B42: x | D42: Total deposit with bank | E42: KSH | F42: =SUM(F40:F41) -> 85581202 | H42: =F42+SUM(G40:G41) -> 181608032 | I42: =SUM(I40:I41) -> 1520241 | J42: =SUM(J40:J41) -> 39037296 | K42: =SUM(K40:K41) -> 10036352 | L42: =SUM(L40:L41) -> 0 | M42: =SUM(M40:M41) -> 25142374 | N42: =SUM(N40:N41) -> 0 | O42: =SUM(O40:O41) -> 7312366 | P42: =SUM(P40:P41) -> 0 | ... X42: =SUM(X40:X41) -> 0
D44: Interest Income From Financial Investment | E44: KSH | F44: =SUM(I44:X44) -> 109362738 | H44: =H38+H42 -> 206321980 | I44: =I38+I42 -> 2872033 | J44: =J38+J42 -> 43976608 | K44: =K38+K42 -> 11584506 | L44: =L38+L42 -> 810111 | M44: =M38+M42 -> 28265900 | N44: =N38+N42 -> 3110120 | O44: =O38+O42 -> 11139856 | ... X44: =X38+X42 -> 0
D46: Salary Processiong Charges | E46: KSH | F46: =SUM(I46:X46) -> 7773364 | I46: 1066205 | J46: 1381009 | K46: 586700 | L46: 807860 | M46: 1596829 | N46: 206250 | O46: 955670 | P46: 601200 | Q46: 171900 | R46: 89100 | S46: 16200 | T46: 36500 | U46: 57300 | V46: 100186 | W46: 74855 | X46: 25600
D47: Withdrawal transaction charge | E47: KSH | F47: =SUM(I47:X47) -> 25616170 | I47: 2418368 | J47: 4174850 | K47: 1618735 | L47: 1978192 | M47: 3679478 | N47: 1173449 | O47: 1833247 | P47: 2490960 | Q47: 806738 | R47: 904642 | S47: 935583 | T47: 289421 | U47: 688189 | V47: 543603 | W47: 1636584 | X47: 444131
D48: Mobile Banking cash withdrawal and notification charge | E48: KSH | F48: =SUM(I48:X48) -> 17052437 | I48: 1560102 | J48: 1926318 | K48: 525833 | L48: 1148015 | M48: 1883002 | N48: 818311 | O48: 1766903 | P48: 1763913 | Q48: 795352 | R48: 1743682 | S48: 466878 | T48: 595525 | U48: 520622 | V48: 271543 | W48: 742377 | X48: 524061
D49: Ledger fee on charging customers | E49: KSH | F49: =SUM(I49:X49) -> 14326729 | I49: 906960 | J49: 3471664 | K49: 736169 | L49: 1170404 | M49: 2773466 | N49: 581788 | O49: 1478325 | P49: 1445645 | Q49: 455554 | R49: 438735 | S49: 118656 | T49: 134879 | U49: 190364 | V49: 175691 | W49: 141923 | X49: 106506
D50: Other Operating Income | E50: KSH | F50: =SUM(I50:X50) -> 25711184 | G50: =12834183+44037006+28344 -> 56899533 | I50: =7995760-SUM(I46:I49) -> 2044125 | J50: =16849136-SUM(J46:J49) -> 5895295 | K50: =5392603-SUM(K46:K49) -> 1925166 | L50: =6712854-SUM(L46:L49) -> 1608383 | M50: =13650464-SUM(M46:M49) -> 3717689 | N50: =3318921-SUM(N46:N49) -> 539123 | O50: =8137135-SUM(O46:O49) -> 2102990 | P50: =8521633-SUM(P46:P49) -> 2219915 | Q50: =2932118-SUM(Q46:Q49) -> 702574 | R50: =3944202-SUM(R46:R49) -> 768043 | S50: =2653462-SUM(S46:S49) -> 1116145 | T50: =1563915-SUM(T46:T49) -> 507590 | U50: =1983367-SUM(U46:U49) -> 526892 | V50: =1393672-SUM(V46:V49) -> 302649 | W50: =3911967-SUM(W46:W49) -> 1316228 | X50: =1518675-SUM(X46:X49) -> 418377
D51: Total other operating income | E51: KSH | F51: =SUM(F46:F50) -> 90479884 | H51: =F51+SUM(G46:G50) -> 147379417 | I51: =SUM(I46:I50) -> 7995760 | J51: =SUM(J46:J50) -> 16849136 | K51: =SUM(K46:K50) -> 5392603 | L51: =SUM(L46:L50) -> 6712854 | M51: =SUM(M46:M50) -> 13650464 | N51: =SUM(N46:N50) -> 3318921 | O51: =SUM(O46:O50) -> 8137135 | P51: =SUM(P46:P50) -> 8521633 | ... X51: =SUM(X46:X50) -> 1518675
D53: Other Income | E53: KSH | F53: 0 | G53: =1249616+232429342 -> 233678958
D55: Total Revenue | E55: KSH | F55: =F25+F33+F38+F42+F51+F53 -> 1091524083 | G55: =SUM(G6:G53) -> 387537854 | H55: =F55+G55 -> 1479061937 | I55: =I25+I33+I38+I42+I51 -> 194987150 | J55: =J25+J33+J38+J42+J51 -> 219060653 | K55: =K25+K33+K38+K42+K51 -> 43780900 | L55: =L25+L33+L38+L42+L51 -> 56031844 | M55: =M25+M33+M38+M42+M51 -> 125338228 | N55: =N25+N33+N38+N42+N51 -> 52184245 | O55: =O25+O33+O38+O42+O51 -> 106871523 | P55: =P25+P33+P38+P42+P51 -> 63287462 | ... X55: =X25+X33+X38+X42+X51 -> 9699679
D57: Interest on savings | E57: KSH | F57: =SUM(I57:X57) -> -194768850 | I57: -33648430 | J57: -23367599 | K57: -4955972 | L57: -14022858 | M57: -27661694 | N57: -8128183 | O57: -20806895 | P57: -22190926 | Q57: -12317046 | R57: -12429948 | S57: -706969 | T57: -5031036 | U57: -2036704 | V57: -2791330 | W57: -3371011 | X57: -1302249
D58: Interest on fixed deposits | E58: KSH | F58: =SUM(I58:X58) -> -10650246 | I58: -1004831 | J58: -330459 | K58: -241483 | L58: -164089 | M58: -6069629 | N58: -1225711 | O58: -562186 | P58: -573312 | Q58: -145306 | R58: 0 | S58: 0 | T58: -295472 | U58: 0 | V58: -36664 | W58: 0 | X58: -1104
D59: Interest on Diaspora jijenge savings | E59: KSH | F59: =SUM(I59:X59) -> -2650123 | I59: -2381215 | J59: -6457 | K59: 0 | L59: 0 | M59: -262451 | N59: 0 | O59: 0 | P59: 0 | Q59: 0 | R59: 0 | S59: 0 | T59: 0 | U59: 0 | V59: 0 | W59: 0 | X59: 0
D60: Total interest expense on deposits | E60: KSH | F60: =SUM(F57:F59) -> -208069219 | I60: =SUM(I57:I59) -> -37034476 | J60: =SUM(J57:J59) -> -23704515 | K60: =SUM(K57:K59) -> -5197455 | L60: =SUM(L57:L59) -> -14186947 | M60: =SUM(M57:M59) -> -33993774 | N60: =SUM(N57:N59) -> -9353894 | O60: =SUM(O57:O59) -> -21369081 | P60: =SUM(P57:P59) -> -22764238 | ... X60: =SUM(X57:X59) -> -1303353
D62: Mobile deposit charges paybill | E62: KSH | F62: =SUM(I62:X62) -> -10966219 | I62: -1003766 | J62: -778998 | K62: -245685 | L62: -759332 | M62: -939750 | N62: -764353 | O62: -1146814 | P62: -1184443 | Q62: -731231 | R62: -987780 | S62: -415480 | T62: -385482 | U62: -459435 | V62: -331813 | W62: -509345 | X62: -322512
D63: loss impairement of financial assets | E63: KSH | F63: =SUM(I63:X63) -> -21178647 | I63: 0 | J63: -7294511 | K63: -13884136 | L63: 0 | M63: 0 | N63: 0 | O63: 0 | P63: 0 | Q63: 0 | R63: 0 | S63: 0 | T63: 0 | U63: 0 | V63: 0 | W63: 0 | X63: 0
D64: Appraisal fee | E64: KSH | F64: =SUM(I64:X64) -> -24809401 | I64: -3267903 | J64: -1442686 | K64: -151990 | L64: -2298113 | M64: -1561783 | N64: -1834200 | O64: -4530458 | P64: -2048870 | Q64: -1195368 | R64: -2373983 | S64: -432332 | T64: -463260 | U64: -521962 | V64: -1529338 | W64: -678339 | X64: -478816
D65: Other Expenses | E65: KSH | F65: =SUM(I65:X65) -> -875964 | G65: =-13718475 -> -13718475 | I65: 2677 | J65: -146397 | K65: -26932 | L65: -94496 | M65: -277654 | N65: -688 | O65: -138046 | P65: -2306 | Q65: -10433 | R65: -15451 | S65: -160522 | T65: =963-5003 -> -4040 | U65: 17618 | V65: -2148 | W65: -8520 | X65: -8626
D66: Total fees and commission expenses | E66: KSH | F66: =SUM(F62:F65) -> -57830231 | H66: =F66+SUM(G62:G65) -> -71548706 | I66: =SUM(I62:I65) -> -4268992 | J66: =SUM(J62:J65) -> -9662592 | K66: =SUM(K62:K65) -> -14308743 | L66: =SUM(L62:L65) -> -3151941 | M66: =SUM(M62:M65) -> -2779187 | N66: =SUM(N62:N65) -> -2599241 | O66: =SUM(O62:O65) -> -5815318 | P66: =SUM(P62:P65) -> -3235619 | ... X66: =SUM(X62:X65) -> -809954
D68: Other Expenses | E68: KSH | F68: =SUM(I68:X68) -> -765718 | I68: -1710 | J68: -72150 | K68: 0 | L68: 0 | M68: 0 | N68: 0 | O68: -475580 | P68: -1500 | Q68: 0 | R68: -208778 | S68: -4000 | T68: 0 | U68: -2000 | V68: 0 | W68: 0 | X68: 0
D70: Total Provision for Loan Losses | E70: KSH | F70: =SUM(I70:X70) -> -54165271 | G70: =-(5217191+3002803) -> -8219994 | H70: =F70+G70 -> -62385265 | I70: -9306992 | J70: -1376133 | K70: -8926505 | L70: -4320139 | M70: -5193101 | N70: -1801070 | O70: -402807 | P70: 1804419 | Q70: -21349660 | R70: 661467 | S70: 2341477 | T70: -578459 | U70: -4427575 | V70: -1246911 | W70: 523732 | X70: -567014
D72: Staff salaries | E72: KSH | F72: =SUM(I72:X72) -> -99004652 | I72: -7311965 | J72: -9459269 | K72: -5640867 | L72: -7727244 | M72: -13107328 | N72: -6270802 | O72: -10416504 | P72: -7185464 | Q72: -5873101 | R72: -5940236 | S72: -3955291 | T72: -3344053 | U72: -3360082 | V72: -3069839 | W72: -3935531 | X72: -2407076
D73: House alowance | E73: KSH | F73: =SUM(I73:X73) -> -23173335 | I73: -1702861 | J73: -2231848 | K73: -1345843 | L73: -1807628 | M73: -3147262 | N73: -1492942 | O73: -2561669 | P73: -1726188 | Q73: -1334628 | R73: -1345285 | S73: -859239 | T73: -739547 | U73: -729875 | V73: -740803 | W73: -869113 | X73: -538604
D74: Other personnel expenses | E74: KSH | F74: =SUM(I74:X74) -> -54734958 | I74: =-13781864-SUM(I72:I73) -> -4767038 | J74: =-16385063-SUM(J72:J73) -> -4693946 | K74: =-9793085-SUM(K72:K73) -> -2806375 | L74: =-13621346-SUM(L72:L73) -> -4086474 | M74: =-21912184-SUM(M72:M73) -> -5657594 | N74: =-10791933-SUM(N72:N73) -> -3028189 | O74: =-19197749-SUM(O72:O73) -> -6219576 | P74: =-10739262-SUM(P72:P73) -> -1827610 | Q74: =-9988589-SUM(Q72:Q73) -> -2780860 | R74: =-11663475-SUM(R72:R73) -> -4377954 | S74: =-8073736-SUM(S72:S73) -> -3259206 | T74: =-6358615-SUM(T72:T73) -> -2275015 | U74: =-6098958-SUM(U72:U73) -> -2009001 | V74: =-5401588-SUM(V72:V73) -> -1590946 | W74: =-8426996-SUM(W72:W73) -> -3622352 | X74: =-4678502-SUM(X72:X73) -> -1732822
D75: Total personnel expenses | E75: KSH | F75: =SUM(F72:F74) -> -176912945 | G75: =H75-F75 -> -117427451 | H75: -294340396 | I75: =SUM(I72:I74) -> -13781864 | J75: =SUM(J72:J74) -> -16385063 | K75: =SUM(K72:K74) -> -9793085 | L75: =SUM(L72:L74) -> -13621346 | M75: =SUM(M72:M74) -> -21912184 | N75: =SUM(N72:N74) -> -10791933 | O75: =SUM(O72:O74) -> -19197749 | P75: =SUM(P72:P74) -> -10739262 | ... X75: =SUM(X72:X74) -> -4678502
D77: Total governance Expenses | E77: KSH | F77: =SUM(I77:X77) -> -47313870 | G77: -3065194 | H77: =F77+G77 -> -50379064 | I77: -5905791 | J77: -9489309 | K77: -2365646 | L77: -2972638 | M77: -7784156 | N77: -2419179 | O77: -4731275 | P77: -3449742 | Q77: -2338878 | R77: -1812212 | S77: -1365856 | T77: -446382 | U77: -442833 | V77: -450899 | W77: -1339074 | X77: 0
D79: Total Marketing Expenses | E79: KSH | F79: =SUM(I79:X79) -> -2474757 | G79: -22216087 | H79: =F79+G79 -> -24690844 | I79: -148000 | J79: -245285 | K79: -207790 | L79: -187300 | M79: -28765 | N79: -119760 | O79: -201200 | P79: -118595 | Q79: -152719 | R79: -106330 | S79: -155654 | T79: -165236 | U79: -59235 | V79: -145487 | W79: -100145 | X79: -333256
D81: Total Depreciation and amortization | E81: KSH | F81: =SUM(I81:X81) -> -3305308 | G81: -20619332 | H81: =F81+G81 -> -23924640 | I81: -157339 | J81: -148949 | K81: -180799 | L81: -166236 | M81: -280815 | N81: -236161 | O81: -254148 | P81: -362583 | Q81: -193491 | R81: -296090 | S81: -176505 | T81: -104507 | U81: -69830 | V81: -193037 | W81: -240461 | X81: -244357
D83: Security | E83: KSH | F83: =SUM(I83:X83) -> -27026462 | G83: -4522800 | I83: -1707385 | J83: -1769120 | K83: -1827828 | L83: -1902920 | M83: -2025434 | N83: -1828120 | O83: -1744050 | P83: -1814842 | Q83: -1829102 | R83: -1826470 | S83: -1645928 | T83: -1394481 | U83: -1328301 | V83: -1503611 | W83: -1636820 | X83: -1242050
D84: Other Admin Expenses | E84: KSH | F84: =SUM(I84:X84) -> -54136686 | G84: =-78625049-G83 -> -74102249 | I84: =-6521573-I83 -> -4814188 | J84: =-6092452-J83 -> -4323332 | K84: =-4305313-K83 -> -2477485 | L84: =-4632124-L83 -> -2729204 | M84: =-7406959-M83 -> -5381525 | N84: =-5266507-N83 -> -3438387 | O84: =-5243225-O83 -> -3499175 | P84: =-6120178-P83 -> -4305336 | Q84: =-6312577-Q83 -> -4483475 | R84: =-6582752-R83 -> -4756282 | S84: =-4034689-S83 -> -2388761 | T84: =-5125330-T83 -> -3730849 | U84: =-2987737-U83 -> -1659436 | V84: =-2702674-V83 -> -1199063 | W84: =-3704309-W83 -> -2067489 | X84: =-4124749-X83 -> -2882699
D85: Total Admin expenses | E85: KSH | F85: =SUM(F83:F84) -> -81163148 | H85: =F85+SUM(G83:G84) -> -159788197 | I85: =SUM(I83:I84) -> -6521573 | J85: =SUM(J83:J84) -> -6092452 | K85: =SUM(K83:K84) -> -4305313 | L85: =SUM(L83:L84) -> -4632124 | M85: =SUM(M83:M84) -> -7406959 | N85: =SUM(N83:N84) -> -5266507 | O85: =SUM(O83:O84) -> -5243225 | P85: =SUM(P83:P84) -> -6120178 | ... X85: =SUM(X83:X84) -> -4124749
D87: Total Expenses | E87: KSH | F87: =F60+F66+F68+F70+F75+F77+F79+F81+F85 -> -632000467 | G87: =SUM(G57:G85) -> -263891582 | H87: =F87+G87 -> -895892049 | I87: =I60+I66+I68+I70+I75+I77+I79+I81+I85 -> -77126737 | J87: =J60+J66+J68+J70+J75+J77+J79+J81+J85 -> -67176448 | K87: =K60+K66+K68+K70+K75+K77+K79+K81+K85 -> -45285336 | L87: =L60+L66+L68+L70+L75+L77+L79+L81+L85 -> -43238671 | M87: =M60+M66+M68+M70+M75+M77+M79+M81+M85 -> -79378941 | N87: =N60+N66+N68+N70+N75+N77+N79+N81+N85 -> -32587745 | O87: =O60+O66+O68+O70+O75+O77+O79+O81+O85 -> -57690383 | P87: =P60+P66+P68+P70+P75+P77+P79+P81+P85 -> -44987298 | ... X87: =X60+X66+X68+X70+X75+X77+X79+X81+X85 -> -12061185
D89: Banking Operating Profit | E89: KSH | F89: =F55+F87 -> 459523616 | I89: =I55+I87 -> 117860413 | J89: =J55+J87 -> 151884205 | K89: =K55+K87 -> -1504436 | L89: =L55+L87 -> 12793173 | M89: =M55+M87 -> 45959287 | N89: =N55+N87 -> 19596500 | O89: =O55+O87 -> 49181140 | P89: =P55+P87 -> 18300164 | ... X89: =X55+X87 -> -2361506
D92: Contribution % or share of total
D94: =D6 -> Interest on short term loan me | E94: % of Totals | F94: =F6/$F6 -> 1 | I94: =I6/$F6 -> 0.053289504 | J94: =J6/$F6 -> 0.26121896 | K94: =K6/$F6 -> 0.067262469 | L94: =L6/$F6 -> 0.051444579 | M94: =M6/$F6 -> 0.12716887 | N94: =N6/$F6 -> 0.01557373 | O94: =O6/$F6 -> 0.047462941 | P94: =P6/$F6 -> 0.040909896 | ... X94: =X6/$F6 -> 0.0021620759
D95: =D7 -> Interest on short term loan Cu | E95: % of Totals | F95: =F7/$F7 -> 1 | I95: =I7/$F7 -> 0.10363172 | J95: =J7/$F7 -> 0.091227165 | K95: =K7/$F7 -> 0.023254389 | L95: =L7/$F7 -> 0.099644279 | M95: =M7/$F7 -> 0.11085627 | N95: =N7/$F7 -> 0.076068321 | O95: =O7/$F7 -> 0.084455697 | P95: =P7/$F7 -> 0.090815148 | ... X95: =X7/$F7 -> 0.014310156
D96: =D8 -> Interest on medium term loan m | E96: % of Totals | F96: =F8/$F8 -> 1 | I96: =I8/$F8 -> 0.043739264 | J96: =J8/$F8 -> 0.53714919 | K96: =K8/$F8 -> 0.030223695 | L96: =L8/$F8 -> 0.027828389 | M96: =M8/$F8 -> 0.16977483 | N96: =N8/$F8 -> 0.0049326179 | O96: =O8/$F8 -> 0.033101169 | P96: =P8/$F8 -> 0.093033488 | ... X96: =X8/$F8 -> 0.0015070646
D97: =D9 -> Interest on medium term loan C | E97: % of Totals | F97: =F9/$F9 -> 1 | I97: =I9/$F9 -> 0.17895589 | J97: =J9/$F9 -> 0.1471283 | K97: =K9/$F9 -> 0.0094605826 | L97: =L9/$F9 -> 0.056161911 | M97: =M9/$F9 -> 0.092957994 | N97: =N9/$F9 -> 0.087986009 | O97: =O9/$F9 -> 0.13143407 | P97: =P9/$F9 -> 0.043757261 | ... X97: =X9/$F9 -> 0.0057639577
D98: =D10 -> Interest on staff loan | E98: % of Totals | F98: =F10/$F10 -> 1 | I98: =I10/$F10 -> 1 | J98: =J10/$F10 -> 0 | K98: =K10/$F10 -> 0 | L98: =L10/$F10 -> 0 | M98: =M10/$F10 -> 0 | N98: =N10/$F10 -> 0 | O98: =O10/$F10 -> 0 | P98: =P10/$F10 -> 0 | ... X98: =X10/$F10 -> 0
D99: =D11 -> Interest on development loan soc | E99: % of Totals | F99: =F11/$F11 -> 1 | I99: =I11/$F11 -> 0.27161142 | J99: =J11/$F11 -> 0.18365502 | K99: =K11/$F11 -> 0.002181475 | L99: =L11/$F11 -> 0 | M99: =M11/$F11 -> 0 | N99: =N11/$F11 -> 0 | O99: =O11/$F11 -> 0.16846427 | P99: =P11/$F11 -> 0 | ... X99: =X11/$F11 -> 0
D100: =D12 -> Interest on overdraft members | E100: % of Totals | F100: =F12/$F12 -> 1 | I100: =I12/$F12 -> 0.43445173 | J100: =J12/$F12 -> 0 | K100: =K12/$F12 -> 0 | L100: =L12/$F12 -> 0.096392447 | M100: =M12/$F12 -> 0.04183192 | N100: =N12/$F12 -> 0.014574755 | O100: =O12/$F12 -> 0.11549707 | P100: =P12/$F12 -> 0.0055942946 | ... X100: =X12/$F12 -> 0.0082037473
D101: =D13 -> Interest on Overdue loan | E101: % of Totals | F101: =F13/$F13 -> 1 | I101: =I13/$F13 -> 0.10315964 | J101: =J13/$F13 -> 0.2288685 | K101: =K13/$F13 -> 0.064603933 | L101: =L13/$F13 -> 0.1671296 | M101: =M13/$F13 -> 0.2362802 | N101: =N13/$F13 -> 0.0075602697 | O101: =O13/$F13 -> 0.15167031 | P101: =P13/$F13 -> 0.040727543 | ... X101: =X13/$F13 -> 0
D102: =D14 -> Advance interest | E102: % of Totals | F102: =F14/$F14 -> 1 | I102: =I14/$F14 -> 0.16718886 | J102: =J14/$F14 -> 0.20194856 | K102: =K14/$F14 -> 0.039581047 | L102: =L14/$F14 -> 0.066668996 | M102: =M14/$F14 -> 0.11434275 | N102: =N14/$F14 -> 0.031131913 | O102: =O14/$F14 -> 0.090735675 | P102: =P14/$F14 -> 0.053605788 | ... X102: =X14/$F14 -> 0.018730362
D103: =D15 -> Interest on shirika loan | E103: % of Totals | F103: =F15/$F15 -> 1 | I103: =I15/$F15 -> 0.00063618673 | J103: =J15/$F15 -> 0 | K103: =K15/$F15 -> 6.8337193e-05 | L103: =L15/$F15 -> 0.043704657 | M103: =M15/$F15 -> 0.020642249 | N103: =N15/$F15 -> 0.22540605 | O103: =O15/$F15 -> 0.26292805 | P103: =P15/$F15 -> 0.12548894 | ... X103: =X15/$F15 -> 0.0027432502
D104: =D16 -> Interest on bonus advance loan | E104: % of Totals | F104: =F16/$F16 -> 1 | I104: =I16/$F16 -> 0 | J104: =J16/$F16 -> 0.46980503 | K104: =K16/$F16 -> 0.3982856 | L104: =L16/$F16 -> 0.027085804 | M104: =M16/$F16 -> 0.016548712 | N104: =N16/$F16 -> 0 | O104: =O16/$F16 -> 0 | P104: =P16/$F16 -> 0 | ... X104: =X16/$F16 -> 0.011340684
D105: =D17 -> Interest on Premium Financing | E105: % of Totals | F105: =F17/$F17 -> 1 | I105: =I17/$F17 -> 0.061610878 | J105: =J17/$F17 -> 0.32397533 | K105: =K17/$F17 -> 0.01887689 | L105: =L17/$F17 -> 0.027658667 | M105: =M17/$F17 -> 0 | N105: =N17/$F17 -> 0.00062486436 | O105: =O17/$F17 -> 0 | P105: =P17/$F17 -> 0.12128355 | ... X105: =X17/$F17 -> 0
... D130: =D42 -> Total deposit with bank | E130: % of Totals | F130: =F42/$F42 -> 1 | I130: =I42/$F42 -> 0.017763726 | J130: =J42/$F42 -> 0.45614335 | K130: =K42/$F42 -> 0.11727286 | L130: =L42/$F42 -> 0 | M130: =M42/$F42 -> 0.29378384 | N130: =N42/$F42 -> 0 | O130: =O42/$F42 -> 0.0854436 | P130: =P42/$F42 -> 0 | ... X130: =X42/$F42 -> 0
D132: =CONCATENATE(D44, " (Bank + Govnt)") -> Interest Income From Financial Investment (Bank + Govnt) | E132: % of Totals | F132: =F44/$F44 -> 1 | I132: =I44/$F44 -> 0.026261532 | J132: =J44/$F44 -> 0.40211693 | K132: =K44/$F44 -> 0.10592736 | L132: =L44/$F44 -> 0.0074075596 | M132: =M44/$F44 -> 0.25846006 | N132: =N44/$F44 -> 0.028438571 | O132: =O44/$F44 -> 0.10186153 | P132: =P44/$F44 -> 0.027962778 | ... X132: =X44/$F44 -> 0
D134: =D46 -> Salary Processiong Charges | E134: % of Totals | F134: =F46/$F46 -> 1 | I134: =I46/$F46 -> 0.13716134 | J134: =J46/$F46 -> 0.17765912 | K134: =K46/$F46 -> 0.075475689 | L134: =L46/$F46 -> 0.10392669 | M134: =M46/$F46 -> 0.20542316 | N134: =N46/$F46 -> 0.026532914 | O134: =O46/$F46 -> 0.12294162 | P134: =P46/$F46 -> 0.077341033 | ... X134: =X46/$F46 -> 0.0032932975
D135: =D47 -> Withdrawal transaction charge | E135: % of Totals | F135: =F47/$F47 -> 1 | I135: =I47/$F47 -> 0.094407868 | J135: =J47/$F47 -> 0.16297714 | K135: =K47/$F47 -> 0.063191921 | L135: =L47/$F47 -> 0.077224347 | M135: =M47/$F47 -> 0.14363888 | N135: =N47/$F47 -> 0.045808917 | O135: =O47/$F47 -> 0.071566007 | P135: =P47/$F47 -> 0.097241703 | ... X135: =X47/$F47 -> 0.017337916
D136: =D48 -> Mobile Banking cash withdrawal and notification charge | E136: % of Totals | F136: =F48/$F48 -> 1 | I136: =I48/$F48 -> 0.091488507 | J136: =J48/$F48 -> 0.11296438 | K136: =K48/$F48 -> 0.030836238 | L136: =L48/$F48 -> 0.067322635 | M136: =M48/$F48 -> 0.11042422 | N136: =N48/$F48 -> 0.047987921 | O136: =O48/$F48 -> 0.10361586 | P136: =P48/$F48 -> 0.10344052 | ... X136: =X48/$F48 -> 0.030732323
D137: =D49 -> Ledger fee on charging customers | E137: % of Totals | F137: =F49/$F49 -> 1 | I137: =I49/$F49 -> 0.063305448 | J137: =J49/$F49 -> 0.24232077 | K137: =K49/$F49 -> 0.051384304 | L137: =L49/$F49 -> 0.081693735 | M137: =M49/$F49 -> 0.19358683 | N137: =N49/$F49 -> 0.040608572 | O137: =O49/$F49 -> 0.1031865 | P137: =P49/$F49 -> 0.10090545 | ... X137: =X49/$F49 -> 0.0074340765
D138: =D50 -> Other Operating Income | E138: % of Totals | F138: =F50/$F50 -> 1 | I138: =I50/$F50 -> 0.07950334 | J138: =J50/$F50 -> 0.22928913 | K138: =K50/$F50 -> 0.074876598 | L138: =L50/$F50 -> 0.062555773 | M138: =M50/$F50 -> 0.14459424 | N138: =N50/$F50 -> 0.020968424 | O138: =O50/$F50 -> 0.08179281 | P138: =P50/$F50 -> 0.086340442 | ... X138: =X50/$F50 -> 0.016272179
D139: =D51 -> Total other operating income | E139: % of Totals | F139: =F51/$F51 -> 1 | I139: =I51/$F51 -> 0.088370582 | J139: =J51/$F51 -> 0.18621969 | K139: =K51/$F51 -> 0.059600021 | L139: =L51/$F51 -> 0.074191673 | M139: =M51/$F51 -> 0.15086739 | N139: =N51/$F51 -> 0.036681314 | O139: =O51/$F51 -> 0.089933084 | P139: =P51/$F51 -> 0.094182625 | ... X139: =X51/$F51 -> 0.01678467
D141: =D53 -> Other Income | E141: % of Totals | F141: 0 | I141: 0 | J141: 0 | K141: 0 | L141: 0 | M141: 0 | N141: 0 | O141: 0 | P141: 0 | Q141: 0 | R141: 0 | S141: 0 | T141: 0 | U141: 0 | V141: 0 | W141: 0 | X141: 0
D143: =D55 -> Total Revenue | E143: % of Totals | F143: =F55/$F55 -> 1 | I143: =I55/$F55 -> 0.17863752 | J143: =J55/$F55 -> 0.20069246 | K143: =K55/$F55 -> 0.04010988 | L143: =L55/$F55 -> 0.051333585 | M143: =M55/$F55 -> 0.11482864 | N143: =N55/$F55 -> 0.047808606 | O143: =O55/$F55 -> 0.097910366 | P143: =P55/$F55 -> 0.057980821 | ... X143: =X55/$F55 -> 0.0088863628
D145: =D57 -> Interest on savings | E145: % of Totals | F145: =F57/$F57 -> 1 | I145: =I57/$F57 -> 0.17276084 | J145: =J57/$F57 -> 0.11997606 | K145: =K57/$F57 -> 0.025445404 | L145: =L57/$F57 -> 0.071997437 | M145: =M57/$F57 -> 0.14202319 | N145: =N57/$F57 -> 0.041732459 | O145: =O57/$F57 -> 0.10682866 | P145: =P57/$F57 -> 0.11393468 | ... X145: =X57/$F57 -> 0.0066861256
D146: =D58 -> Interest on fixed deposits | E146: % of Totals | F146: =F58/$F58 -> 1 | I146: =I58/$F58 -> 0.094348149 | J146: =J58/$F58 -> 0.031028297 | K146: =K58/$F58 -> 0.022673936 | L146: =L58/$F58 -> 0.015407062 | M146: =M58/$F58 -> 0.56990505 | N146: =N58/$F58 -> 0.11508758 | O146: =O58/$F58 -> 0.052786199 | P146: =P58/$F58 -> 0.053830869 | ... X146: =X58/$F58 -> 0.00010365958
D147: =D59 -> Interest on Diaspora jijenge savings | E147: % of Totals | F147: =F59/$F59 -> 1 | I147: =I59/$F59 -> 0.89852999 | J147: =J59/$F59 -> 0.0024364907 | K147: =K59/$F59 -> 0 | L147: =L59/$F59 -> 0 | M147: =M59/$F59 -> 0.099033517 | N147: =N59/$F59 -> 0 | O147: =O59/$F59 -> 0 | P147: =P59/$F59 -> 0 | ... X147: =X59/$F59 -> 0
D148: =D60 -> Total interest expense on deposits | E148: % of Totals | F148: =F60/$F60 -> 1 | I148: =I60/$F60 -> 0.17799113 | J148: =J60/$F60 -> 0.1139261 | K148: =K60/$F60 -> 0.024979452 | L148: =L60/$F60 -> 0.068183786 | M148: =M60/$F60 -> 0.16337724 | N148: =N60/$F60 -> 0.044955684 | O148: =O60/$F60 -> 0.10270179 | P148: =P60/$F60 -> 0.10940704 | ... X148: =X60/$F60 -> 0.0062640356
D150: =D62 -> Mobile deposit charges paybill | E150: % of Totals | F150: =F62/$F62 -> 1 | I150: =I62/$F62 -> 0.091532551 | J150: =J62/$F62 -> 0.071036152 | K150: =K62/$F62 -> 0.022403802 | L150: =L62/$F62 -> 0.069242827 | M150: =M62/$F62 -> 0.085694987 | N150: =N62/$F62 -> 0.069700687 | O150: =O62/$F62 -> 0.10457697 | P150: =P62/$F62 -> 0.10800833 | ... X150: =X62/$F62 -> 0.02940959
D151: =D63 -> loss impairement of financial assets | E151: % of Totals | F151: =F63/$F63 -> 1 | I151: =I63/$F63 -> 0 | J151: =J63/$F63 -> 0.34442762 | K151: =K63/$F63 -> 0.65557238 | L151: =L63/$F63 -> 0 | M151: =M63/$F63 -> 0 | N151: =N63/$F63 -> 0 | O151: =O63/$F63 -> 0 | P151: =P63/$F63 -> 0 | ... X151: =X63/$F63 -> 0
D152: =D64 -> Appraisal fee | E152: % of Totals | F152: =F64/$F64 -> 1 | I152: =I64/$F64 -> 0.13172035 | J152: =J64/$F64 -> 0.058150779 | K152: =K64/$F64 -> 0.0061263067 | L152: =L64/$F64 -> 0.092630733 | M152: =M64/$F64 -> 0.062951258 | N152: =N64/$F64 -> 0.073931652 | O152: =O64/$F64 -> 0.18261054 | P152: =P64/$F64 -> 0.08258442 | ... X152: =X64/$F64 -> 0.019299781
D153: =D65 -> Other Expenses | E153: % of Totals | F153: =F65/$F65 -> 1 | I153: =I65/$F65 -> -0.0030560617 | J153: =J65/$F65 -> 0.16712673 | K153: =K65/$F65 -> 0.030745556 | L153: =L65/$F65 -> 0.10787658 | M153: =M65/$F65 -> 0.31696965 | N153: =N65/$F65 -> 0.00078542041 | O153: =O65/$F65 -> 0.15759323 | P153: =P65/$F65 -> 0.0026325283 | ... X153: =X65/$F65 -> 0.0098474367
D154: =D66 -> Total fees and commission expenses | E154: % of Totals | F154: =F66/$F66 -> 1 | I154: =I66/$F66 -> 0.073819383 | J154: =J66/$F66 -> 0.16708548 | K154: =K66/$F66 -> 0.2474267 | L154: =L66/$F66 -> 0.054503344 | M154: =M66/$F66 -> 0.048057685 | N154: =N66/$F66 -> 0.044946059 | O154: =O66/$F66 -> 0.10055844 | P154: =P66/$F66 -> 0.055950304 | ... X154: =X66/$F66 -> 0.01400572
...

Sheet 2024 Data
D2: ='2023 Data'!D2 -> K - Unity Data
D3: 2024 | F3: Totals | G3: Other Ops | H3: Totals Net Other Ops | I3: Kiambu | J3: Githunguri | K3: Kagwe | L3: Kiriita | M3: Limuru | N3: Mai mahiu | O3: Kikuyu | P3: Wangige | Q3: Banana | R3: Gikomba | S3: Suswa | T3: Ruaka | U3: Wakimbo | V3: Gikambura | W3: Nairekia Enkare | X3: Kamwangi
C5: Income Statements
D6: ='2023 Data'!D6 -> Interest on short term loan me | E6: KSH | F6: =SUM(I6:X6) -> 40146646 | I6: 1194643 | J6: 10915940 | K6: 2587581 | L6: 2024799 | M6: 4736744 | N6: 606511 | O6: 1860844 | P6: 1719502 | Q6: 97300 | R6: 67193 | S6: 7796372 | T6: 45220 | U6: 244891 | V6: 51214 | W6: 6143438 | X6: 54454
D7: ='2023 Data'!D7 -> Interest on short term loan Cu | E7: KSH | F7: =SUM(I7:X7) -> 60779965 | I7: 5850740 | J7: 5456624 | K7: 1797858 | L7: 5625924 | M7: 6188855 | N7: 5003756 | O7: 5084914 | P7: 6275706 | Q7: 2943526 | R7: 5718916 | S7: 2268686 | T7: 1159984 | U7: 1586825 | V7: 894362 | W7: 3964827 | X7: 958462
D8: ='2023 Data'!D8 -> Interest on medium term loan m | E8: KSH | F8: =SUM(I8:X8) -> 56015978 | I8: 4056571 | J8: 24594940 | K8: 2691897 | L8: 1568972 | M8: 10721361 | N8: 634421 | O8: 3537327 | P8: 5658096 | Q8: 1436353 | R8: 0 | S8: 386485 | T8: 0 | U8: 0 | V8: 297865 | W8: 431690 | X8: 0
D9: ='2023 Data'!D9 -> Interest on medium term loan C | E9: KSH | F9: =SUM(I9:X9) -> 239627084 | I9: 37053073 | J9: 44082137 | K9: 3020109 | L9: 13918980 | M9: 18950326 | N9: 22555964 | O9: 31629586 | P9: 8821027 | Q9: 14490663 | R9: 17202041 | S9: 9652345 | T9: 2029941 | U9: 5909537 | V9: 3242021 | W9: 6363546 | X9: 705788
D10: ='2023 Data'!D10 -> Interest on staff loan | E10: KSH | F10: =SUM(I10:X10) -> 19774041 | I10: 19774041 | J10: 0 | K10: 0 | L10: 0 | M10: 0 | N10: 0 | O10: 0 | P10: 0 | Q10: 0 | R10: 0 | S10: 0 | T10: 0 | U10: 0 | V10: 0 | W10: 0 | X10: 0
D11: ='2023 Data'!D11 -> Interest on development loan soc | E11: KSH | F11: =SUM(I11:X11) -> 10551967 | I11: 3516486 | J11: 0 | K11: 20440 | L11: 1501295 | M11: 0 | N11: 0 | O11: 1591697 | P11: 0 | Q11: 3520682 | R11: 0 | S11: 0 | T11: 0 | U11: 0 | V11: 401367 | W11: 0 | X11: 0
D12: ='2023 Data'!D12 -> Interest on overdraft members + society | E12: KSH | F12: =SUM(I12:X12) -> 19080366 | I12: =0+4016659 -> 4016659 | J12: 414862 | K12: 1826 | L12: 713046 | M12: 1542163 | N12: 133422 | O12: 4553669 | P12: 44205 | Q12: 2293032 | R12: 5038273 | S12: 93322 | T12: -21831 | U12: 206197 | V12: 20213 | W12: 5311 | X12: 25997
D13: ='2023 Data'!D13 -> Interest on Overdue loan | E13: KSH | F13: =SUM(I13:X13) -> 2837299 | I13: 322027 | J13: 556160 | K13: 156712 | L13: 456369 | M13: 754063 | N13: 32240 | O13: 406480 | P13: 153248 | Q13: 0 | R13: 0 | S13: 0 | T13: 0 | U13: 0 | V13: 0 | W13: 0 | X13: 0
D14: ='2023 Data'!D14 -> Advance interest (crop + salary + staff + soko + mfi + raw) | E14: KSH | F14: =SUM(I14:X14) -> 72228964 | I14: =1592191+11408+8933870+73400 -> 10610869 | J14: =1577634+947390+10233088+62800 -> 12820912 | K14: =275663+169386+2445817+1000 -> 2891866 | L14: =1284064+18467+3741901+141400 -> 5185832 | M14: =1768705+233697+5716440+23000 -> 7741842 | N14: =443179+50000+3051715+73000 -> 3617894 | O14: =1408478+26767+5436049+427020 -> 7298314 | P14: =391438+11900+4241501+151620 -> 4796459 | Q14: =231413+3050+2909204+57400 -> 3201067 | R14: =197842+3989167+7400 -> 4194409 | S14: =89932+33000+1777215 -> 1900147 | T14: =79155+1282070 -> 1361225 | U14: =40764+10000+1056309 -> 1107073 | V14: =49942+1202364 -> 1252306 | W14: =471672+453+3100911 -> 3573036 | X14: =87583+588130 -> 675713
D15: ='2023 Data'!D15 -> Interest on shirika loan | E15: KSH | F15: =SUM(I15:X15) -> 5616400 | I15: 0 | J15: 0 | K15: 23129 | L15: 385037 | M15: 145088 | N15: 1072346 | O15: 1492916 | P15: 664086 | Q15: 0 | R15: 0 | S15: 69150 | T15: 0 | U15: 18492 | V15: 0 | W15: 1733405 | X15: 12751
D16: ='2023 Data'!D16 -> Interest on bonus advance loan | E16: KSH | F16: =SUM(I16:X16) -> 16899662 | I16: 0 | J16: 8573909 | K16: 5430744 | L16: 163044 | M16: 966365 | N16: 0 | O16: 0 | P16: 0 | Q16: 0 | R16: 0 | S16: 574834 | T16: 0 | U16: 0 | V16: 0 | W16: 1190766 | X16: 0
D17: ='2023 Data'!D17 -> Interest on Premium Financing + penalty interest (raw + loan recovery) | E17: KSH | F17: =SUM(I17:X17) -> 11223687 | I17: =18601+1797915 -> 1816516 | J17: =1339904+49033 -> 1388937 | K17: 360398 | L17: =20408+898455 -> 918863 | M17: =623125+151485 -> 774610 | N17: =1810+382754 -> 384564 | O17: 1251879 | P17: =787+637934+2000 -> 640721 | Q17: 1640503 | R17: =23881+727705 -> 751586 | S17: =3494+753140 -> 756634 | T17: 200727 | U17: =950+86663 -> 87613 | V17: 39261 | W17: =19761+144463 -> 164224 | X17: 46651
D18: ='2023 Data'!D18 -> Interest on MFI loan | E18: KSH | F18: =SUM(I18:X18) -> 14312981 | I18: 663886 | J18: 1226757 | K18: 78728 | L18: 1621053 | M18: 602916 | N18: 770012 | O18: 5507681 | P18: 2692066 | Q18: 967412 | R18: 128583 | S18: 52437 | T18: 0 | U18: 0 | V18: 0 | W18: 1450 | X18: 0
D19: ='2023 Data'!D19 -> Interest on Jijenge Loan | E19: KSH | F19: =SUM(I19:X19) -> 125287123 | I19: 42398405 | J19: 12678549 | K19: 2129758 | L19: 3252422 | M19: 8450187 | N19: 4767670 | O19: 8160155 | P19: 11037725 | Q19: 11093843 | R19: 11384407 | S19: 163961 | T19: 4448544 | U19: 10157 | V19: 1198054 | W19: 3920445 | X19: 192841
D20: ='2023 Data'!D20 -> Interest on Soko loan | E20: KSH | F20: =SUM(I20:X20) -> 4458 | I20: 0 | J20: 0 | K20: 0 | L20: 0 | M20: 0 | N20: 0 | O20: 0 | P20: 0 | Q20: 0 | R20: 0 | S20: 4458 | T20: 0 | U20: 0 | V20: 0 | W20: 0 | X20: 0
D21: ='2023 Data'!D21 -> Interest on Inuka loan | E21: KSH | F21: =SUM(I21:X21) -> 21847865 | I21: 1049330 | J21: 9731915 | K21: 2378277 | L21: 1361054 | M21: 2570084 | N21: 352818 | O21: 653483 | P21: 1733724 | Q21: 233807 | R21: 26579 | S21: 94353 | T21: 215804 | U21: 61604 | V21: 554994 | W21: 639280 | X21: 190759
D22: ='2023 Data'!D22 -> Interest on youthbiz loan | E22: KSH | F22: =SUM(I22:X22) -> 0 | I22: 0 | J22: 0 | K22: 0 | L22: 0 | M22: 0 | N22: 0 | O22: 0 | P22: 0 | Q22: 0 | R22: 0 | S22: 0 | T22: 0 | U22: 0 | V22: 0 | W22: 0 | X22: 0
D23: ='2023 Data'!D23 -> Interest on Kwamua Biashara | E23: KSH | F23: =SUM(I23:X23) -> 6759860 | I23: 1041047 | J23: 211866 | K23: 50470 | L23: 1367303 | M23: 126489 | N23: 382461 | O23: 1426829 | P23: 250725 | Q23: 215440 | R23: 732326 | S23: 150735 | T23: 79556 | U23: 139795 | V23: 352659 | W23: 169995 | X23: 62164
D24: ='2023 Data'!D24 -> Interest on Uni-Mobiloan | E24: KSH | F24: =SUM(I24:X24) -> 14076704 | I24: 3348134 | J24: 1478861 | K24: 436063 | L24: 637755 | M24: 949767 | N24: 471838 | O24: 1297712 | P24: 666747 | Q24: 557770 | R24: 1771573 | S24: 385488 | T24: 373670 | U24: 223234 | V24: 190601 | W24: 517767 | X24: 769724
B25: x | D25: Total interest on loan Portfolio | E25: KSH | F25: =SUM(F6:F24) -> 737071050 | G25: =H25-F25 -> -1 | H25: 737071049 | I25: =SUM(I6:I24) -> 136712427 | J25: =SUM(J6:J24) -> 134132369 | K25: =SUM(K6:K24) -> 24055856 | L25: =SUM(L6:L24) -> 40701748 | M25: =SUM(M6:M24) -> 65220860 | N25: =SUM(N6:N24) -> 40785917 | O25: =SUM(O6:O24) -> 75753486 | P25: =SUM(P6:P24) -> 45154037 | ... X25: =SUM(X6:X24) -> 3695304
D27: Loan Processing fee | E27: KSH | F27: =SUM(I27:X27) -> 6555824 | I27: 1385400 | J27: 993642 | K27: 456250 | L27: 607000 | M27: 785300 | N27: 289850 | O27: 442781 | P27: 360971 | Q27: 385400 | R27: 186080 | S27: 125100 | T27: 61800 | U27: 56700 | V27: 43600 | W27: 267650 | X27: 108300
D28: Other loan recovey inome | E28: KSH | F28: =SUM(I28:X28) -> 1123218 | I28: 198154 | J28: 2409 | K28: 115172 | L28: 382062 | M28: 15704 | N28: 102463 | O28: 46712 | P28: 45978 | Q28: 27311 | R28: 25 | S28: 89754 | T28: 0 | U28: 5000 | V28: 4000 | W28: 88474 | X28: 0
D29: Ledger fee on loans | E29: KSH | F29: =SUM(I29:X29) -> 21041314 | I29: 2097935 | J29: 5167674 | K29: 1327412 | L29: 1776691 | M29: 2979161 | N29: 1435526 | O29: 1065532 | P29: 1582370 | Q29: 654683 | R29: 1222458 | S29: 542688 | T29: -800882 | U29: 436014 | V29: -83648 | W29: 1341180 | X29: 296520
D30: Ledger fee on MFI loan | E30: KSH | F30: =SUM(I30:X30) -> 3495360 | I30: 166560 | J30: 349920 | K30: 20640 | L30: 403200 | M30: 148800 | N30: 210720 | O30: 1193280 | P30: 769920 | Q30: 183360 | R30: 46560 | S30: 2400 | T30: 0 | U30: 0 | V30: 0 | W30: 0 | X30: 0
D31: MFI loan procesing fee | E31: KSH | F31: =SUM(I31:X31) -> 208700 | I31: 6800 | J31: 8400 | K31: 400 | L31: 17200 | M31: 3600 | N31: 26000 | O31: 87900 | P31: 48800 | Q31: 7200 | R31: 2400 | S31: 0 | T31: 0 | U31: 0 | V31: 0 | W31: 0 | X31: 0
D32: MFI other incomes | E32: KSH | F32: =SUM(I32:X32) -> 213097 | I32: 7195 | J32: 22575 | K32: 111 | L32: 20396 | M32: 8862 | N32: 28635 | O32: 83366 | P32: 24397 | Q32: 3153 | R32: 3347 | S32: 8560 | T32: 0 | U32: 0 | V32: 0 | W32: 0 | X32: 2500
B33: x | D33: Total fees and Commision on loan Portfolio | E33: KSH | F33: =SUM(F27:F32) -> 32637513 | I33: =SUM(I27:I32) -> 3862044 | J33: =SUM(J27:J32) -> 6544620 | K33: =SUM(K27:K32) -> 1919985 | L33: =SUM(L27:L32) -> 3206549 | M33: =SUM(M27:M32) -> 3941427 | N33: =SUM(N27:N32) -> 2093194 | O33: =SUM(O27:O32) -> 2919571 | P33: =SUM(P27:P32) -> 2832436 | ... X33: =SUM(X27:X32) -> 407320
D35: Interest on treasury bonds | E35: KSH | F35: =SUM(I35:X35) -> 13034253 | I35: 1343379 | J35: 3424280 | K35: 1539820 | L35: 790610 | M35: 485896 | N35: 1833459 | O35: 1814795 | P35: 1099913 | Q35: 405534 | R35: 296567 | S35: 0 | T35: 0 | U35: 0 | V35: 0 | W35: 0 | X35: 0
D36: Discount on infrastructure Bonds | E36: KSH | F36: =SUM(I36:X36) -> 234268 | I36: 11270 | J36: 35640 | K36: 11082 | L36: 26002 | M36: 24950 | N36: 12475 | O36: 83595 | P36: 14791 | Q36: 14463 | R36: 0 | S36: 0 | T36: 0 | U36: 0 | V36: 0 | W36: 0 | X36: 0
D37: Interest on corporate Bonds | E37: KSH | F37: =SUM(I37:X37) -> 10399992 | G37: 0 | I37: 0 | J37: 1299996 | K37: 0 | L37: 0 | M37: 2600004 | N37: 1299996 | O37: 1950000 | P37: 1950000 | Q37: 1299996 | R37: 0 | S37: 0 | T37: 0 | U37: 0 | V37: 0 | W37: 0 | X37: 0
D38: Interest on Wealth C deposits | E38: KSH | F38: =SUM(I38:X38) -> 10365 | I38: 0 | J38: 0 | K38: 0 | L38: 0 | M38: 10365 | N38: 0 | O38: 0 | P38: 0 | Q38: 0 | R38: 0 | S38: 0 | T38: 0 | U38: 0 | V38: 0 | W38: 0 | X38: 0
D39: Total Government Securities | E39: KSH | F39: =SUM(F35:F38) -> 23678878 | H39: =F39+SUM(G35:G37) -> 23678878 | I39: =SUM(I35:I38) -> 1354649 | J39: =SUM(J35:J38) -> 4759916 | K39: =SUM(K35:K38) -> 1550902 | L39: =SUM(L35:L38) -> 816612 | M39: =SUM(M35:M38) -> 3121215 | N39: =SUM(N35:N38) -> 3145930 | O39: =SUM(O35:O38) -> 3848390 | P39: =SUM(P35:P38) -> 3064704 | ... X39: =SUM(X35:X38) -> 0
D41: Interest on fixed deposit | E41: KSH | F41: =SUM(I41:X41) -> 66730025 | G41: 0 | I41: 0 | J41: 36171461 | K41: 5099004 | L41: 0 | M41: 18271857 | N41: 0 | O41: 7187703 | P41: 0 | Q41: 0 | R41: 0 | S41: 0 | T41: 0 | U41: 0 | V41: 0 | W41: 0 | X41: 0
D42: Interest on call deposit | E42: KSH | F42: =SUM(I42:X42) -> 19020729 | G42: 0 | I42: 445902 | J42: 17946663 | K42: 0 | L42: 0 | M42: 628164 | N42: 0 | O42: 0 | P42: 0 | Q42: 0 | R42: 0 | S42: 0 | T42: 0 | U42: 0 | V42: 0 | W42: 0 | X42: 0
B43: x | D43: Total deposit with bank | E43: KSH | F43: =SUM(F41:F42) -> 85750754 | H43: =F43+SUM(G41:G42) -> 85750754 | I43: =SUM(I41:I42) -> 445902 | J43: =SUM(J41:J42) -> 54118124 | K43: =SUM(K41:K42) -> 5099004 | L43: =SUM(L41:L42) -> 0 | M43: =SUM(M41:M42) -> 18900021 | N43: =SUM(N41:N42) -> 0 | O43: =SUM(O41:O42) -> 7187703 | P43: =SUM(P41:P42) -> 0 | ... X43: =SUM(X41:X42) -> 0
D45: Interest Income From Financial Investment | E45: KSH | F45: =SUM(I45:X45) -> 109429632 | H45: =H39+H43 -> 109429632 | I45: =I39+I43 -> 1800551 | J45: =J39+J43 -> 58878040 | K45: =K39+K43 -> 6649906 | L45: =L39+L43 -> 816612 | M45: =M39+M43 -> 22021236 | N45: =N39+N43 -> 3145930 | O45: =O39+O43 -> 11036093 | ... X45: =X39+X43 -> 0
D47: Salary Processiong Charges | E47: KSH | F47: =SUM(I47:X47) -> 10131507 | I47: 1144750 | J47: 2127936 | K47: 1266734 | L47: 868283 | M47: 1988621 | N47: 228216 | O47: 1023338 | P47: 675330 | Q47: 166650 | R47: 122341 | S47: 23318 | T47: 37500 | U47: 49900 | V47: 89904 | W47: 116048 | X47: 202638
D48: Withdrawal transaction charge | E48: KSH | F48: =SUM(I48:X48) -> 27360908 | I48: 2237089 | J48: 4478355 | K48: 1786581 | L48: 2164882 | M48: 4863787 | N48: 1327674 | O48: 1991857 | P48: 2489435 | Q48: 796300 | R48: 1022163 | S48: 795604 | T48: 239893 | U48: 744541 | V48: 520100 | W48: 1432794 | X48: 469853
D49: Mobile Banking cash withdrawal and notification charge | E49: KSH | F49: =SUM(I49:X49) -> 12984431 | I49: =832892+347221 -> 1180113 | J49: =602718+237848 -> 840566 | K49: =76454+85439 -> 161893 | L49: =511425+185479 -> 696904 | M49: =869413+324509 -> 1193922 | N49: =459140+162836 -> 621976 | O49: =1482949+313798 -> 1796747 | P49: =1150783+419931 -> 1570714 | Q49: =477161+117271 -> 594432 | R49: =1340639+254238 -> 1594877 | S49: =252089+110300 -> 362389 | T49: =339045+57974 -> 397019 | U49: =397089+97199 -> 494288 | V49: =185133+54531 -> 239664 | W49: =555023+183026 -> 738049 | X49: =418418+82460 -> 500878
D50: Ledger fee on charging customers | E50: KSH | F50: =SUM(I50:X50) -> 12841942 | I50: 827722 | J50: 3085938 | K50: 770616 | L50: 1112196 | M50: 2735366 | N50: 545057 | O50: 1388853 | P50: 1159399 | Q50: 393460 | R50: 223943 | S50: 130419 | T50: 76466 | U50: 110019 | V50: 121420 | W50: 115259 | X50: 45809
D51: Other Operating Income | E51: KSH | F51: =SUM(I51:X51) -> 24733827 | G51: 0 | I51: =7332166-SUM(I47:I50) -> 1942492 | J51: =16411803-SUM(J47:J50) -> 5879008 | K51: =5600011-SUM(K47:K50) -> 1614187 | L51: =6487751-SUM(L47:L50) -> 1645486 | M51: =14354025-SUM(M47:M50) -> 3572329 | N51: =3524659-SUM(N47:N50) -> 801736 | O51: =8265058-SUM(O47:O50) -> 2064263 | P51: =7909592-SUM(P47:P50) -> 2014714 | Q51: =2870725-SUM(Q47:Q50) -> 919883 | R51: =3762194-SUM(R47:R50) -> 798870 | S51: =1814778-SUM(S47:S50) -> 503048 | T51: =1199597-SUM(T47:T50) -> 448719 | U51: =2188571-SUM(U47:U50) -> 789823 | V51: =1307930-SUM(V47:V50) -> 336842 | W51: =3463020-SUM(W47:W50) -> 1060870 | X51: =1560735-SUM(X47:X50) -> 341557
D52: Total other operating income | E52: KSH | F52: =SUM(F47:F51) -> 88052615 | H52: =F52+SUM(G47:G51) -> 88052615 | I52: =SUM(I47:I51) -> 7332166 | J52: =SUM(J47:J51) -> 16411803 | K52: =SUM(K47:K51) -> 5600011 | L52: =SUM(L47:L51) -> 6487751 | M52: =SUM(M47:M51) -> 14354025 | N52: =SUM(N47:N51) -> 3524659 | O52: =SUM(O47:O51) -> 8265058 | P52: =SUM(P47:P51) -> 7909592 | ... X52: =SUM(X47:X51) -> 1560735
D54: Other Income | E54: KSH | F54: 0 | G54: 0
D56: Total Revenue | E56: KSH | F56: =F25+F33+F39+F43+F52+F54 -> 967190810 | G56: =SUM(G6:G54) -> -1 | H56: =F56+G56 -> 967190809 | I56: =I25+I33+I39+I43+I52 -> 149707188 | J56: =J25+J33+J39+J43+J52 -> 215966832 | K56: =K25+K33+K39+K43+K52 -> 38225758 | L56: =L25+L33+L39+L43+L52 -> 51212660 | M56: =M25+M33+M39+M43+M52 -> 105537548 | N56: =N25+N33+N39+N43+N52 -> 49549700 | O56: =O25+O33+O39+O43+O52 -> 97974208 | P56: =P25+P33+P39+P43+P52 -> 58960769 | ... X56: =X25+X33+X39+X43+X52 -> 5663359
D58: Interest on savings | E58: KSH | F58: =SUM(I58:X58) -> -137377401 | I58: -26109213 | J58: -17722816 | K58: -4039941 | L58: -9180277 | M58: -16934340 | N58: -5932370 | O58: -14097436 | P58: -13378596 | Q58: -10076641 | R58: =-9442443 -> -9442443 | S58: -936912 | T58: -2776690 | U58: -1072408 | V58: -1548444 | W58: -3293397 | X58: -835477
D59: Interest on fixed deposits | E59: KSH | F59: =SUM(I59:X59) -> -12745753 | I59: -690380 | J59: -546330 | K59: -283910 | L59: -399292 | M59: -7576524 | N59: -1499315 | O59: -1106457 | P59: -503412 | Q59: -24369 | R59: 0 | S59: 0 | T59: -90000 | U59: -25758 | V59: 0 | W59: 0 | X59: -6
D60: Interest on Diaspora jijenge savings | E60: KSH | F60: =SUM(I60:X60) -> 0 | I60: 0 | J60: 0 | K60: 0 | L60: 0 | M60: 0 | N60: 0 | O60: 0 | P60: 0 | Q60: 0 | R60: 0 | S60: 0 | T60: 0 | U60: 0 | V60: 0 | W60: 0 | X60: 0
D61: Total interest expense on deposits | E61: KSH | F61: =SUM(F58:F60) -> -150123154 | I61: =SUM(I58:I60) -> -26799593 | J61: =SUM(J58:J60) -> -18269146 | K61: =SUM(K58:K60) -> -4323851 | L61: =SUM(L58:L60) -> -9579569 | M61: =SUM(M58:M60) -> -24510864 | N61: =SUM(N58:N60) -> -7431685 | O61: =SUM(O58:O60) -> -15203893 | P61: =SUM(P58:P60) -> -13882008 | ... X61: =SUM(X58:X60) -> -835483
D63: Mobile deposit charges paybill | E63: KSH | F63: =SUM(I63:X63) -> -10588128 | I63: -943307 | J63: -576555 | K63: -121313 | L63: -592677 | M63: -788792 | N63: -666755 | O63: -1191453 | P63: -1601042 | Q63: -684889 | R63: -1618800 | S63: -313593 | T63: -222132 | U63: -369724 | V63: -190693 | W63: -449202 | X63: -257201
D64: loss impairement of financial assets | E64: KSH | F64: =SUM(I64:X64) -> -736927 | I64: 0 | J64: -245642 | K64: -491285 | L64: 0 | M64: 0 | N64: 0 | O64: 0 | P64: 0 | Q64: 0 | R64: 0 | S64: 0 | T64: 0 | U64: 0 | V64: 0 | W64: 0 | X64: 0
D65: Appraisal fee | E65: KSH | F65: =SUM(I65:X65) -> -22700 | I65: 0 | J65: 0 | K65: 0 | L65: 0 | M65: 0 | N65: 0 | O65: 0 | P65: 0 | Q65: 0 | R65: -8000 | S65: -3100 | T65: -5800 | U65: -5800 | V65: 0 | W65: 0 | X65: 0
D66: Other Expenses | E66: KSH | F66: =SUM(I66:X66) -> -671146 | G66: 0 | I66: -140857 | J66: -145605 | K66: -29270 | L66: -81631 | M66: -54857 | N66: -14336 | O66: -80532 | P66: -40117 | Q66: -11102 | R66: -39814 | S66: -5710 | T66: -1490 | U66: -24482 | V66: -1745 | W66: -350 | X66: 752
D67: Total fees and commission expenses | E67: KSH | F67: =SUM(F63:F66) -> -12018901 | H67: =F67+SUM(G63:G66) -> -12018901 | I67: =SUM(I63:I66) -> -1084164 | J67: =SUM(J63:J66) -> -967802 | K67: =SUM(K63:K66) -> -641868 | L67: =SUM(L63:L66) -> -674308 | M67: =SUM(M63:M66) -> -843649 | N67: =SUM(N63:N66) -> -681091 | O67: =SUM(O63:O66) -> -1271985 | P67: =SUM(P63:P66) -> -1641159 | ... X67: =SUM(X63:X66) -> -256449
D69: Other Expenses | E69: KSH | F69: =SUM(I69:X69) -> 0 | I69: 0 | J69: 0 | K69: 0 | L69: 0 | M69: 0 | N69: 0 | O69: 0 | P69: 0 | Q69: 0 | R69: 0 | S69: 0 | T69: 0 | U69: 0 | V69: 0 | W69: 0 | X69: 0
D71: Total Provision for Loan Losses | E71: KSH | F71: =SUM(I71:X71) -> -117296332 | G71: 0 | H71: =F71+G71 -> -117296332 | I71: -9217893 | J71: -12234267 | K71: 1559261 | L71: -2299543 | M71: -16725031 | N71: -2238274 | O71: -4557331 | P71: -5793784 | Q71: -13593539 | R71: -28952929 | S71: -14456798 | T71: -1161513 | U71: -3587690 | V71: -1220701 | W71: -2622874 | X71: -193426
D73: Staff salaries | E73: KSH | F73: =SUM(I73:X73) -> -93418728 | I73: -7070359 | J73: -8975542 | K73: -5755374 | L73: -7787200 | M73: -11428336 | N73: -5758966 | O73: -8356989 | P73: -7285498 | Q73: -5315499 | R73: -6474099 | S73: -3325364 | T73: -3320954 | U73: -2852852 | V73: -3172203 | W73: -3780032 | X73: -2759461
D74: House alowance | E74: KSH | F74: =SUM(I74:X74) -> -21733528 | I74: =-1652599 -> -1652599 | J74: -2069894 | K74: -1378847 | L74: -1882810 | M74: -2733098 | N74: -1375752 | O74: -1961252 | P74: -1697384 | Q74: -1204882 | R74: -1499530 | S74: -706014 | T74: -725444 | U74: -604421 | V74: -758055 | W74: -882137 | X74: -601409
D75: Other personnel expenses | E75: KSH | F75: =SUM(I75:X75) -> -51537083 | I75: =-12014095-SUM(I73:I74) -> -3291137 | J75: =-15313356-SUM(J73:J74) -> -4267920 | K75: =-9750455-SUM(K73:K74) -> -2616234 | L75: =-14198460-SUM(L73:L74) -> -4528450 | M75: =-19196737-SUM(M73:M74) -> -5035303 | N75: =-11341406-SUM(N73:N74) -> -4206688 | O75: =-14612557-SUM(O73:O74) -> -4294316 | P75: =-12364061-SUM(P73:P74) -> -3381179 | Q75: =-9152717-SUM(Q73:Q74) -> -2632336 | R75: =-12077289-SUM(R73:R74) -> -4103660 | S75: =-6823213-SUM(S73:S74) -> -2791835 | T75: =-6077350-SUM(T73:T74) -> -2030952 | U75: =-5144978-SUM(U73:U74) -> -1687705 | V75: =-5624796-SUM(V73:V74) -> -1694538 | W75: =-7610518-SUM(W73:W74) -> -2948349 | X75: =-5387351-SUM(X73:X74) -> -2026481
D76: Total personnel expenses | E76: KSH | F76: =SUM(F73:F75) -> -166689339 | G76: =H76-F76 -> 0 | H76: =F76 -> -166689339 | I76: =SUM(I73:I75) -> -12014095 | J76: =SUM(J73:J75) -> -15313356 | K76: =SUM(K73:K75) -> -9750455 | L76: =SUM(L73:L75) -> -14198460 | M76: =SUM(M73:M75) -> -19196737 | N76: =SUM(N73:N75) -> -11341406 | O76: =SUM(O73:O75) -> -14612557 | P76: =SUM(P73:P75) -> -12364061 | ... X76: =SUM(X73:X75) -> -5387351
D78: Total governance Expenses | E78: KSH | F78: =SUM(I78:X78) -> -56550927 | G78: 0 | H78: =F78+G78 -> -56550927 | I78: -5086634 | J78: -11846974 | K78: -2825915 | L78: -6217021 | M78: -13564396 | N78: -3969950 | O78: -5621639 | P78: -3956281 | Q78: -2260726 | R78: -568205 | S78: -583186 | T78: -34000 | U78: 0 | V78: -16000 | W78: 0 | X78: 0
D80: Total Marketing Expenses | E80: KSH | F80: =SUM(I80:X80) -> -1717399 | G80: 0 | H80: =F80+G80 -> -1717399 | I80: -163638 | J80: -202825 | K80: -104950 | L80: -111500 | M80: -20182 | N80: -104460 | O80: -168680 | P80: -36200 | Q80: -161875 | R80: -62232 | S80: -175100 | T80: -108856 | U80: -90237 | V80: -100116 | W80: -3100 | X80: -103448
D82: Total Depreciation and amortization | E82: KSH | F82: =SUM(I82:X82) -> -2564321 | G82: 0 | H82: =F82+G82 -> -2564321 | I82: -152212 | J82: -147396 | K82: -116509 | L82: -102592 | M82: -225679 | N82: -212035 | O82: -85387 | P82: -185313 | Q82: -200445 | R82: -243088 | S82: -205169 | T82: -84159 | U82: -62479 | V82: -208818 | W82: -230024 | X82: -103016
D84: Security | E84: KSH | F84: =SUM(I84:X84) -> -27077015 | G84: 0 | I84: -1762280 | J84: -1842034 | K84: -1741720 | L84: -1770165 | M84: -1940753 | N84: -1847320 | O84: -1758280 | P84: -1827060 | Q84: -1797543 | R84: -1878588 | S84: -1622720 | T84: -1572164 | U84: -1284800 | V84: -1563920 | W84: -1602886 | X84: -1264782
D85: Other Admin Expenses | E85: KSH | F85: =SUM(I85:X85) -> -58548388 | G85: 0 | I85: =-6304866-I84 -> -4542586 | J85: =-6518135-J84 -> -4676101 | K85: =-4647559-K84 -> -2905839 | L85: =-4880233-L84 -> -3110068 | M85: =-7021110-M84 -> -5080357 | N85: =-5525362-N84 -> -3678042 | O85: =-5566822-O84 -> -3808542 | P85: =-5204181-P84 -> -3377121 | Q85: =-7579424-Q84 -> -5781881 | R85: =-9287257-R84 -> -7408669 | S85: =-4303130-S84 -> -2680410 | T85: =-5166926-T84 -> -3594762 | U85: =-3362998-U84 -> -2078198 | V85: =-2914941-V84 -> -1351021 | W85: =-3974191-W84 -> -2371305 | X85: =-3368268-X84 -> -2103486
D86: Total Admin expenses | E86: KSH | F86: =SUM(F84:F85) -> -85625403 | H86: =F86+SUM(G84:G85) -> -85625403 | I86: =SUM(I84:I85) -> -6304866 | J86: =SUM(J84:J85) -> -6518135 | K86: =SUM(K84:K85) -> -4647559 | L86: =SUM(L84:L85) -> -4880233 | M86: =SUM(M84:M85) -> -7021110 | N86: =SUM(N84:N85) -> -5525362 | O86: =SUM(O84:O85) -> -5566822 | P86: =SUM(P84:P85) -> -5204181 | ... X86: =SUM(X84:X85) -> -3368268
D88: Total Expenses | E88: KSH | F88: =F61+F67+F69+F71+F76+F78+F80+F82+F86 -> -592585776 | G88: =SUM(G58:G86) -> 0 | H88: =F88+G88 -> -592585776 | I88: =I61+I67+I69+I71+I76+I78+I80+I82+I86 -> -60823095 | J88: =J61+J67+J69+J71+J76+J78+J80+J82+J86 -> -65499901 | K88: =K61+K67+K69+K71+K76+K78+K80+K82+K86 -> -20851846 | L88: =L61+L67+L69+L71+L76+L78+L80+L82+L86 -> -38063226 | M88: =M61+M67+M69+M71+M76+M78+M80+M82+M86 -> -82107648 | N88: =N61+N67+N69+N71+N76+N78+N80+N82+N86 -> -31504263 | O88: =O61+O67+O69+O71+O76+O78+O80+O82+O86 -> -47088294 | P88: =P61+P67+P69+P71+P76+P78+P80+P82+P86 -> -43062987 | ... X88: =X61+X67+X69+X71+X76+X78+X80+X82+X86 -> -10247441
D90: Banking Operating Profit | E90: KSH | F90: =F56+F88 -> 374605034 | G90: =G56+G88 -> -1 | I90: =I56+I88 -> 88884093 | J90: =J56+J88 -> 150466931 | K90: =K56+K88 -> 17373912 | L90: =L56+L88 -> 13149434 | M90: =M56+M88 -> 23429900 | N90: =N56+N88 -> 18045437 | O90: =O56+O88 -> 50885914 | P90: =P56+P88 -> 15897782 | ... X90: =X56+X88 -> -4584082
D93: ='2025 Data'!D92 -> Contribution % or share of total
D95: =D6 -> Interest on short term loan me | E95: ='2025 Data'!E94 -> % of Totals | F95: =F6/$F6 -> 1 | I95: =I6/$F6 -> 0.029756981 | J95: =J6/$F6 -> 0.27190167 | K95: =K6/$F6 -> 0.06445323 | L95: =L6/$F6 -> 0.050435072 | M95: =M6/$F6 -> 0.11798605 | N95: =N6/$F6 -> 0.015107389 | O95: =O6/$F6 -> 0.04635117 | P95: =P6/$F6 -> 0.042830527 | ... X95: =X6/$F6 -> 0.0013563773
D96: =D7 -> Interest on short term loan Cu | E96: ='2025 Data'!E95 -> % of Totals | F96: =F7/$F7 -> 1 | I96: =I7/$F7 -> 0.096260997 | J96: =J7/$F7 -> 0.089776689 | K96: =K7/$F7 -> 0.02957978 | L96: =L7/$F7 -> 0.092562146 | M96: =M7/$F7 -> 0.10182393 | N96: =N7/$F7 -> 0.082325747 | O96: =O7/$F7 -> 0.083661022 | P96: =P7/$F7 -> 0.10325287 | ... X96: =X7/$F7 -> 0.015769374
D97: =D8 -> Interest on medium term loan m | E97: ='2025 Data'!E96 -> % of Totals | F97: =F8/$F8 -> 1 | I97: =I8/$F8 -> 0.072418105 | J97: =J8/$F8 -> 0.43907008 | K97: =K8/$F8 -> 0.048055878 | L97: =L8/$F8 -> 0.028009365 | M97: =M8/$F8 -> 0.19139826 | N97: =N8/$F8 -> 0.011325715 | O97: =O8/$F8 -> 0.063148536 | P97: =P8/$F8 -> 0.10100861 | ... X97: =X8/$F8 -> 0
D98: =D9 -> Interest on medium term loan C | E98: ='2025 Data'!E97 -> % of Totals | F98: =F9/$F9 -> 1 | I98: =I9/$F9 -> 0.15462807 | J98: =J9/$F9 -> 0.18396141 | K98: =K9/$F9 -> 0.012603371 | L98: =L9/$F9 -> 0.058086005 | M98: =M9/$F9 -> 0.079082571 | N98: =N9/$F9 -> 0.094129443 | O98: =O9/$F9 -> 0.13199504 | P98: =P9/$F9 -> 0.036811477 | ... X98: =X9/$F9 -> 0.0029453599
D99: =D10 -> Interest on staff loan | E99: ='2025 Data'!E98 -> % of Totals | F99: =F10/$F10 -> 1 | I99: =I10/$F10 -> 1 | J99: =J10/$F10 -> 0 | K99: =K10/$F10 -> 0 | L99: =L10/$F10 -> 0 | M99: =M10/$F10 -> 0 | N99: =N10/$F10 -> 0 | O99: =O10/$F10 -> 0 | P99: =P10/$F10 -> 0 | ... X99: =X10/$F10 -> 0
D100: =D11 -> Interest on development loan soc | E100: ='2025 Data'!E99 -> % of Totals | F100: =F11/$F11 -> 1 | I100: =I11/$F11 -> 0.33325407 | J100: =J11/$F11 -> 0 | K100: =K11/$F11 -> 0.0019370796 | L100: =L11/$F11 -> 0.14227632 | M100: =M11/$F11 -> 0 | N100: =N11/$F11 -> 0 | O100: =O11/$F11 -> 0.15084363 | P100: =P11/$F11 -> 0 | ... X100: =X11/$F11 -> 0
D101: =D12 -> Interest on overdraft members + society | E101: ='2025 Data'!E100 -> % of Totals | F101: =F12/$F12 -> 1 | I101: =I12/$F12 -> 0.21051268 | J101: =J12/$F12 -> 0.021742874 | K101: =K12/$F12 -> 9.570047e-05 | L101: =L12/$F12 -> 0.037370667 | M101: =M12/$F12 -> 0.080824603 | N101: =N12/$F12 -> 0.0069926332 | O101: =O12/$F12 -> 0.23865732 | P101: =P12/$F12 -> 0.0023167795 | ... X101: =X12/$F12 -> 0.0013625001
D102: =D13 -> Interest on Overdue loan | E102: ='2025 Data'!E101 -> % of Totals | F102: =F13/$F13 -> 1 | I102: =I13/$F13 -> 0.11349773 | J102: =J13/$F13 -> 0.19601741 | K102: =K13/$F13 -> 0.055232811 | L102: =L13/$F13 -> 0.16084628 | M102: =M13/$F13 -> 0.2657679 | N102: =N13/$F13 -> 0.011362919 | O102: =O13/$F13 -> 0.14326301 | P102: =P13/$F13 -> 0.054011932 | ... X102: =X13/$F13 -> 0
D103: =D14 -> Advance interest (crop + salary + staff + soko + mfi + raw) | E103: ='2025 Data'!E102 -> % of Totals | F103: =F14/$F14 -> 1 | I103: =I14/$F14 -> 0.14690601 | J103: =J14/$F14 -> 0.17750375 | K103: =K14/$F14 -> 0.040037484 | L103: =L14/$F14 -> 0.071797126 | M103: =M14/$F14 -> 0.10718473 | N103: =N14/$F14 -> 0.050089241 | O103: =O14/$F14 -> 0.10104415 | P103: =P14/$F14 -> 0.06640631 | ... X103: =X14/$F14 -> 0.0093551529
D104: =D15 -> Interest on shirika loan | E104: ='2025 Data'!E103 -> % of Totals | F104: =F15/$F15 -> 1 | I104: =I15/$F15 -> 0 | J104: =J15/$F15 -> 0 | K104: =K15/$F15 -> 0.0041181184 | L104: =L15/$F15 -> 0.068555836 | M104: =M15/$F15 -> 0.025832918 | N104: =N15/$F15 -> 0.1909312 | O104: =O15/$F15 -> 0.26581369 | P104: =P15/$F15 -> 0.11824051 | ... X104: =X15/$F15 -> 0.0022703155
D105: =D16 -> Interest on bonus advance loan | E105: ='2025 Data'!E104 -> % of Totals | F105: =F16/$F16 -> 1 | I105: =I16/$F16 -> 0 | J105: =J16/$F16 -> 0.50734204 | K105: =K16/$F16 -> 0.32135223 | L105: =L16/$F16 -> 0.0096477669 | M105: =M16/$F16 -> 0.057182505 | N105: =N16/$F16 -> 0 | O105: =O16/$F16 -> 0 | P105: =P16/$F16 -> 0 | ... X105: =X16/$F16 -> 0
D106: =D17 -> Interest on Premium Financing + penalty interest (raw + loan recovery) | E106: ='2025 Data'!E105 -> % of Totals | F106: =F17/$F17 -> 1 | I106: =I17/$F17 -> 0.16184664 | J106: =J17/$F17 -> 0.12375051 | K106: =K17/$F17 -> 0.032110482 | L106: =L17/$F17 -> 0.081868195 | M106: =M17/$F17 -> 0.069015645 | N106: =N17/$F17 -> 0.034263607 | O106: =O17/$F17 -> 0.11153902 | P106: =P17/$F17 -> 0.057086499 | ... X106: =X17/$F17 -> 0.0041564773
... D110: =D21 -> Interest on Inuka loan | E110: ='2025 Data'!E109 -> % of Totals | F110: =F21/$F21 -> 1 | I110: =I21/$F21 -> 0.048028949 | J110: =J21/$F21 -> 0.44544009 | K110: =K21/$F21 -> 0.10885627 | L110: =L21/$F21 -> 0.062296888 | M110: =M21/$F21 -> 0.11763548 | N110: =N21/$F21 -> 0.016148855 | O110: =O21/$F21 -> 0.029910611 | P110: =P21/$F21 -> 0.07935439 | ... X110: =X21/$F21 -> 0.0087312422
D111: =D22 -> Interest on youthbiz loan | E111: ='2025 Data'!E110 -> % of Totals | F111: 0 | I111: 0 | J111: 0 | K111: 0 | L111: 0 | M111: 0 | N111: 0 | O111: 0 | P111: 0 | Q111: 0 | R111: 0 | S111: 0 | T111: 0 | U111: 0 | V111: 0 | W111: 0 | X111: 0
D112: =D23 -> Interest on Kwamua Biashara | E112: ='2025 Data'!E111 -> % of Totals | F112: =F23/$F23 -> 1 | I112: =I23/$F23 -> 0.15400422 | J112: =J23/$F23 -> 0.031341773 | K112: =K23/$F23 -> 0.007466131 | L112: =L23/$F23 -> 0.20226795 | M112: =M23/$F23 -> 0.018711778 | N112: =N23/$F23 -> 0.056578243 | O112: =O23/$F23 -> 0.21107375 | P112: =P23/$F23 -> 0.037090265 | ... X112: =X23/$F23 -> 0.0091960484
D113: =D24 -> Interest on Uni-Mobiloan | E113: ='2025 Data'!E112 -> % of Totals | F113: =F24/$F24 -> 1 | I113: =I24/$F24 -> 0.23784929 | J113: =J24/$F24 -> 0.10505733 | K113: =K24/$F24 -> 0.030977635 | L113: =L24/$F24 -> 0.045305705 | M113: =M24/$F24 -> 0.067470837 | N113: =N24/$F24 -> 0.033519068 | O113: =O24/$F24 -> 0.092188626 | P113: =P24/$F24 -> 0.047365278 | ... X113: =X24/$F24 -> 0.054680698
D114: =D25 -> Total interest on loan Portfolio | E114: ='2025 Data'!E113 -> % of Totals | F114: =F25/$F25 -> 1 | I114: =I25/$F25 -> 0.18548066 | J114: =J25/$F25 -> 0.18198024 | K114: =K25/$F25 -> 0.032637092 | L114: =L25/$F25 -> 0.055220929 | M114: =M25/$F25 -> 0.088486531 | N114: =N25/$F25 -> 0.055335123 | O114: =O25/$F25 -> 0.10277637 | P114: =P25/$F25 -> 0.061261444 | ... X114: =X25/$F25 -> 0.0050134977
E115: ='2025 Data'!E114 -> 0
D116: =D27 -> Loan Processing fee | E116: ='2025 Data'!E115 -> % of Totals | F116: =F27/$F27 -> 1 | I116: =I27/$F27 -> 0.21132355 | J116: =J27/$F27 -> 0.1515663 | K116: =K27/$F27 -> 0.069594608 | L116: =L27/$F27 -> 0.092589429 | M116: =M27/$F27 -> 0.11978662 | N116: =N27/$F27 -> 0.044212596 | O116: =O27/$F27 -> 0.067540099 | P116: =P27/$F27 -> 0.055061118 | ... X116: =X27/$F27 -> 0.016519663
D117: =D28 -> Other loan recovey inome | E117: ='2025 Data'!E116 -> % of Totals | F117: =F28/$F28 -> 1 | I117: =I28/$F28 -> 0.17641633 | J117: =J28/$F28 -> 0.0021447306 | K117: =K28/$F28 -> 0.10253753 | L117: =L28/$F28 -> 0.34014946 | M117: =M28/$F28 -> 0.013981257 | N117: =N28/$F28 -> 0.091222719 | O117: =O28/$F28 -> 0.041587653 | P117: =P28/$F28 -> 0.040934173 | ... X117: =X28/$F28 -> 0
D118: =D29 -> Ledger fee on loans | E118: ='2025 Data'!E117 -> % of Totals | F118: =F29/$F29 -> 1 | I118: =I29/$F29 -> 0.099705513 | J118: =J29/$F29 -> 0.24559654 | K118: =K29/$F29 -> 0.063085984 | L118: =L29/$F29 -> 0.084438215 | M118: =M29/$F29 -> 0.14158626 | N118: =N29/$F29 -> 0.068224161 | O118: =O29/$F29 -> 0.050639993 | P118: =P29/$F29 -> 0.075203003 | ... X118: =X29/$F29 -> 0.014092276
D119: =D30 -> Ledger fee on MFI loan | E119: ='2025 Data'!E118 -> % of Totals | F119: =F30/$F30 -> 1 | I119: =I30/$F30 -> 0.047651744 | J119: =J30/$F30 -> 0.10010986 | K119: =K30/$F30 -> 0.0059049712 | L119: =L30/$F30 -> 0.11535293 | M119: =M30/$F30 -> 0.042570722 | N119: =N30/$F30 -> 0.060285636 | O119: =O30/$F30 -> 0.34138973 | P119: =P30/$F30 -> 0.22026916 | ... X119: =X30/$F30 -> 0
D120: =D31 -> MFI loan procesing fee | E120: ='2025 Data'!E119 -> % of Totals | F120: =F31/$F31 -> 1 | I120: =I31/$F31 -> 0.032582655 | J120: =J31/$F31 -> 0.040249161 | K120: =K31/$F31 -> 0.0019166267 | L120: =L31/$F31 -> 0.08241495 | M120: =M31/$F31 -> 0.017249641 | N120: =N31/$F31 -> 0.12458074 | O120: =O31/$F31 -> 0.42117873 | P120: =P31/$F31 -> 0.23382846 | ... X120: =X31/$F31 -> 0
D121: =D32 -> MFI other incomes | E121: ='2025 Data'!E120 -> % of Totals | F121: =F32/$F32 -> 1 | I121: =I32/$F32 -> 0.033763967 | J121: =J32/$F32 -> 0.10593767 | K121: =K32/$F32 -> 0.00052088955 | L121: =L32/$F32 -> 0.095712281 | M121: =M32/$F32 -> 0.041586695 | N121: =N32/$F32 -> 0.13437543 | O121: =O32/$F32 -> 0.39121151 | P121: =P32/$F32 -> 0.11448777 | ... X121: =X32/$F32 -> 0.011731747
D122: =D33 -> Total fees and Commision on loan Portfolio | E122: ='2025 Data'!E121 -> % of Totals | F122: =F33/$F33 -> 1 | I122: =I33/$F33 -> 0.11833144 | J122: =J33/$F33 -> 0.20052447 | K122: =K33/$F33 -> 0.058827552 | L122: =L33/$F33 -> 0.098247345 | M122: =M33/$F33 -> 0.12076371 | N122: =N33/$F33 -> 0.064134605 | O122: =O33/$F33 -> 0.089454457 | P122: =P33/$F33 -> 0.086784676 | ... X122: =X33/$F33 -> 0.012480118
E123: ='2025 Data'!E122 -> 0
D124: =D35 -> Interest on treasury bonds | E124: ='2025 Data'!E123 -> % of Totals | F124: =F35/$F35 -> 1 | I124: =I35/$F35 -> 0.10306528 | J124: =J35/$F35 -> 0.26271394 | K124: =K35/$F35 -> 0.11813642 | L124: =L35/$F35 -> 0.060656334 | M124: =M35/$F35 -> 0.037278393 | N124: =N35/$F35 -> 0.14066468 | O124: =O35/$F35 -> 0.13923276 | P124: =P35/$F35 -> 0.084386347 | ... X124: =X35/$F35 -> 0
D125: =D36 -> Discount on infrastructure Bonds | E125: ='2025 Data'!E124 -> % of Totals | F125: =F36/$F36 -> 1 | I125: =I36/$F36 -> 0.048107296 | J125: =J36/$F36 -> 0.15213345 | K125: =K36/$F36 -> 0.047304796 | L125: =L36/$F36 -> 0.11099254 | M125: =M36/$F36 -> 0.10650196 | N125: =N36/$F36 -> 0.053250978 | O125: =O36/$F36 -> 0.35683491 | P125: =P36/$F36 -> 0.063137091 | ... X125: =X36/$F36 -> 0
D126: =D37 -> Interest on corporate Bonds | E126: ='2025 Data'!E125 -> % of Totals | F126: =F37/$F37 -> 1 | I126: =I37/$F37 -> 0 | J126: =J37/$F37 -> 0.12499971 | K126: =K37/$F37 -> 0 | L126: =L37/$F37 -> 0 | M126: =M37/$F37 -> 0.25000058 | N126: =N37/$F37 -> 0.12499971 | O126: =O37/$F37 -> 0.18750014 | P126: =P37/$F37 -> 0.18750014 | ... X126: =X37/$F37 -> 0
...

Sheet 2023 Data
D2: K - Unity Data
D3: 2023 | F3: Totals | G3: Diff | H3: Reported
C5: Income Statements
D6: Interest on short term loan me | E6: KSH | F6: 39201557
D7: Interest on short term loan Cu | E7: KSH | F7: 57246553
D8: Interest on medium term loan m | E8: KSH | F8: 48782578
D9: Interest on medium term loan C | E9: KSH | F9: 194424006
D10: Interest on staff loan | E10: KSH | F10: 18038056
D11: Interest on development loan soc | E11: KSH | F11: 9838194
D12: Interest on overdraft members + society | E12: KSH | F12: =-13448+26752520 -> 26739072
D13: Interest on Overdue loan | E13: KSH | F13: 2437563
D14: Advance interest (crop + salary + staff + soko + mfi + raw) | E14: KSH | F14: =7844762+2528881+0+57760287+1596606 -> 69730536
D15: Interest on shirika loan | E15: KSH | F15: 2727798
D16: Interest on bonus advance loan | E16: KSH | F16: 7995144
D17: Interest on Premium Financing + penalty interest (raw + loan recovery) | E17: KSH | F17: =77465+15641024+25232 -> 15743721
D18: Interest on MFI loan | E18: KSH | F18: 13524540
D19: Interest on Jijenge Loan | E19: KSH | F19: 93513320
D20: Interest on Soko loan | E20: KSH | F20: 0
D21: Interest on Inuka loan | E21: KSH | F21: 19224063
D22: Interest on youthbiz loan | E22: KSH | F22: 0
D23: Interest on Kwamua Biashara | E23: KSH | F23: 0
D24: Interest on Uni-Mobiloan | E24: KSH | F24: 6510025
B25: x | D25: Total interest on loan Portfolio | E25: KSH | F25: =SUM(F6:F24) -> 625676726 | G25: =H25-F25 -> 20109 | H25: 625696835
D27: Loan Processing fee | E27: KSH | F27: 4903000
D28: Other loan recovey inome | E28: KSH | F28: 452356
D29: Ledger fee on loans | E29: KSH | F29: 30568905
D30: Ledger fee on MFI loan | E30: KSH | F30: 3959916
D31: MFI loan procesing fee | E31: KSH | F31: 167120
D32: MFI other incomes | E32: KSH | F32: 370263
B33: x | D33: Total fees and Commision on loan Portfolio | E33: KSH | F33: =SUM(F27:F32) -> 40421560 | H33: 40421560
D35: Interest on treasury bonds | E35: KSH | F35: 12759332
D36: Discount on infrastructure Bonds | E36: KSH | F36: 231170
D37: Interest on corporate Bonds | E37: KSH | F37: =10399992 -> 10399992 | G37: 0
D38: interest on deposits Wealth C | E38: KSH | F38: 12415
D39: Total Government Securities | E39: KSH | F39: =SUM(F35:F38) -> 23402909 | H39: 23402909
D41: Interest on fixed deposit | E41: KSH | F41: 48045587 | G41: 0
B42: x | D42: Interest on call deposit | E42: KSH | F42: 16043890 | G42: 0
D43: Total deposit with bank | E43: KSH | F43: =SUM(F41:F42) -> 64089477 | H43: 64089477
D45: Interest Income From Financial Investment | E45: KSH | F45: =F39+F43 -> 87492386 | H45: =H39+H43 -> 87492386
D47: Salary Processiong Charges | E47: KSH | F47: 11623361
D48: Withdrawal transaction charge | E48: KSH | F48: 26994820
D49: Mobile Banking cash withdrawal and notification charge | E49: KSH | F49: =16226555+1532021 -> 17758576
D50: Ledger fee on charging customers | E50: KSH | F50: =14343910 -> 14343910
D51: Other Operating Income | E51: KSH | F51: =93912901-SUM(F47:F50) -> 23192234 | G51: 0
D52: Total other operating income | E52: KSH | F52: =SUM(F47:F51) -> 93912901 | H52: =F52+SUM(G47:G51) -> 93912901
D54: Other Income | E54: KSH | F54: 0
D56: Total Revenue | E56: KSH | F56: =F25+F33+F39+F43+F52+F54 -> 847503573 | G56: =SUM(G6:G55) -> 20109 | H56: =F56+G56 -> 847523682
D58: Interest on savings | E58: KSH | F58: -117780391
D59: Interest on fixed deposits | E59: KSH | F59: -10015942
D60: Interest on Diaspora jijenge savings | E60: KSH | F60: =SUM(I59:X59) -> 0
D61: Total interest expense on deposits | E61: KSH | F61: =SUM(F58:F60) -> -127796333
D63: Mobile deposit charges paybill | E63: KSH | F63: -17576878
D64: loss impairement of financial assets | E64: KSH | F64: 0
D65: Appraisal fee | E65: KSH | F65: 0
D66: Other Expenses | E66: KSH | F66: =-756858-2320 -> -759178 | G66: 0
D67: Total fees and commission expenses | E67: KSH | F67: =SUM(F63:F66) -> -18336056 | G67: =H67-F67 -> -11 | H67: -18336067
D69: Other Expenses | E69: KSH | F69: 0
D71: Total Provision for Loan Losses | E71: KSH | F71: -130646575 | G71: 0 | H71: =F71+G71 -> -130646575
D73: Staff salaries | E73: KSH | F73: -87948465
D74: House alowance | E74: KSH | F74: -20555655
D75: Other personnel expenses | E75: KSH | F75: =-158166408-SUM(F73:F74) -> -49662288
D76: Total personnel expenses | E76: KSH | F76: =SUM(F73:F75) -> -158166408 | G76: =H76-F76 -> 0 | H76: =F76 -> -158166408
D78: Total governance Expenses | E78: KSH | F78: -43554754 | G78: 0 | H78: =F78+G78 -> -43554754
D80: Total Marketing Expenses | E80: KSH | F80: -2053376 | G80: 0 | H80: =F80+G80 -> -2053376
D82: Total Depreciation and amortization | E82: KSH | F82: =-2995686 -> -2995686 | G82: 0 | H82: =F82+G82 -> -2995686
D84: Security | E84: KSH | F84: -26115116 | G84: 0
D85: Other Admin Expenses | E85: KSH | F85: =-82516161-F84 -> -56401045 | G85: 0
D86: Total Admin expenses | E86: KSH | F86: =SUM(F84:F85) -> -82516161 | H86: =F86+SUM(G84:G85) -> -82516161
D88: Total Expenses | E88: KSH | F88: =F61+F67+F69+F71+F76+F78+F80+F82+F86 -> -566065349 | G88: =SUM(G58:G86) -> -11 | H88: =F88+G88 -> -566065360
D90: Banking Operating Profit | E90: KSH | F90: =F56+F88 -> 281438224
